Workbook
Name Slicer_Decade: #N/A
Name Slicer_Genre: #N/A
Name Slicer_Language: #N/A

Sheet Data_Info
E3: Shape
E4: Rows | F4: Columns | H4: Null values Count
E5: =COUNTA('IMDB Movie Database'!A2:A3727) -> 3726 | F5: =COUNTA('IMDB Movie Database'!A1:R1) -> 18 | H5: Title | I5: Release Date | J5: Color/B&W | K5: Genre | L5: Language | M5: Country | N5: Rating | O5: Lead Actor | P5: Director Name | Q5: Lead Actor FB Likes | R5: Cast FB Likes | S5: Director FB Likes | T5: Movie FB Likes | U5: IMDb Score (1-10) | V5: Total Reviews | W5: Duration (min) | X5: Gross Revenue | Y5: Budget
H6: =COUNTBLANK('IMDB Movie Database'!A2:A3727) -> 0 | I6: =COUNTBLANK('IMDB Movie Database'!B2:B3727) -> 0 | J6: =COUNTBLANK('IMDB Movie Database'!C2:C3727) -> 0 | K6: =COUNTBLANK('IMDB Movie Database'!D2:D3727) -> 0 | L6: =COUNTBLANK('IMDB Movie Database'!E2:E3727) -> 2 | M6: =COUNTBLANK('IMDB Movie Database'!F2:F3727) -> 0 | N6: =COUNTBLANK('IMDB Movie Database'!G2:G3727) -> 49 | O6: =COUNTBLANK('IMDB Movie Database'!H2:H3727) -> 3 | ... Y6: =COUNTBLANK('IMDB Movie Database'!R2:R3727) -> 0
D9: Statistical Measure
D10: Statistical Measure | E10: Title | F10: Release Date | G10: Color/B&W | H10: Genre | I10: Language | J10: Country | K10: Rating | L10: Lead Actor | M10: Director Name | N10: Lead Actor FB Likes | O10: Cast FB Likes | P10: Director FB Likes | Q10: Movie FB Likes | R10: IMDb Score (1-10) | S10: Total Reviews | T10: Duration (min) | U10: Gross Revenue | V10: Budget
D11: count | E11: =COUNTA('IMDB Movie Database'!A2:A3727) -> 3726 | F11: =COUNTA('IMDB Movie Database'!B2:B3727) -> 3726 | G11: =COUNTA('IMDB Movie Database'!C2:C3727) -> 3726 | H11: =COUNTA('IMDB Movie Database'!D2:D3727) -> 3726 | I11: =COUNTA('IMDB Movie Database'!E2:E3727) -> 3724 | J11: =COUNTA('IMDB Movie Database'!F2:F3727) -> 3726 | K11: =COUNTA('IMDB Movie Database'!G2:G3727) -> 3677 | L11: =COUNTA('IMDB Movie Database'!H2:H3727) -> 3723 | ... V11: =COUNTA('IMDB Movie Database'!R2:R3727) -> 3726
D12: Mean | N12: =AVERAGE('IMDB Movie Database'!J2:J3727) -> 7467.9498 | O12: =AVERAGE('IMDB Movie Database'!K2:K3727) -> 11052.391 | P12: =AVERAGE('IMDB Movie Database'!L2:L3727) -> 793.09071 | Q12: =AVERAGE('IMDB Movie Database'!M2:M3727) -> 8621.7246 | R12: =AVERAGE('IMDB Movie Database'!N2:N3727) -> 6.463956 | S12: =AVERAGE('IMDB Movie Database'!O2:O3727) -> 159.89262 | T12: =AVERAGE('IMDB Movie Database'!P2:P3727) -> 109.7745 | U12: =AVERAGE('IMDB Movie Database'!Q2:Q3727) -> 49729300 | V12: =AVERAGE('IMDB Movie Database'!R2:R3727) -> 44357968
D13: std | N13: =_xlfn.STDEV.S('IMDB Movie Database'!J2:J3727) -> 15524.904 | O13: =_xlfn.STDEV.S('IMDB Movie Database'!K2:K3727) -> 18956.09 | P13: =_xlfn.STDEV.S('IMDB Movie Database'!L2:L3727) -> 3054.6348 | Q13: =_xlfn.STDEV.S('IMDB Movie Database'!M2:M3727) -> 20793.501 | R13: =_xlfn.STDEV.S('IMDB Movie Database'!N2:N3727) -> 1.0588444 | S13: =_xlfn.STDEV.S('IMDB Movie Database'!O2:O3727) -> 122.40478 | T13: =_xlfn.STDEV.S('IMDB Movie Database'!P2:P3727) -> 22.846089 | U13: =_xlfn.STDEV.S('IMDB Movie Database'!Q2:Q3727) -> 68173099 | V13: =_xlfn.STDEV.S('IMDB Movie Database'!R2:R3727) -> 2.2682128e+08
D14: min | N14: =MIN('IMDB Movie Database'!J2:J3727) -> 0 | O14: =MIN('IMDB Movie Database'!K2:K3727) -> 0 | P14: =MIN('IMDB Movie Database'!L2:L3727) -> 0 | Q14: =MIN('IMDB Movie Database'!M2:M3727) -> 0 | R14: =MIN('IMDB Movie Database'!N2:N3727) -> 1.6 | S14: =MIN('IMDB Movie Database'!O2:O3727) -> 1 | T14: =MIN('IMDB Movie Database'!P2:P3727) -> 34 | U14: =MIN('IMDB Movie Database'!Q2:Q3727) -> 162 | V14: =MIN('IMDB Movie Database'!R2:R3727) -> 218
D15: max | N15: =MAX('IMDB Movie Database'!J2:J3727) -> 640000 | O15: =MAX('IMDB Movie Database'!K2:K3727) -> 656730 | P15: =MAX('IMDB Movie Database'!L2:L3727) -> 23000 | Q15: =MAX('IMDB Movie Database'!M2:M3727) -> 349000 | R15: =MAX('IMDB Movie Database'!N2:N3727) -> 9.3 | S15: =MAX('IMDB Movie Database'!O2:O3727) -> 813 | T15: =MAX('IMDB Movie Database'!P2:P3727) -> 330 | U15: =MAX('IMDB Movie Database'!Q2:Q3727) -> 760505847 | V15: =MAX('IMDB Movie Database'!R2:R3727) -> 12215500000
D16: Unique Count | E16: =COUNTA(_xlfn.UNIQUE('IMDB Movie Database'!A2:A3727)) -> 3726 | G16: =COUNTA(_xlfn.UNIQUE('IMDB Movie Database'!C2:C3727)) -> 2 | H16: =COUNTA(_xlfn.UNIQUE('IMDB Movie Database'!D2:D3727)) -> 17 | I16: =COUNTA(_xlfn.UNIQUE('IMDB Movie Database'!E2:E3727)) -> 39 | J16: =COUNTA(_xlfn.UNIQUE('IMDB Movie Database'!F2:F3727)) -> 46 | K16: =COUNTA(_xlfn.UNIQUE('IMDB Movie Database'!G2:G3727)) -> 13 | L16: =COUNTA(_xlfn.UNIQUE('IMDB Movie Database'!H2:H3727)) -> 1495 | M16: =COUNTA(_xlfn.UNIQUE('IMDB Movie Database'!I2:I3727)) -> 1733 | N16: =COUNTA(_xlfn.UNIQUE('IMDB Movie Database'!J2:J3727)) -> 735 | ... V16: =COUNTA(_xlfn.UNIQUE('IMDB Movie Database'!R2:R3727)) -> 370

Sheet IMDB Movie Database
A1: Title | B1: Release Date | C1: Color/B&W | D1: Genre | E1: Language | F1: Country | G1: Rating | H1: Lead Actor | I1: Director Name | J1: Lead Actor FB Likes | K1: Cast FB Likes | L1: Director FB Likes | M1: Movie FB Likes | N1: IMDb Score (1-10) | O1: Total Reviews | P1: Duration (min) | Q1: Gross Revenue | R1: Budget
A2: Anchorman: The Legend of Ron Burgundy | B2: 38129 | C2: Color | D2: Comedy | E2: English | F2: USA | G2: PG-13 | H2: Darcy Donavan | I2: Adam McKay | J2: 640000 | K2: 656730 | L2: 285 | M2: 0 | N2: 7.2 | O2: 181 | P2: 98 | Q2: 84136909 | R2: 26000000
A3: Hardflip | B3: 41138 | C3: Color | D3: Action | E3: English | F3: USA | G3: PG-13 | H3: Matthew Ziff | I3: Johnny Remo | J3: 260000 | K3: 263584 | L3: 74 | M3: 706 | N3: 5.6 | O3: 2 | P3: 112 | Q3: 96734 | R3: 1000000 | T3: =COUNTBLANK(A2:R3726) -> 55
A4: The Final Destination | B4: 40064 | C4: Color | D4: Horror | E4: English | F4: USA | G4: R | H4: Krista Allen | I4: David R. Ellis | J4: 164000 | K4: 303717 | L4: 160 | M4: 0 | N4: 5.2 | O4: 221 | P4: 82 | Q4: 66466372 | R4: 40000000
A5: Quarantine | B5: 39762 | C5: Color | D5: Horror | E5: English | F5: USA | G5: R | H5: Andrew Fiscella | I5: John Erick Dowdle | J5: 137000 | K5: 140268 | L5: 66 | M5: 0 | N5: 6 | O5: 198 | P5: 89 | Q5: 31691811 | R5: 12000000 | U5: =CORREL(IMDB[IMDb Score (1-10)],IMDB[Lead Actor FB Likes]) -> 0.091218506
A6: Armored | B6: 39838 | C6: Color | D6: Action | E6: English | F6: USA | G6: PG-13 | H6: Andrew Fiscella | I6: NimrÃ³d Antal | J6: 137000 | K6: 137712 | L6: 190 | M6: 0 | N6: 5.7 | O6: 107 | P6: 88 | Q6: 15988876 | R6: 27000000
A7: Evan Almighty | B7: 39424 | C7: Color | D7: Comedy | E7: English | F7: USA | G7: PG | H7: Jimmy Bennett | I7: Tom Shadyac | J7: 87000 | K7: 108016 | L7: 293 | M7: 2000 | N7: 5.4 | O7: 186 | P7: 96 | Q7: 100289690 | R7: 175000000
A8: The Amityville Horror | B8: 38591 | C8: Color | D8: Drama | E8: English | F8: USA | G8: R | H8: Jimmy Bennett | I8: Andrew Douglas | J8: 87000 | K8: 120797 | L8: 15 | M8: 0 | N8: 6 | O8: 220 | P8: 90 | Q8: 64255243 | R8: 19000000
A9: Poseidon | B9: 38786 | C9: Color | D9: Action | E9: English | F9: USA | G9: PG-13 | H9: Jimmy Bennett | I9: Wolfgang Petersen | J9: 87000 | K9: 92456 | L9: 249 | M9: 0 | N9: 5.6 | O9: 231 | P9: 98 | Q9: 60655503 | R9: 160000000
A10: Firewall | B10: 39027 | C10: Color | D10: Crime | E10: English | F10: USA | G10: PG-13 | H10: Jimmy Bennett | I10: Richard Loncraine | J10: 87000 | K10: 101383 | L10: 12 | M10: 773 | N10: 5.8 | O10: 171 | P10: 105 | Q10: 48745150 | R10: 50000000
A11: Hostage | B11: 38678 | C11: Color | D11: Action | E11: English | F11: USA | G11: R | H11: Jimmy Bennett | I11: Florent-Emilio Siri | J11: 87000 | K11: 103354 | L11: 17 | M11: 0 | N11: 6.6 | O11: 152 | P11: 113 | Q11: 34636443 | R11: 52000000
A12: Shorts | B12: 39919 | C12: Color | D12: Comedy | E12: English | F12: USA | G12: PG | H12: Jimmy Bennett | I12: Robert Rodriguez | J12: 87000 | K12: 88422 | L12: 0 | M12: 431 | N12: 4.9 | O12: 103 | P12: 89 | Q12: 20916309 | R12: 40000000
A13: Trucker | B13: 39619 | C13: Color | D13: Drama | E13: English | F13: USA | G13: R | H13: Jimmy Bennett | I13: James Mottern | J13: 87000 | K13: 89263 | L13: 7 | M13: 371 | N13: 6.7 | O13: 46 | P13: 90 | Q13: 52166 | R13: 2000000
A14: The Grace Card | B14: 40498 | C14: Color | D14: Drama | E14: English | F14: USA | G14: PG-13 | H14: Michael Joiner | I14: David G. Evans | J14: 77000 | K14: 77046 | L14: 0 | M14: 0 | N14: 6.4 | O14: 25 | P14: 101 | Q14: 2428241 | R14: 200000 | W14: hours studies | Y14: Marks | AB14: watching hours | AC14: marks
A15: Night at the Museum | B15: 38835 | C15: Color | D15: Action | E15: English | F15: USA | G15: PG | H15: Robin Williams | I15: Shawn Levy | J15: 49000 | K15: 55486 | L15: 189 | M15: 3000 | N15: 6.4 | O15: 179 | P15: 108 | Q15: 250863268 | R15: 110000000 | W15: 1 | Y15: 10 | AB15: 5 | AC15: 10
A16: Mrs. Doubtfire | B16: 34227 | C16: Color | D16: Comedy | E16: English | F16: USA | G16: PG-13 | H16: Robin Williams | I16: Chris Columbus | J16: 49000 | K16: 52201 | L16: 0 | M16: 0 | N16: 6.9 | O16: 57 | P16: 125 | Q16: 219200000 | R16: 25000000 | W16: 2 | Y16: 20 | AB16: 4 | AC16: 20
A17: Aladdin | B17: 33910 | C17: Color | D17: Adventure | E17: English | F17: USA | G17: G | H17: Robin Williams | I17: Ron Clements | J17: 49000 | K17: 52970 | L17: 63 | M17: 0 | N17: 8 | O17: 124 | P17: 90 | Q17: 217350219 | R17: 28000000 | W17: 3 | Y17: 30 | AB17: 3 | AC17: 30
A18: Happy Feet | B18: 38758 | C18: Color | D18: Animation | E18: English | F18: USA | G18: PG | H18: Robin Williams | I18: George Miller | J18: 49000 | K18: 70996 | L18: 750 | M18: 0 | N18: 6.5 | O18: 206 | P18: 108 | Q18: 197992827 | R18: 100000000 | W18: 4 | Y18: 40 | AB18: 2 | AC18: 40
A19: Night at the Museum: Battle of the Smithsonian | B19: 40011 | C19: Color | D19: Adventure | E19: English | F19: USA | G19: PG | H19: Robin Williams | I19: Shawn Levy | J19: 49000 | K19: 54039 | L19: 189 | M19: 2000 | N19: 5.9 | O19: 185 | P19: 105 | Q19: 177243721 | R19: 150000000 | W19: 5 | Y19: 50 | AB19: 1 | AC19: 50
A20: Good Will Hunting | B20: 35562 | C20: Color | D20: Drama | E20: English | F20: USA | G20: R | H20: Robin Williams | I20: Gus Van Sant | J20: 49000 | K20: 63710 | L20: 835 | M20: 31000 | N20: 8.3 | O20: 161 | P20: 126 | Q20: 138339411 | R20: 10000000
A21: Patch Adams | B21: 35803 | C21: Color | D21: Biography | E21: English | F21: USA | G21: PG-13 | H21: Robin Williams | I21: Tom Shadyac | J21: 49000 | K21: 74382 | L21: 293 | M21: 0 | N21: 6.7 | O21: 55 | P21: 115 | Q21: 135014968 | R21: 50000000
A22: Good Morning, Vietnam | B22: 31858 | C22: Color | D22: Biography | E22: English | F22: USA | G22: R | H22: Robin Williams | I22: Barry Levinson | J22: 49000 | K22: 50141 | L22: 272 | M22: 0 | N22: 7.3 | O22: 62 | P22: 121 | Q22: 123922370 | R22: 13000000
A23: Hook | B23: 33368 | C23: Color | D23: Adventure | E23: English | F23: USA | G23: PG | H23: Robin Williams | I23: Steven Spielberg | J23: 49000 | K23: 64259 | L23: 14000 | M23: 13000 | N23: 6.7 | O23: 75 | P23: 142 | Q23: 119654900 | R23: 70000000
A24: Night at the Museum: Secret of the Tomb | B24: 41645 | C24: Color | D24: Adventure | E24: English | F24: USA | G24: PG | H24: Robin Williams | I24: Shawn Levy | J24: 49000 | K24: 53587 | L24: 189 | M24: 11000 | N24: 6.2 | O24: 154 | P24: 98 | Q24: 113733726 | R24: 127000000
A25: Dead Poets Society | B25: 32512 | C25: Color | D25: Comedy | E25: English | F25: USA | G25: PG | H25: Robin Williams | I25: Peter Weir | J25: 49000 | K25: 51609 | L25: 608 | M25: 23000 | N25: 8 | O25: 96 | P25: 128 | Q25: 95860116 | R25: 16400000
A26: Flubber | B26: 35744 | C26: Color | D26: Comedy | E26: English | F26: USA | G26: PG | H26: Robin Williams | I26: Les Mayfield | J26: 49000 | K26: 50005 | L26: 10 | M26: 0 | N26: 5.2 | O26: 53 | P26: 90 | Q26: 92969824 | R26: 80000000
A27: Happy Feet 2 | B27: 40769 | C27: Color | D27: Animation | E27: English | F27: Australia | G27: PG | H27: Robin Williams | I27: George Miller | J27: 49000 | K27: 62644 | L27: 750 | M27: 0 | N27: 5.9 | O27: 156 | P27: 100 | Q27: 63992328 | R27: 135000000
A28: Bicentennial Man | B28: 36164 | C28: Color | D28: Comedy | E28: English | F28: USA | G28: PG | H28: Robin Williams | I28: Chris Columbus | J28: 49000 | K28: 55254 | L28: 0 | M28: 0 | N28: 6.8 | O28: 93 | P28: 132 | Q28: 58220776 | R28: 100000000
A29: What Dreams May Come | B29: 35874 | C29: Color | D29: Drama | E29: English | F29: USA | G29: PG-13 | H29: Robin Williams | I29: Vincent Ward | J29: 49000 | K29: 49631 | L29: 25 | M29: 32000 | N29: 7 | O29: 121 | P29: 113 | Q29: 55350897 | R29: 85000000
A30: Old Dogs | B30: 39941 | C30: Color | D30: Comedy | E30: English | F30: USA | G30: PG | H30: Robin Williams | I30: Walt Becker | J30: 49000 | K30: 53370 | L30: 12 | M30: 0 | N30: 5.4 | O30: 124 | P30: 88 | Q30: 49474048 | R30: 35000000
A31: License to Wed | B31: 39254 | C31: Color | D31: Comedy | E31: English | F31: USA | G31: PG-13 | H31: Robin Williams | I31: Ken Kwapis | J31: 49000 | K31: 52566 | L31: 42 | M31: 913 | N31: 5.3 | O31: 120 | P31: 91 | Q31: 43792641 | R31: 35000000 | AA31: 1
A32: Man of the Year | B32: 38963 | C32: Color | D32: Comedy | E32: English | F32: USA | G32: PG-13 | H32: Robin Williams | I32: Barry Levinson | J32: 49000 | K32: 52571 | L32: 272 | M32: 0 | N32: 6.2 | O32: 111 | P32: 115 | Q32: 37442180 | R32: 20000000 | AA32: 3
A33: August Rush | B33: 39161 | C33: Color | D33: Drama | E33: English | F33: USA | G33: PG | H33: Robin Williams | I33: Kirsten Sheridan | J33: 49000 | K33: 50927 | L33: 59 | M33: 18000 | N33: 7.5 | O33: 148 | P33: 114 | Q33: 31655091 | R33: 30000000 | AA33: 2
A34: One Hour Photo | B34: 37578 | C34: Color | D34: Drama | E34: English | F34: USA | G34: R | H34: Robin Williams | I34: Mark Romanek | J34: 49000 | K34: 52138 | L34: 132 | M34: 0 | N34: 6.8 | O34: 207 | P34: 96 | Q34: 31597131 | R34: 12000000 | AA34: 5
A35: The Big Wedding | B35: 41534 | C35: Color | D35: Comedy | E35: English | F35: USA | G35: R | H35: Robin Williams | I35: Justin Zackham | J35: 49000 | K35: 74181 | L35: 16 | M35: 0 | N35: 5.6 | O35: 133 | P35: 89 | Q35: 21784432 | R35: 35000000 | AA35: 5
A36: Death to Smoochy | B36: 37352 | C36: Color | D36: Comedy | E36: English | F36: UK | G36: R | H36: Robin Williams | I36: Danny DeVito | J36: 49000 | K36: 52885 | L36: 0 | M36: 0 | N36: 6.4 | O36: 105 | P36: 109 | Q36: 8355815 | R36: 55000000 | AA36: 3
A37: The Night Listener | B37: 38728 | C37: Color | D37: Crime | E37: English | F37: USA | G37: R | H37: Robin Williams | I37: Patrick Stettner | J37: 49000 | K37: 50831 | L37: 5 | M37: 576 | N37: 5.9 | O37: 125 | P37: 81 | Q37: 7825820 | R37: 4000000 | AA37: 5
A38: Jakob the Liar | B38: 36228 | C38: Color | D38: Drama | E38: English | F38: France | G38: PG-13 | H38: Robin Williams | I38: Peter Kassovitz | J38: 49000 | K38: 51657 | L38: 0 | M38: 0 | N38: 6.5 | O38: 68 | P38: 120 | Q38: 4956401 | R38: 15000000 | AA38: 5
A39: House of D | B39: 38236 | C39: Color | D39: Comedy | E39: English | F39: USA | G39: PG-13 | H39: Robin Williams | I39: David Duchovny | J39: 49000 | K39: 51441 | L39: 0 | M39: 857 | N39: 7 | O39: 46 | P39: 96 | Q39: 371081 | R39: 6000000 | AA39: 4
A40: Certifiably Jonathan | B40: 39324 | C40: Color | D40: Comedy | E40: English | F40: USA | H40: Robin Williams | I40: James David Pasternak | J40: 49000 | K40: 54484 | L40: 0 | M40: 87 | N40: 6.2 | O40: 17 | P40: 85 | Q40: 7826 | R40: 1200000
A41: The Hateful Eight | B41: 42037 | C41: Color | D41: Crime | E41: English | F41: USA | G41: R | H41: Craig Stark | I41: Quentin Tarantino | J41: 46000 | K41: 49912 | L41: 16000 | M41: 114000 | N41: 7.9 | O41: 596 | P41: 187 | Q41: 54116191 | R41: 44000000
A42: Austin Powers: The Spy Who Shagged Me | B42: 36397 | C42: Color | D42: Action | E42: English | F42: USA | G42: PG-13 | H42: Muse Watson | I42: Jay Roach | J42: 45000 | K42: 47203 | L42: 116 | M42: 0 | N42: 6.6 | O42: 199 | P42: 95 | Q42: 205399422 | R42: 33000000
A43: I Know What You Did Last Summer | B43: 35774 | C43: Color | D43: Horror | E43: English | F43: USA | G43: R | H43: Muse Watson | I43: Jim Gillespie | J43: 45000 | K43: 50284 | L43: 13 | M43: 0 | N43: 5.6 | O43: 140 | P43: 99 | Q43: 72219395 | R43: 17000000
A44: I Still Know What You Did Last Summer | B44: 35959 | C44: Color | D44: Horror | E44: English | F44: USA | G44: R | H44: Muse Watson | I44: Danny Cannon | J44: 45000 | K44: 49847 | L44: 41 | M44: 891 | N44: 4.6 | O44: 125 | P44: 100 | Q44: 39989008 | R44: 24000000
A45: Assassins | B45: 34751 | C45: Black and White | D45: Action | E45: English | F45: France | G45: R | H45: Muse Watson | I45: Richard Donner | J45: 45000 | K45: 58528 | L45: 503 | M45: 0 | N45: 6.3 | O45: 61 | P45: 132 | Q45: 30306268 | R45: 50000000
A46: The Last Exorcism Part II | B46: 41590 | C46: Color | D46: Drama | E46: English | F46: France | G46: PG-13 | H46: Muse Watson | I46: Ed Gass-Donnelly | J46: 45000 | K46: 46868 | L46: 8 | M46: 0 | N46: 4 | O46: 161 | P46: 93 | Q46: 15152879 | R46: 5000000
A47: Oz the Great and Powerful | B47: 41376 | C47: Color | D47: Adventure | E47: English | F47: USA | G47: PG | H47: Tim Holmes | I47: Sam Raimi | J47: 44000 | K47: 73441 | L47: 0 | M47: 60000 | N47: 6.4 | O47: 525 | P47: 130 | Q47: 234903076 | R47: 215000000
A48: Pirates of the Caribbean: Dead Man's Chest | B48: 39081 | C48: Color | D48: Action | E48: English | F48: USA | G48: PG-13 | H48: Johnny Depp | I48: Gore Verbinski | J48: 40000 | K48: 48486 | L48: 563 | M48: 5000 | N48: 7.3 | O48: 313 | P48: 151 | Q48: 423032628 | R48: 225000000
A49: Alice in Wonderland | B49: 40266 | C49: Color | D49: Adventure | E49: English | F49: USA | G49: PG | H49: Johnny Depp | I49: Tim Burton | J49: 40000 | K49: 79957 | L49: 13000 | M49: 24000 | N49: 6.5 | O49: 451 | P49: 108 | Q49: 334185206 | R49: 200000000
A50: Pirates of the Caribbean: At World's End | B50: 39409 | C50: Color | D50: Action | E50: English | F50: USA | G50: PG-13 | H50: Johnny Depp | I50: Gore Verbinski | J50: 40000 | K50: 48350 | L50: 563 | M50: 0 | N50: 7.1 | O50: 302 | P50: 169 | Q50: 309404152 | R50: 300000000
A51: Pirates of the Caribbean: The Curse of the Black Pearl | B51: 37951 | C51: Color | D51: Action | E51: English | F51: USA | G51: PG-13 | H51: Johnny Depp | I51: Gore Verbinski | J51: 40000 | K51: 48184 | L51: 563 | M51: 10000 | N51: 8.1 | O51: 271 | P51: 143 | Q51: 305388685 | R51: 140000000
A52: Pirates of the Caribbean: On Stranger Tides | B52: 40865 | C52: Color | D52: Action | E52: English | F52: USA | G52: PG-13 | H52: Johnny Depp | I52: Rob Marshall | J52: 40000 | K52: 54083 | L52: 252 | M52: 58000 | N52: 6.7 | O52: 448 | P52: 136 | Q52: 241063875 | R52: 250000000
... A330: Synecdoche, New York | B330: 39781 | C330: Color | D330: Comedy | E330: English | F330: USA | G330: R | H330: Philip Seymour Hoffman | I330: Charlie Kaufman | J330: 22000 | K330: 24732 | L330: 0 | M330: 13000 | N330: 7.5 | O330: 245 | P330: 124 | Q330: 3081925 | R330: 21000000
A331: Happiness | B331: 35869 | C331: Color | D331: Comedy | E331: English | F331: USA | H331: Philip Seymour Hoffman | I331: Todd Solondz | J331: 22000 | K331: 36859 | L331: 377 | M331: 0 | N331: 7.8 | O331: 148 | P331: 134 | Q331: 3000000 | R331: 3000000
A332: Stone | B332: 40305 | C332: Color | D332: Drama | E332: English | F332: USA | G332: R | H332: Robert De Niro | I332: John Curran | J332: 22000 | K332: 37766 | L332: 43 | M332: 0 | N332: 5.4 | O332: 138 | P332: 105 | Q332: 1796024 | R332: 22000000
A333: Find Me Guilty | B333: 38952 | C333: Color | D333: Biography | E333: English | F333: Germany | G333: R | H333: Peter Dinklage | I333: Sidney Lumet | J333: 22000 | K333: 37606 | L333: 0 | M333: 0 | N333: 7.1 | O333: 94 | P333: 125 | Q333: 1172769 | R333: 13000000
A334: What Just Happened | B334: 39744 | C334: Color | D334: Comedy | E334: English | F334: USA | G334: R | H334: Robert De Niro | I334: Barry Levinson | J334: 22000 | K334: 71973 | L334: 272 | M334: 845 | N334: 5.7 | O334: 137 | P334: 104 | Q334: 1089365 | R334: 25000000
A335: Owning Mahowny | B335: 37984 | C335: Color | D335: Crime | E335: English | F335: Canada | G335: R | H335: Philip Seymour Hoffman | I335: Richard Kwietniowski | J335: 22000 | K335: 23513 | L335: 23 | M335: 0 | N335: 7.2 | O335: 82 | P335: 104 | Q335: 1011054 | R335: 10000000
A336: Never Again | B336: 37035 | C336: Color | D336: Comedy | E336: English | F336: USA | G336: R | H336: Peter Dinklage | I336: Eric Schaeffer | J336: 22000 | K336: 24382 | L336: 71 | M336: 139 | N336: 6 | O336: 25 | P336: 98 | Q336: 295468 | R336: 500000
A337: Saint John of Las Vegas | B337: 39888 | C337: Color | D337: Comedy | E337: English | F337: USA | G337: R | H337: Peter Dinklage | I337: Hue Rhodes | J337: 22000 | K337: 36885 | L337: 0 | M337: 407 | N337: 5.8 | O337: 45 | P337: 85 | Q337: 100669 | R337: 3800000
A338: Raging Bull | B338: 29430 | C338: Black and White | D338: Biography | E338: English | F338: USA | G338: R | H338: Robert De Niro | I338: Martin Scorsese | J338: 22000 | K338: 23008 | L338: 17000 | M338: 0 | N338: 8.3 | O338: 151 | P338: 121 | Q338: 45250 | R338: 18000000
A339: The Bridge of San Luis Rey | B339: 38241 | C339: Color | D339: Drama | E339: English | F339: UK | G339: PG | H339: Robert De Niro | I339: Mary McGuckian | J339: 22000 | K339: 23769 | L339: 6 | M339: 181 | N339: 5.1 | O339: 16 | P339: 120 | Q339: 42880 | R339: 24000000
A340: Mean Streets | B340: 26967 | C340: Color | D340: Crime | E340: English | F340: USA | G340: R | H340: Robert De Niro | I340: Martin Scorsese | J340: 22000 | K340: 23737 | L340: 17000 | M340: 0 | N340: 7.4 | O340: 112 | P340: 112 | Q340: 32645 | R340: 500000
A341: Iron Man 3 | B341: 41385 | C341: Color | D341: Action | E341: English | F341: USA | G341: PG-13 | H341: Robert Downey Jr. | I341: Shane Black | J341: 21000 | K341: 30426 | L341: 1000 | M341: 95000 | N341: 7.2 | O341: 608 | P341: 195 | Q341: 408992272 | R341: 200000000
A342: Iron Man | B342: 39622 | C342: Color | D342: Action | E342: English | F342: USA | G342: PG-13 | H342: Robert Downey Jr. | I342: Jon Favreau | J342: 21000 | K342: 39252 | L342: 4000 | M342: 10000 | N342: 7.9 | O342: 486 | P342: 126 | Q342: 318298180 | R342: 140000000
A343: Iron Man 2 | B343: 40180 | C343: Color | D343: Action | E343: English | F343: USA | G343: PG-13 | H343: Robert Downey Jr. | I343: Jon Favreau | J343: 21000 | K343: 48638 | L343: 4000 | M343: 18000 | N343: 7 | O343: 453 | P343: 124 | Q343: 312057433 | R343: 200000000
... A1300: The Yards | B1300: 36530 | C1300: Color | D1300: Crime | E1300: English | F1300: USA | G1300: R | H1300: Charlize Theron | I1300: James Gray | J1300: 9000 | K1300: 11433 | L1300: 115 | M1300: 401 | N1300: 6.4 | O1300: 93 | P1300: 115 | Q1300: 882710 | R1300: 24000000
A1301: Pink Ribbons, Inc. | B1301: 40828 | C1301: Color | D1301: Documentary | E1301: English | F1301: Canada | G1301: Not Rated | I1301: LÃ©a Pool | J1301: 8621 | K1301: 0 | L1301: 4 | M1301: 5000 | N1301: 7.4 | O1301: 23 | P1301: 97 | Q1301: 24784 | R1301: 1200000
A1302: Ayurveda: Art of Being | B1302: 37138 | C1302: Color | D1302: Documentary | E1302: English | F1302: India | I1302: Pan Nalin | J1302: 8621 | K1302: 0 | L1302: 95 | M1302: 379 | N1302: 7.6 | O1302: 15 | P1302: 102 | Q1302: 16892 | R1302: 300000
A1303: The Harvest/La Cosecha | B1303: 40624 | C1303: Color | D1303: Documentary | E1303: English | F1303: USA | I1303: U. Roberto Romano | J1303: 8621 | K1303: 0 | L1303: 6 | M1303: 88 | N1303: 7.2 | O1303: 3 | P1303: 80 | Q1303: 2245 | R1303: 560000
A1304: Pretty Woman | B1304: 33103 | C1304: Color | D1304: Comedy | E1304: English | F1304: USA | G1304: R | H1304: Julia Roberts | I1304: Garry Marshall | J1304: 8000 | K1304: 11135 | L1304: 0 | M1304: 11000 | N1304: 6.9 | O1304: 82 | P1304: 125 | Q1304: 178406268 | R1304: 14000000
A1305: Runaway Bride | B1305: 36177 | C1305: Color | D1305: Comedy | E1305: English | F1305: USA | G1305: PG | H1305: Julia Roberts | I1305: Garry Marshall | J1305: 8000 | K1305: 12790 | L1305: 0 | M1305: 0 | N1305: 5.5 | O1305: 103 | P1305: 116 | Q1305: 152149590 | R1305: 70000000
A1306: Daddy's Home | B1306: 42146 | C1306: Color | D1306: Comedy | E1306: English | F1306: USA | G1306: PG-13 | H1306: Will Ferrell | I1306: Sean Anders | J1306: 8000 | K1306: 10886 | L1306: 51 | M1306: 13000 | N1306: 6.1 | O1306: 145 | P1306: 96 | Q1306: 150315155 | R1306: 50000000
A1307: Talladega Nights: The Ballad of Ricky Bobby | B1307: 38902 | C1307: Color | D1307: Action | E1307: English | F1307: USA | G1307: PG-13 | H1307: Will Ferrell | I1307: Adam McKay | J1307: 8000 | K1307: 12410 | L1307: 285 | M1307: 0 | N1307: 6.6 | O1307: 164 | P1307: 122 | Q1307: 148213377 | R1307: 73000000
A1308: My Best Friend's Wedding | B1308: 35728 | C1308: Color | D1308: Comedy | E1308: English | F1308: USA | G1308: PG-13 | H1308: Julia Roberts | I1308: P.J. Hogan | J1308: 8000 | K1308: 12344 | L1308: 29 | M1308: 0 | N1308: 6.3 | O1308: 84 | P1308: 105 | Q1308: 126805112 | R1308: 46000000
A1309: Erin Brockovich | B1309: 36810 | C1309: Color | D1309: Biography | E1309: English | F1309: USA | G1309: R | H1309: Julia Roberts | I1309: Steven Soderbergh | J1309: 8000 | K1309: 10003 | L1309: 0 | M1309: 0 | N1309: 7.3 | O1309: 169 | P1309: 131 | Q1309: 125548685 | R1309: 52000000
A1310: The Fault in Our Stars | B1310: 41863 | C1310: Color | D1310: Drama | E1310: English | F1310: USA | G1310: PG-13 | H1310: Shailene Woodley | I1310: Josh Boone | J1310: 8000 | K1310: 10565 | L1310: 131 | M1310: 93000 | N1310: 7.8 | O1310: 326 | P1310: 133 | Q1310: 124868837 | R1310: 12000000
A1311: Blades of Glory | B1311: 39162 | C1311: Color | D1311: Comedy | E1311: English | F1311: USA | G1311: PG-13 | H1311: Will Ferrell | I1311: Josh Gordon | J1311: 8000 | K1311: 13232 | L1311: 8 | M1311: 0 | N1311: 6.3 | O1311: 191 | P1311: 93 | Q1311: 118153533 | R1311: 61000000
A1312: Notting Hill | B1312: 36255 | C1312: Color | D1312: Comedy | E1312: English | F1312: UK | G1312: PG-13 | H1312: Julia Roberts | I1312: Roger Michell | J1312: 8000 | K1312: 9255 | L1312: 50 | M1312: 11000 | N1312: 7 | O1312: 150 | P1312: 124 | Q1312: 116006080 | R1312: 42000000
A1313: Step Brothers | B1313: 39716 | C1313: Color | D1313: Comedy | E1313: English | F1313: USA | G1313: R | H1313: Will Ferrell | I1313: Adam McKay | J1313: 8000 | K1313: 11264 | L1313: 285 | M1313: 0 | N1313: 6.9 | O1313: 173 | P1313: 106 | Q1313: 100468793 | R1313: 65000000
A1314: America's Sweethearts | B1314: 36936 | C1314: Color | D1314: Comedy | E1314: English | F1314: USA | G1314: PG-13 | H1314: Julia Roberts | I1314: Joe Roth | J1314: 8000 | K1314: 9176 | L1314: 148 | M1314: 881 | N1314: 5.7 | O1314: 142 | P1314: 102 | Q1314: 93607673 | R1314: 48000000
A1315: Stepmom | B1315: 36013 | C1315: Color | D1315: Comedy | E1315: English | F1315: USA | G1315: PG-13 | H1315: Julia Roberts | I1315: Chris Columbus | J1315: 8000 | K1315: 9988 | L1315: 0 | M1315: 0 | N1315: 6.7 | O1315: 65 | P1315: 124 | Q1315: 91030827 | R1315: 50000000
... A1346: Jab Tak Hai Jaan | B1346: 41023 | C1346: Color | D1346: Drama | E1346: Hindi | F1346: India | G1346: Not Rated | H1346: Shah Rukh Khan | I1346: Yash Chopra | J1346: 8000 | K1346: 13762 | L1346: 147 | M1346: 12000 | N1346: 6.9 | O1346: 50 | P1346: 176 | Q1346: 3047539 | R1346: 7217600
A1347: Veer-Zaara | B1347: 38180 | C1347: Color | D1347: Drama | E1347: Hindi | F1347: India | H1347: Shah Rukh Khan | I1347: Yash Chopra | J1347: 8000 | K1347: 9984 | L1347: 147 | M1347: 2000 | N1347: 7.9 | O1347: 29 | P1347: 192 | Q1347: 2921738 | R1347: 7000000
A1348: Everything Must Go | B1348: 40300 | C1348: Color | D1348: Comedy | E1348: English | F1348: USA | G1348: R | H1348: Will Ferrell | I1348: Dan Rush | J1348: 8000 | K1348: 10517 | L1348: 7 | M1348: 0 | N1348: 6.4 | O1348: 155 | P1348: 97 | Q1348: 2711210 | R1348: 5000000
A1349: Full Frontal | B1349: 37344 | C1349: Color | D1349: Comedy | E1349: English | F1349: USA | G1349: R | H1349: Julia Roberts | I1349: Steven Soderbergh | J1349: 8000 | K1349: 11327 | L1349: 0 | M1349: 134 | N1349: 4.7 | O1349: 108 | P1349: 101 | Q1349: 2506446 | R1349: 2000000
A1350: The Wendell Baker Story | B1350: 38604 | C1350: Color | D1350: Comedy | E1350: English | F1350: USA | G1350: PG-13 | H1350: Will Ferrell | I1350: Andrew Wilson | J1350: 8000 | K1350: 9608 | L1350: 387 | M1350: 143 | N1350: 5.5 | O1350: 32 | P1350: 99 | Q1350: 127144 | R1350: 8000000
A1351: The Butterfly Effect | B1351: 38347 | C1351: Color | D1351: Sci-Fi | E1351: English | F1351: USA | G1351: R | H1351: Logan Lerman | I1351: Eric Bress | J1351: 8000 | K1351: 12755 | L1351: 19 | M1351: 15000 | N1351: 7.7 | O1351: 185 | P1351: 120 | Q1351: 23947 | R1351: 13000000
A1352: Despicable Me 2 | B1352: 41439 | C1352: Color | D1352: Animation | E1352: English | F1352: USA | G1352: PG | H1352: Steve Carell | I1352: Pierre Coffin | J1352: 7000 | K1352: 11905 | L1352: 275 | M1352: 56000 | N1352: 7.5 | O1352: 306 | P1352: 98 | Q1352: 368049635 | R1352: 76000000
A1353: Minions | B1353: 42220 | C1353: Color | D1353: Action | E1353: English | F1353: USA | G1353: PG | H1353: Steve Carell | I1353: Kyle Balda | J1353: 7000 | K1353: 13616 | L1353: 22 | M1353: 70000 | N1353: 6.4 | O1353: 308 | P1353: 91 | Q1353: 336029560 | R1353: 74000000
A1354: Despicable Me | B1354: 40445 | C1354: Color | D1354: Animation | E1354: English | F1354: USA | G1354: PG | H1354: Steve Carell | I1354: Pierre Coffin | J1354: 7000 | K1354: 11608 | L1354: 275 | M1354: 31000 | N1354: 7.7 | O1354: 304 | P1354: 87 | Q1354: 251501645 | R1354: 69000000
A1355: The 40-Year-Old Virgin | B1355: 38678 | C1355: Color | D1355: Comedy | E1355: English | F1355: USA | G1355: R | H1355: Steve Carell | I1355: Judd Apatow | J1355: 7000 | K1355: 8341 | L1355: 0 | M1355: 0 | N1355: 7.1 | O1355: 217 | P1355: 133 | Q1355: 109243478 | R1355: 26000000
A1356: Little Miss Sunshine | B1356: 38818 | C1356: Color | D1356: Comedy | E1356: English | F1356: USA | G1356: R | H1356: Steve Carell | I1356: Jonathan Dayton | J1356: 7000 | K1356: 7227 | L1356: 36 | M1356: 15000 | N1356: 7.9 | O1356: 270 | P1356: 101 | Q1356: 59889948 | R1356: 8000000
A1357: The Way Way Back | B1357: 41403 | C1357: Color | D1357: Comedy | E1357: English | F1357: USA | G1357: PG-13 | H1357: Steve Carell | I1357: Nat Faxon | J1357: 7000 | K1357: 8375 | L1357: 214 | M1357: 22000 | N1357: 7.4 | O1357: 276 | P1357: 103 | Q1357: 21501098 | R1357: 5000000
A1358: Sleepover | B1358: 38151 | C1358: Color | D1358: Comedy | E1358: English | F1358: USA | G1358: PG | H1358: Steve Carell | I1358: Joe Nussbaum | J1358: 7000 | K1358: 13626 | L1358: 18 | M1358: 0 | N1358: 5.3 | O1358: 52 | P1358: 89 | Q1358: 8070311 | R1358: 10000000
A1359: Seeking a Friend for the End of the World | B1359: 41154 | C1359: Black and White | D1359: Adventure | E1359: English | F1359: USA | G1359: R | H1359: Steve Carell | I1359: Lorene Scafaria | J1359: 7000 | K1359: 7747 | L1359: 63 | M1359: 25000 | N1359: 6.7 | O1359: 265 | P1359: 101 | Q1359: 6619173 | R1359: 10000000
... A1551: Punisher: War Zone | B1551: 39679 | C1551: Color | D1551: Action | E1551: English | F1551: USA | G1551: R | H1551: Julie Benz | I1551: Lexi Alexander | J1551: 3000 | K1551: 6563 | L1551: 189 | M1551: 0 | N1551: 6 | O1551: 151 | P1551: 103 | Q1551: 7948159 | R1551: 35000000
A1552: Kids | B1552: 35043 | C1552: Color | D1552: Drama | E1552: English | F1552: USA | H1552: Rosario Dawson | I1552: Larry Clark | J1552: 3000 | K1552: 3310 | L1552: 184 | M1552: 0 | N1552: 7 | O1552: 71 | P1552: 91 | Q1552: 7417210 | R1552: 1500000
A1553: City Island | B1553: 39933 | C1553: Color | D1553: Comedy | E1553: English | F1553: USA | G1553: PG-13 | H1553: Ezra Miller | I1553: Raymond De Felitta | J1553: 3000 | K1553: 3825 | L1553: 20 | M1553: 0 | N1553: 7.4 | O1553: 149 | P1553: 104 | Q1553: 6670712 | R1553: 6000000
A1554: Gods and Monsters | B1554: 36157 | C1554: Black and White | D1554: Biography | E1554: English | F1554: USA | G1554: R | H1554: Brendan Fraser | I1554: Bill Condon | J1554: 3000 | K1554: 4238 | L1554: 386 | M1554: 0 | N1554: 7.5 | O1554: 127 | P1554: 105 | Q1554: 6390032 | R1554: 3500000
...

Sheet Cleaned_Data_&_Helper_Columns
A1: Title | B1: Release Date | C1: Year | D1: Decade | E1: Color/B&W | F1: Genre | G1: Language | H1: Country | I1: Rating | J1: Lead Actor | K1: Director Name | L1: Lead Actor FB Likes | M1: Cast FB Likes | N1: Director FB Likes | O1: Movie FB Likes | P1: IMDb Score (1-10) | Q1: Total Reviews | R1: Duration (min) | S1: Gross Revenue | T1: Budget | U1: Profit | V1: Hit/Flop | W1: Rating Category | X1: Movie Length Category
A2: Anchorman: The Legend of Ron Burgundy | B2: 38129 | C2: =YEAR(IMDB4[[#This Row],[Release Date]]) -> 2004 | D2: =FLOOR(IMDB4[[#This Row],[Year]],10)&"s" -> 2000s | E2: Color | F2: Comedy | G2: English | H2: USA | I2: PG-13 | J2: Darcy Donavan | K2: Adam McKay | L2: 640000 | M2: 656730 | N2: 285 | O2: 0 | P2: 7.2 | Q2: 181 | R2: 98 | S2: 84136909 | T2: 26000000 | U2: =IMDB4[[#This Row],[Gross Revenue]]-IMDB4[[#This Row],[Budget]] -> 58136909 | V2: =IF(IMDB4[[#This Row],[Profit]]>0,"Hit","Flop") -> Hit | W2: {=_xlfn.IFS(IMDB4[[#This Row],[IMDb Score (1-10)]]>=8,"Excellent",IMDB4[[#This Row],[IMDb Score (1-10)]]>=7,"Good",IMDB4[[#This Row],[IMDb Score (1-10)]]>=5,"Average",TRUE,"Poor")} -> Good | X2: =IF(IMDB4[[#This Row],[Duration (min)]]<90,"Short",IF(IMDB4[[#This Row],[Duration (min)]]<=120,"Medium", "Long")) -> Medium
A3: Hardflip | B3: 41138 | C3: =YEAR(IMDB4[[#This Row],[Release Date]]) -> 2012 | D3: =FLOOR(IMDB4[[#This Row],[Year]],10)&"s" -> 2010s | E3: Color | F3: Action | G3: English | H3: USA | I3: PG-13 | J3: Matthew Ziff | K3: Johnny Remo | L3: 260000 | M3: 263584 | N3: 74 | O3: 706 | P3: 5.6 | Q3: 2 | R3: 112 | S3: 96734 | T3: 1000000 | U3: =IMDB4[[#This Row],[Gross Revenue]]-IMDB4[[#This Row],[Budget]] -> -903266 | V3: =IF(IMDB4[[#This Row],[Profit]]>0,"Hit","Flop") -> Flop | W3: {=_xlfn.IFS(IMDB4[[#This Row],[IMDb Score (1-10)]]>=8,"Excellent",IMDB4[[#This Row],[IMDb Score (1-10)]]>=7,"Good",IMDB4[[#This Row],[IMDb Score (1-10)]]>=5,"Average",TRUE,"Poor")} -> Average | X3: =IF(IMDB4[[#This Row],[Duration (min)]]<90,"Short",IF(IMDB4[[#This Row],[Duration (min)]]<=120,"Medium", "Long")) -> Medium
A4: The Final Destination | B4: 40064 | C4: =YEAR(IMDB4[[#This Row],[Release Date]]) -> 2009 | D4: =FLOOR(IMDB4[[#This Row],[Year]],10)&"s" -> 2000s | E4: Color | F4: Horror | G4: English | H4: USA | I4: R | J4: Krista Allen | K4: David R. Ellis | L4: 164000 | M4: 303717 | N4: 160 | O4: 0 | P4: 5.2 | Q4: 221 | R4: 82 | S4: 66466372 | T4: 40000000 | U4: =IMDB4[[#This Row],[Gross Revenue]]-IMDB4[[#This Row],[Budget]] -> 26466372 | V4: =IF(IMDB4[[#This Row],[Profit]]>0,"Hit","Flop") -> Hit | W4: {=_xlfn.IFS(IMDB4[[#This Row],[IMDb Score (1-10)]]>=8,"Excellent",IMDB4[[#This Row],[IMDb Score (1-10)]]>=7,"Good",IMDB4[[#This Row],[IMDb Score (1-10)]]>=5,"Average",TRUE,"Poor")} -> Average | X4: =IF(IMDB4[[#This Row],[Duration (min)]]<90,"Short",IF(IMDB4[[#This Row],[Duration (min)]]<=120,"Medium", "Long")) -> Short | AA4: Cavite | AB4: Fantasy
A5: Quarantine | B5: 39762 | C5: =YEAR(IMDB4[[#This Row],[Release Date]]) -> 2008 | D5: =FLOOR(IMDB4[[#This Row],[Year]],10)&"s" -> 2000s | E5: Color | F5: Horror | G5: English | H5: USA | I5: R | J5: Andrew Fiscella | K5: John Erick Dowdle | L5: 137000 | M5: 140268 | N5: 66 | O5: 0 | P5: 6 | Q5: 198 | R5: 89 | S5: 31691811 | T5: 12000000 | U5: =IMDB4[[#This Row],[Gross Revenue]]-IMDB4[[#This Row],[Budget]] -> 19691811 | V5: =IF(IMDB4[[#This Row],[Profit]]>0,"Hit","Flop") -> Hit | W5: {=_xlfn.IFS(IMDB4[[#This Row],[IMDb Score (1-10)]]>=8,"Excellent",IMDB4[[#This Row],[IMDb Score (1-10)]]>=7,"Good",IMDB4[[#This Row],[IMDb Score (1-10)]]>=5,"Average",TRUE,"Poor")} -> Average | X5: =IF(IMDB4[[#This Row],[Duration (min)]]<90,"Short",IF(IMDB4[[#This Row],[Duration (min)]]<=120,"Medium", "Long")) -> Short
A6: Armored | B6: 39838 | C6: =YEAR(IMDB4[[#This Row],[Release Date]]) -> 2009 | D6: =FLOOR(IMDB4[[#This Row],[Year]],10)&"s" -> 2000s | E6: Color | F6: Action | G6: English | H6: USA | I6: PG-13 | J6: Andrew Fiscella | K6: NimrÃ³d Antal | L6: 137000 | M6: 137712 | N6: 190 | O6: 0 | P6: 5.7 | Q6: 107 | R6: 88 | S6: 15988876 | T6: 27000000 | U6: =IMDB4[[#This Row],[Gross Revenue]]-IMDB4[[#This Row],[Budget]] -> -11011124 | V6: =IF(IMDB4[[#This Row],[Profit]]>0,"Hit","Flop") -> Flop | W6: {=_xlfn.IFS(IMDB4[[#This Row],[IMDb Score (1-10)]]>=8,"Excellent",IMDB4[[#This Row],[IMDb Score (1-10)]]>=7,"Good",IMDB4[[#This Row],[IMDb Score (1-10)]]>=5,"Average",TRUE,"Poor")} -> Average | X6: =IF(IMDB4[[#This Row],[Duration (min)]]<90,"Short",IF(IMDB4[[#This Row],[Duration (min)]]<=120,"Medium", "Long")) -> Short | AB6: {=_xlfn._xlws.FILTER(IMDB4[#All],IMDB4[[#All],[Title]]=AA4,IMDB4[[#All],[Genre]]=AB4)} -> Cavite | AC6: 38555 | AD6: 2005 | AE6: 2000s | AF6: Color | AG6: Thriller | AH6: English | AI6: Philippines | AJ6: Not Rated | AK6: Ian Gamazon | AL6: Neill Dela Llana | AM6: 0 | AN6: 0 | AO6: 0 | AP6: 74 | AQ6: 6.3 | AR6: 35 | AS6: 80 | AT6: 70071 | AU6: 7000 | AV6: 63071 | AW6: Hit | AX6: Average | AY6: Short
A7: Evan Almighty | B7: 39424 | C7: =YEAR(IMDB4[[#This Row],[Release Date]]) -> 2007 | D7: =FLOOR(IMDB4[[#This Row],[Year]],10)&"s" -> 2000s | E7: Color | F7: Comedy | G7: English | H7: USA | I7: PG | J7: Jimmy Bennett | K7: Tom Shadyac | L7: 87000 | M7: 108016 | N7: 293 | O7: 2000 | P7: 5.4 | Q7: 186 | R7: 96 | S7: 100289690 | T7: 175000000 | U7: =IMDB4[[#This Row],[Gross Revenue]]-IMDB4[[#This Row],[Budget]] -> -74710310 | V7: =IF(IMDB4[[#This Row],[Profit]]>0,"Hit","Flop") -> Flop | W7: {=_xlfn.IFS(IMDB4[[#This Row],[IMDb Score (1-10)]]>=8,"Excellent",IMDB4[[#This Row],[IMDb Score (1-10)]]>=7,"Good",IMDB4[[#This Row],[IMDb Score (1-10)]]>=5,"Average",TRUE,"Poor")} -> Average | X7: =IF(IMDB4[[#This Row],[Duration (min)]]<90,"Short",IF(IMDB4[[#This Row],[Duration (min)]]<=120,"Medium", "Long")) -> Medium
A8: The Amityville Horror | B8: 38591 | C8: =YEAR(IMDB4[[#This Row],[Release Date]]) -> 2005 | D8: =FLOOR(IMDB4[[#This Row],[Year]],10)&"s" -> 2000s | E8: Color | F8: Drama | G8: English | H8: USA | I8: R | J8: Jimmy Bennett | K8: Andrew Douglas | L8: 87000 | M8: 120797 | N8: 15 | O8: 0 | P8: 6 | Q8: 220 | R8: 90 | S8: 64255243 | T8: 19000000 | U8: =IMDB4[[#This Row],[Gross Revenue]]-IMDB4[[#This Row],[Budget]] -> 45255243 | V8: =IF(IMDB4[[#This Row],[Profit]]>0,"Hit","Flop") -> Hit | W8: {=_xlfn.IFS(IMDB4[[#This Row],[IMDb Score (1-10)]]>=8,"Excellent",IMDB4[[#This Row],[IMDb Score (1-10)]]>=7,"Good",IMDB4[[#This Row],[IMDb Score (1-10)]]>=5,"Average",TRUE,"Poor")} -> Average | X8: =IF(IMDB4[[#This Row],[Duration (min)]]<90,"Short",IF(IMDB4[[#This Row],[Duration (min)]]<=120,"Medium", "Long")) -> Medium
A9: Poseidon | B9: 38786 | C9: =YEAR(IMDB4[[#This Row],[Release Date]]) -> 2006 | D9: =FLOOR(IMDB4[[#This Row],[Year]],10)&"s" -> 2000s | E9: Color | F9: Action | G9: English | H9: USA | I9: PG-13 | J9: Jimmy Bennett | K9: Wolfgang Petersen | L9: 87000 | M9: 92456 | N9: 249 | O9: 0 | P9: 5.6 | Q9: 231 | R9: 98 | S9: 60655503 | T9: 160000000 | U9: =IMDB4[[#This Row],[Gross Revenue]]-IMDB4[[#This Row],[Budget]] -> -99344497 | V9: =IF(IMDB4[[#This Row],[Profit]]>0,"Hit","Flop") -> Flop | W9: {=_xlfn.IFS(IMDB4[[#This Row],[IMDb Score (1-10)]]>=8,"Excellent",IMDB4[[#This Row],[IMDb Score (1-10)]]>=7,"Good",IMDB4[[#This Row],[IMDb Score (1-10)]]>=5,"Average",TRUE,"Poor")} -> Average | X9: =IF(IMDB4[[#This Row],[Duration (min)]]<90,"Short",IF(IMDB4[[#This Row],[Duration (min)]]<=120,"Medium", "Long")) -> Medium
A10: Firewall | B10: 39027 | C10: =YEAR(IMDB4[[#This Row],[Release Date]]) -> 2006 | D10: =FLOOR(IMDB4[[#This Row],[Year]],10)&"s" -> 2000s | E10: Color | F10: Crime | G10: English | H10: USA | I10: PG-13 | J10: Jimmy Bennett | K10: Richard Loncraine | L10: 87000 | M10: 101383 | N10: 12 | O10: 773 | P10: 5.8 | Q10: 171 | R10: 105 | S10: 48745150 | T10: 50000000 | U10: =IMDB4[[#This Row],[Gross Revenue]]-IMDB4[[#This Row],[Budget]] -> -1254850 | V10: =IF(IMDB4[[#This Row],[Profit]]>0,"Hit","Flop") -> Flop | W10: {=_xlfn.IFS(IMDB4[[#This Row],[IMDb Score (1-10)]]>=8,"Excellent",IMDB4[[#This Row],[IMDb Score (1-10)]]>=7,"Good",IMDB4[[#This Row],[IMDb Score (1-10)]]>=5,"Average",TRUE,"Poor")} -> Average | X10: =IF(IMDB4[[#This Row],[Duration (min)]]<90,"Short",IF(IMDB4[[#This Row],[Duration (min)]]<=120,"Medium", "Long")) -> Medium | Z10: Rating | AA10: {=_xlfn.UNIQUE(H:H)} -> Country
A11: Hostage | B11: 38678 | C11: =YEAR(IMDB4[[#This Row],[Release Date]]) -> 2005 | D11: =FLOOR(IMDB4[[#This Row],[Year]],10)&"s" -> 2000s | E11: Color | F11: Action | G11: English | H11: USA | I11: R | J11: Jimmy Bennett | K11: Florent-Emilio Siri | L11: 87000 | M11: 103354 | N11: 17 | O11: 0 | P11: 6.6 | Q11: 152 | R11: 113 | S11: 34636443 | T11: 52000000 | U11: =IMDB4[[#This Row],[Gross Revenue]]-IMDB4[[#This Row],[Budget]] -> -17363557 | V11: =IF(IMDB4[[#This Row],[Profit]]>0,"Hit","Flop") -> Flop | W11: {=_xlfn.IFS(IMDB4[[#This Row],[IMDb Score (1-10)]]>=8,"Excellent",IMDB4[[#This Row],[IMDb Score (1-10)]]>=7,"Good",IMDB4[[#This Row],[IMDb Score (1-10)]]>=5,"Average",TRUE,"Poor")} -> Average | X11: =IF(IMDB4[[#This Row],[Duration (min)]]<90,"Short",IF(IMDB4[[#This Row],[Duration (min)]]<=120,"Medium", "Long")) -> Medium | Z11: =W2 -> Good | AA11: USA | AB11: =SUMIFS(U:U,H:H,AA11,W:W,Z11) -> 23714615563 | AE11: =SUMIF(IMDB4[Country],AA11,IMDB4[Profit]) -> 50991982137
A12: Shorts | B12: 39919 | C12: =YEAR(IMDB4[[#This Row],[Release Date]]) -> 2009 | D12: =FLOOR(IMDB4[[#This Row],[Year]],10)&"s" -> 2000s | E12: Color | F12: Comedy | G12: English | H12: USA | I12: PG | J12: Jimmy Bennett | K12: Robert Rodriguez | L12: 87000 | M12: 88422 | N12: 0 | O12: 431 | P12: 4.9 | Q12: 103 | R12: 89 | S12: 20916309 | T12: 40000000 | U12: =IMDB4[[#This Row],[Gross Revenue]]-IMDB4[[#This Row],[Budget]] -> -19083691 | V12: =IF(IMDB4[[#This Row],[Profit]]>0,"Hit","Flop") -> Flop | W12: {=_xlfn.IFS(IMDB4[[#This Row],[IMDb Score (1-10)]]>=8,"Excellent",IMDB4[[#This Row],[IMDb Score (1-10)]]>=7,"Good",IMDB4[[#This Row],[IMDb Score (1-10)]]>=5,"Average",TRUE,"Poor")} -> Poor | X12: =IF(IMDB4[[#This Row],[Duration (min)]]<90,"Short",IF(IMDB4[[#This Row],[Duration (min)]]<=120,"Medium", "Long")) -> Short | Z12: =W3 -> Average | AA12: Australia | AB12: =SUMIFS(U:U,H:H,AA12,W:W,Z12) -> -7042072
A13: Trucker | B13: 39619 | C13: =YEAR(IMDB4[[#This Row],[Release Date]]) -> 2008 | D13: =FLOOR(IMDB4[[#This Row],[Year]],10)&"s" -> 2000s | E13: Color | F13: Drama | G13: English | H13: USA | I13: R | J13: Jimmy Bennett | K13: James Mottern | L13: 87000 | M13: 89263 | N13: 7 | O13: 371 | P13: 6.7 | Q13: 46 | R13: 90 | S13: 52166 | T13: 2000000 | U13: =IMDB4[[#This Row],[Gross Revenue]]-IMDB4[[#This Row],[Budget]] -> -1947834 | V13: =IF(IMDB4[[#This Row],[Profit]]>0,"Hit","Flop") -> Flop | W13: {=_xlfn.IFS(IMDB4[[#This Row],[IMDb Score (1-10)]]>=8,"Excellent",IMDB4[[#This Row],[IMDb Score (1-10)]]>=7,"Good",IMDB4[[#This Row],[IMDb Score (1-10)]]>=5,"Average",TRUE,"Poor")} -> Average | X13: =IF(IMDB4[[#This Row],[Duration (min)]]<90,"Short",IF(IMDB4[[#This Row],[Duration (min)]]<=120,"Medium", "Long")) -> Medium | Z13: =W4 -> Average | AA13: UK | AB13: =SUMIFS(U:U,H:H,AA13,W:W,Z13) -> -999235212
A14: The Grace Card | B14: 40498 | C14: =YEAR(IMDB4[[#This Row],[Release Date]]) -> 2010 | D14: =FLOOR(IMDB4[[#This Row],[Year]],10)&"s" -> 2010s | E14: Color | F14: Drama | G14: English | H14: USA | I14: PG-13 | J14: Michael Joiner | K14: David G. Evans | L14: 77000 | M14: 77046 | N14: 0 | O14: 0 | P14: 6.4 | Q14: 25 | R14: 101 | S14: 2428241 | T14: 200000 | U14: =IMDB4[[#This Row],[Gross Revenue]]-IMDB4[[#This Row],[Budget]] -> 2228241 | V14: =IF(IMDB4[[#This Row],[Profit]]>0,"Hit","Flop") -> Hit | W14: {=_xlfn.IFS(IMDB4[[#This Row],[IMDb Score (1-10)]]>=8,"Excellent",IMDB4[[#This Row],[IMDb Score (1-10)]]>=7,"Good",IMDB4[[#This Row],[IMDb Score (1-10)]]>=5,"Average",TRUE,"Poor")} -> Average | X14: =IF(IMDB4[[#This Row],[Duration (min)]]<90,"Short",IF(IMDB4[[#This Row],[Duration (min)]]<=120,"Medium", "Long")) -> Medium | Z14: =W5 -> Average | AA14: France | AB14: =SUMIFS(U:U,H:H,AA14,W:W,Z14) -> -1031277560
A15: Night at the Museum | B15: 38835 | C15: =YEAR(IMDB4[[#This Row],[Release Date]]) -> 2006 | D15: =FLOOR(IMDB4[[#This Row],[Year]],10)&"s" -> 2000s | E15: Color | F15: Action | G15: English | H15: USA | I15: PG | J15: Robin Williams | K15: Shawn Levy | L15: 49000 | M15: 55486 | N15: 189 | O15: 3000 | P15: 6.4 | Q15: 179 | R15: 108 | S15: 250863268 | T15: 110000000 | U15: =IMDB4[[#This Row],[Gross Revenue]]-IMDB4[[#This Row],[Budget]] -> 140863268 | V15: =IF(IMDB4[[#This Row],[Profit]]>0,"Hit","Flop") -> Hit | W15: {=_xlfn.IFS(IMDB4[[#This Row],[IMDb Score (1-10)]]>=8,"Excellent",IMDB4[[#This Row],[IMDb Score (1-10)]]>=7,"Good",IMDB4[[#This Row],[IMDb Score (1-10)]]>=5,"Average",TRUE,"Poor")} -> Average | X15: =IF(IMDB4[[#This Row],[Duration (min)]]<90,"Short",IF(IMDB4[[#This Row],[Duration (min)]]<=120,"Medium", "Long")) -> Medium | Z15: =W6 -> Average | AA15: Spain | AB15: =SUMIFS(U:U,H:H,AA15,W:W,Z15) -> -133682841
A16: Mrs. Doubtfire | B16: 34227 | C16: =YEAR(IMDB4[[#This Row],[Release Date]]) -> 1993 | D16: =FLOOR(IMDB4[[#This Row],[Year]],10)&"s" -> 1990s | E16: Color | F16: Comedy | G16: English | H16: USA | I16: PG-13 | J16: Robin Williams | K16: Chris Columbus | L16: 49000 | M16: 52201 | N16: 0 | O16: 0 | P16: 6.9 | Q16: 57 | R16: 125 | S16: 219200000 | T16: 25000000 | U16: =IMDB4[[#This Row],[Gross Revenue]]-IMDB4[[#This Row],[Budget]] -> 194200000 | V16: =IF(IMDB4[[#This Row],[Profit]]>0,"Hit","Flop") -> Hit | W16: {=_xlfn.IFS(IMDB4[[#This Row],[IMDb Score (1-10)]]>=8,"Excellent",IMDB4[[#This Row],[IMDb Score (1-10)]]>=7,"Good",IMDB4[[#This Row],[IMDb Score (1-10)]]>=5,"Average",TRUE,"Poor")} -> Average | X16: =IF(IMDB4[[#This Row],[Duration (min)]]<90,"Short",IF(IMDB4[[#This Row],[Duration (min)]]<=120,"Medium", "Long")) -> Long | Z16: =W7 -> Average | AA16: Canada | AB16: =SUMIFS(U:U,H:H,AA16,W:W,Z16) -> 185406739
A17: Aladdin | B17: 33910 | C17: =YEAR(IMDB4[[#This Row],[Release Date]]) -> 1992 | D17: =FLOOR(IMDB4[[#This Row],[Year]],10)&"s" -> 1990s | E17: Color | F17: Adventure | G17: English | H17: USA | I17: G | J17: Robin Williams | K17: Ron Clements | L17: 49000 | M17: 52970 | N17: 63 | O17: 0 | P17: 8 | Q17: 124 | R17: 90 | S17: 217350219 | T17: 28000000 | U17: =IMDB4[[#This Row],[Gross Revenue]]-IMDB4[[#This Row],[Budget]] -> 189350219 | V17: =IF(IMDB4[[#This Row],[Profit]]>0,"Hit","Flop") -> Hit | W17: {=_xlfn.IFS(IMDB4[[#This Row],[IMDb Score (1-10)]]>=8,"Excellent",IMDB4[[#This Row],[IMDb Score (1-10)]]>=7,"Good",IMDB4[[#This Row],[IMDb Score (1-10)]]>=5,"Average",TRUE,"Poor")} -> Excellent | X17: =IF(IMDB4[[#This Row],[Duration (min)]]<90,"Short",IF(IMDB4[[#This Row],[Duration (min)]]<=120,"Medium", "Long")) -> Medium | Z17: =W8 -> Average | AA17: Denmark | AB17: =SUMIFS(U:U,H:H,AA17,W:W,Z17) -> -37699201
A18: Happy Feet | B18: 38758 | C18: =YEAR(IMDB4[[#This Row],[Release Date]]) -> 2006 | D18: =FLOOR(IMDB4[[#This Row],[Year]],10)&"s" -> 2000s | E18: Color | F18: Animation | G18: English | H18: USA | I18: PG | J18: Robin Williams | K18: George Miller | L18: 49000 | M18: 70996 | N18: 750 | O18: 0 | P18: 6.5 | Q18: 206 | R18: 108 | S18: 197992827 | T18: 100000000 | U18: =IMDB4[[#This Row],[Gross Revenue]]-IMDB4[[#This Row],[Budget]] -> 97992827 | V18: =IF(IMDB4[[#This Row],[Profit]]>0,"Hit","Flop") -> Hit | W18: {=_xlfn.IFS(IMDB4[[#This Row],[IMDb Score (1-10)]]>=8,"Excellent",IMDB4[[#This Row],[IMDb Score (1-10)]]>=7,"Good",IMDB4[[#This Row],[IMDb Score (1-10)]]>=5,"Average",TRUE,"Poor")} -> Average | X18: =IF(IMDB4[[#This Row],[Duration (min)]]<90,"Short",IF(IMDB4[[#This Row],[Duration (min)]]<=120,"Medium", "Long")) -> Medium | Z18: =W9 -> Average | AA18: Belgium | AB18: =SUMIFS(U:U,H:H,AA18,W:W,Z18) -> -33995909
A19: Night at the Museum: Battle of the Smithsonian | B19: 40011 | C19: =YEAR(IMDB4[[#This Row],[Release Date]]) -> 2009 | D19: =FLOOR(IMDB4[[#This Row],[Year]],10)&"s" -> 2000s | E19: Color | F19: Adventure | G19: English | H19: USA | I19: PG | J19: Robin Williams | K19: Shawn Levy | L19: 49000 | M19: 54039 | N19: 189 | O19: 2000 | P19: 5.9 | Q19: 185 | R19: 105 | S19: 177243721 | T19: 150000000 | U19: =IMDB4[[#This Row],[Gross Revenue]]-IMDB4[[#This Row],[Budget]] -> 27243721 | V19: =IF(IMDB4[[#This Row],[Profit]]>0,"Hit","Flop") -> Hit | W19: {=_xlfn.IFS(IMDB4[[#This Row],[IMDb Score (1-10)]]>=8,"Excellent",IMDB4[[#This Row],[IMDb Score (1-10)]]>=7,"Good",IMDB4[[#This Row],[IMDb Score (1-10)]]>=5,"Average",TRUE,"Poor")} -> Average | X19: =IF(IMDB4[[#This Row],[Duration (min)]]<90,"Short",IF(IMDB4[[#This Row],[Duration (min)]]<=120,"Medium", "Long")) -> Medium | Z19: =W10 -> Average | AA19: Germany | AB19: =SUMIFS(U:U,H:H,AA19,W:W,Z19) -> -155335898
A20: Good Will Hunting | B20: 35562 | C20: =YEAR(IMDB4[[#This Row],[Release Date]]) -> 1997 | D20: =FLOOR(IMDB4[[#This Row],[Year]],10)&"s" -> 1990s | E20: Color | F20: Drama | G20: English | H20: USA | I20: R | J20: Robin Williams | K20: Gus Van Sant | L20: 49000 | M20: 63710 | N20: 835 | O20: 31000 | P20: 8.3 | Q20: 161 | R20: 126 | S20: 138339411 | T20: 10000000 | U20: =IMDB4[[#This Row],[Gross Revenue]]-IMDB4[[#This Row],[Budget]] -> 128339411 | V20: =IF(IMDB4[[#This Row],[Profit]]>0,"Hit","Flop") -> Hit | W20: {=_xlfn.IFS(IMDB4[[#This Row],[IMDb Score (1-10)]]>=8,"Excellent",IMDB4[[#This Row],[IMDb Score (1-10)]]>=7,"Good",IMDB4[[#This Row],[IMDb Score (1-10)]]>=5,"Average",TRUE,"Poor")} -> Excellent | X20: =IF(IMDB4[[#This Row],[Duration (min)]]<90,"Short",IF(IMDB4[[#This Row],[Duration (min)]]<=120,"Medium", "Long")) -> Long | Z20: =W11 -> Average | AA20: Japan | AB20: =SUMIFS(U:U,H:H,AA20,W:W,Z20) -> -3060904553
A21: Patch Adams | B21: 35803 | C21: =YEAR(IMDB4[[#This Row],[Release Date]]) -> 1998 | D21: =FLOOR(IMDB4[[#This Row],[Year]],10)&"s" -> 1990s | E21: Color | F21: Biography | G21: English | H21: USA | I21: PG-13 | J21: Robin Williams | K21: Tom Shadyac | L21: 49000 | M21: 74382 | N21: 293 | O21: 0 | P21: 6.7 | Q21: 55 | R21: 115 | S21: 135014968 | T21: 50000000 | U21: =IMDB4[[#This Row],[Gross Revenue]]-IMDB4[[#This Row],[Budget]] -> 85014968 | V21: =IF(IMDB4[[#This Row],[Profit]]>0,"Hit","Flop") -> Hit | W21: {=_xlfn.IFS(IMDB4[[#This Row],[IMDb Score (1-10)]]>=8,"Excellent",IMDB4[[#This Row],[IMDb Score (1-10)]]>=7,"Good",IMDB4[[#This Row],[IMDb Score (1-10)]]>=5,"Average",TRUE,"Poor")} -> Average | X21: =IF(IMDB4[[#This Row],[Duration (min)]]<90,"Short",IF(IMDB4[[#This Row],[Duration (min)]]<=120,"Medium", "Long")) -> Medium | Z21: =W12 -> Poor | AA21: Czech Republic | AB21: =SUMIFS(U:U,H:H,AA21,W:W,Z21) -> 0
A22: Good Morning, Vietnam | B22: 31858 | C22: =YEAR(IMDB4[[#This Row],[Release Date]]) -> 1987 | D22: =FLOOR(IMDB4[[#This Row],[Year]],10)&"s" -> 1980s | E22: Color | F22: Biography | G22: English | H22: USA | I22: R | J22: Robin Williams | K22: Barry Levinson | L22: 49000 | M22: 50141 | N22: 272 | O22: 0 | P22: 7.3 | Q22: 62 | R22: 121 | S22: 123922370 | T22: 13000000 | U22: =IMDB4[[#This Row],[Gross Revenue]]-IMDB4[[#This Row],[Budget]] -> 110922370 | V22: =IF(IMDB4[[#This Row],[Profit]]>0,"Hit","Flop") -> Hit | W22: {=_xlfn.IFS(IMDB4[[#This Row],[IMDb Score (1-10)]]>=8,"Excellent",IMDB4[[#This Row],[IMDb Score (1-10)]]>=7,"Good",IMDB4[[#This Row],[IMDb Score (1-10)]]>=5,"Average",TRUE,"Poor")} -> Good | X22: =IF(IMDB4[[#This Row],[Duration (min)]]<90,"Short",IF(IMDB4[[#This Row],[Duration (min)]]<=120,"Medium", "Long")) -> Long | Z22: =W13 -> Average | AA22: China | AB22: =SUMIFS(U:U,H:H,AA22,W:W,Z22) -> -171656361
A23: Hook | B23: 33368 | C23: =YEAR(IMDB4[[#This Row],[Release Date]]) -> 1991 | D23: =FLOOR(IMDB4[[#This Row],[Year]],10)&"s" -> 1990s | E23: Color | F23: Adventure | G23: English | H23: USA | I23: PG | J23: Robin Williams | K23: Steven Spielberg | L23: 49000 | M23: 64259 | N23: 14000 | O23: 13000 | P23: 6.7 | Q23: 75 | R23: 142 | S23: 119654900 | T23: 70000000 | U23: =IMDB4[[#This Row],[Gross Revenue]]-IMDB4[[#This Row],[Budget]] -> 49654900 | V23: =IF(IMDB4[[#This Row],[Profit]]>0,"Hit","Flop") -> Hit | W23: {=_xlfn.IFS(IMDB4[[#This Row],[IMDb Score (1-10)]]>=8,"Excellent",IMDB4[[#This Row],[IMDb Score (1-10)]]>=7,"Good",IMDB4[[#This Row],[IMDb Score (1-10)]]>=5,"Average",TRUE,"Poor")} -> Average | X23: =IF(IMDB4[[#This Row],[Duration (min)]]<90,"Short",IF(IMDB4[[#This Row],[Duration (min)]]<=120,"Medium", "Long")) -> Long | Z23: =W14 -> Average | AA23: Italy | AB23: =SUMIFS(U:U,H:H,AA23,W:W,Z23) -> -61328888
... A56: Rango | B56: 40797 | C56: =YEAR(IMDB4[[#This Row],[Release Date]]) -> 2011 | D56: =FLOOR(IMDB4[[#This Row],[Year]],10)&"s" -> 2010s | E56: Color | F56: Adventure | G56: English | H56: USA | I56: PG | J56: Johnny Depp | K56: Gore Verbinski | L56: 40000 | M56: 43291 | N56: 563 | O56: 26000 | P56: 7.2 | Q56: 362 | R56: 107 | S56: 123207194 | T56: 135000000 | U56: =IMDB4[[#This Row],[Gross Revenue]]-IMDB4[[#This Row],[Budget]] -> -11792806 | V56: =IF(IMDB4[[#This Row],[Profit]]>0,"Hit","Flop") -> Flop | W56: {=_xlfn.IFS(IMDB4[[#This Row],[IMDb Score (1-10)]]>=8,"Excellent",IMDB4[[#This Row],[IMDb Score (1-10)]]>=7,"Good",IMDB4[[#This Row],[IMDb Score (1-10)]]>=5,"Average",TRUE,"Poor")} -> Good | X56: =IF(IMDB4[[#This Row],[Duration (min)]]<90,"Short",IF(IMDB4[[#This Row],[Duration (min)]]<=120,"Medium", "Long")) -> Medium | Z56: =W47 -> Average | AA56: Philippines | AB56: =SUMIFS(U:U,H:H,AA56,W:W,Z56) -> 63071
A57: Public Enemies | B57: 40147 | C57: =YEAR(IMDB4[[#This Row],[Release Date]]) -> 2009 | D57: =FLOOR(IMDB4[[#This Row],[Year]],10)&"s" -> 2000s | E57: Color | F57: Biography | G57: English | H57: USA | I57: R | J57: Johnny Depp | K57: Michael Mann | L57: 40000 | M57: 64599 | N57: 0 | O57: 0 | P57: 7 | Q57: 357 | R57: 140 | S57: 97030725 | T57: 100000000 | U57: =IMDB4[[#This Row],[Gross Revenue]]-IMDB4[[#This Row],[Budget]] -> -2969275 | V57: =IF(IMDB4[[#This Row],[Profit]]>0,"Hit","Flop") -> Flop | W57: {=_xlfn.IFS(IMDB4[[#This Row],[IMDb Score (1-10)]]>=8,"Excellent",IMDB4[[#This Row],[IMDb Score (1-10)]]>=7,"Good",IMDB4[[#This Row],[IMDb Score (1-10)]]>=5,"Average",TRUE,"Poor")} -> Good | X57: =IF(IMDB4[[#This Row],[Duration (min)]]<90,"Short",IF(IMDB4[[#This Row],[Duration (min)]]<=120,"Medium", "Long")) -> Long | Z57: =W48 -> Good | AA57: 0 | AB57: =SUMIFS(U:U,H:H,AA57,W:W,Z57) -> 0
A58: The Lone Ranger | B58: 41630 | C58: =YEAR(IMDB4[[#This Row],[Release Date]]) -> 2013 | D58: =FLOOR(IMDB4[[#This Row],[Year]],10)&"s" -> 2010s | E58: Color | F58: Action | G58: English | H58: USA | I58: PG-13 | J58: Johnny Depp | K58: Gore Verbinski | L58: 40000 | M58: 45757 | N58: 563 | O58: 48000 | P58: 6.5 | Q58: 450 | R58: 150 | S58: 89289910 | T58: 215000000 | U58: =IMDB4[[#This Row],[Gross Revenue]]-IMDB4[[#This Row],[Budget]] -> -125710090 | V58: =IF(IMDB4[[#This Row],[Profit]]>0,"Hit","Flop") -> Flop | W58: {=_xlfn.IFS(IMDB4[[#This Row],[IMDb Score (1-10)]]>=8,"Excellent",IMDB4[[#This Row],[IMDb Score (1-10)]]>=7,"Good",IMDB4[[#This Row],[IMDb Score (1-10)]]>=5,"Average",TRUE,"Poor")} -> Average | X58: =IF(IMDB4[[#This Row],[Duration (min)]]<90,"Short",IF(IMDB4[[#This Row],[Duration (min)]]<=120,"Medium", "Long")) -> Long
A59: Dark Shadows | B59: 40981 | C59: =YEAR(IMDB4[[#This Row],[Release Date]]) -> 2012 | D59: =FLOOR(IMDB4[[#This Row],[Year]],10)&"s" -> 2010s | E59: Color | F59: Comedy | G59: English | H59: USA | I59: PG-13 | J59: Johnny Depp | K59: Tim Burton | L59: 40000 | M59: 80849 | N59: 13000 | O59: 82000 | P59: 6.2 | Q59: 526 | R59: 113 | S59: 79711678 | T59: 100000000 | U59: =IMDB4[[#This Row],[Gross Revenue]]-IMDB4[[#This Row],[Budget]] -> -20288322 | V59: =IF(IMDB4[[#This Row],[Profit]]>0,"Hit","Flop") -> Flop | W59: {=_xlfn.IFS(IMDB4[[#This Row],[IMDb Score (1-10)]]>=8,"Excellent",IMDB4[[#This Row],[IMDb Score (1-10)]]>=7,"Good",IMDB4[[#This Row],[IMDb Score (1-10)]]>=5,"Average",TRUE,"Poor")} -> Average | X59: =IF(IMDB4[[#This Row],[Duration (min)]]<90,"Short",IF(IMDB4[[#This Row],[Duration (min)]]<=120,"Medium", "Long")) -> Medium
A60: The Tourist | B60: 40538 | C60: =YEAR(IMDB4[[#This Row],[Release Date]]) -> 2010 | D60: =FLOOR(IMDB4[[#This Row],[Year]],10)&"s" -> 2010s | E60: Color | F60: Action | G60: English | H60: USA | I60: PG-13 | J60: Johnny Depp | K60: Florian Henckel von Donnersmarck | L60: 40000 | M60: 55175 | N60: 207 | O60: 25000 | P60: 6 | Q60: 321 | R60: 103 | S60: 67631157 | T60: 100000000 | U60: =IMDB4[[#This Row],[Gross Revenue]]-IMDB4[[#This Row],[Budget]] -> -32368843 | V60: =IF(IMDB4[[#This Row],[Profit]]>0,"Hit","Flop") -> Flop | W60: {=_xlfn.IFS(IMDB4[[#This Row],[IMDb Score (1-10)]]>=8,"Excellent",IMDB4[[#This Row],[IMDb Score (1-10)]]>=7,"Good",IMDB4[[#This Row],[IMDb Score (1-10)]]>=5,"Average",TRUE,"Poor")} -> Average | X60: =IF(IMDB4[[#This Row],[Duration (min)]]<90,"Short",IF(IMDB4[[#This Row],[Duration (min)]]<=120,"Medium", "Long")) -> Medium
A61: Black Mass | B61: 42115 | C61: =YEAR(IMDB4[[#This Row],[Release Date]]) -> 2015 | D61: =FLOOR(IMDB4[[#This Row],[Year]],10)&"s" -> 2010s | E61: Color | F61: Biography | G61: English | H61: USA | I61: R | J61: Johnny Depp | K61: Scott Cooper | L61: 40000 | M61: 63769 | N61: 108 | O61: 44000 | P61: 7 | Q61: 391 | R61: 123 | S61: 62563543 | T61: 53000000 | U61: =IMDB4[[#This Row],[Gross Revenue]]-IMDB4[[#This Row],[Budget]] -> 9563543 | V61: =IF(IMDB4[[#This Row],[Profit]]>0,"Hit","Flop") -> Hit | W61: {=_xlfn.IFS(IMDB4[[#This Row],[IMDb Score (1-10)]]>=8,"Excellent",IMDB4[[#This Row],[IMDb Score (1-10)]]>=7,"Good",IMDB4[[#This Row],[IMDb Score (1-10)]]>=5,"Average",TRUE,"Poor")} -> Good | X61: =IF(IMDB4[[#This Row],[Duration (min)]]<90,"Short",IF(IMDB4[[#This Row],[Duration (min)]]<=120,"Medium", "Long")) -> Long
A62: Edward Scissorhands | B62: 33232 | C62: =YEAR(IMDB4[[#This Row],[Release Date]]) -> 1990 | D62: =FLOOR(IMDB4[[#This Row],[Year]],10)&"s" -> 1990s | E62: Color | F62: Fantasy | G62: English | H62: USA | I62: PG-13 | J62: Johnny Depp | K62: Tim Burton | L62: 40000 | M62: 42330 | N62: 13000 | O62: 16000 | P62: 7.9 | Q62: 111 | R62: 105 | S62: 56362352 | T62: 20000000 | U62: =IMDB4[[#This Row],[Gross Revenue]]-IMDB4[[#This Row],[Budget]] -> 36362352 | V62: =IF(IMDB4[[#This Row],[Profit]]>0,"Hit","Flop") -> Hit | W62: {=_xlfn.IFS(IMDB4[[#This Row],[IMDb Score (1-10)]]>=8,"Excellent",IMDB4[[#This Row],[IMDb Score (1-10)]]>=7,"Good",IMDB4[[#This Row],[IMDb Score (1-10)]]>=5,"Average",TRUE,"Poor")} -> Good | X62: =IF(IMDB4[[#This Row],[Duration (min)]]<90,"Short",IF(IMDB4[[#This Row],[Duration (min)]]<=120,"Medium", "Long")) -> Medium
A63: Once Upon a Time in Mexico | B63: 37726 | C63: =YEAR(IMDB4[[#This Row],[Release Date]]) -> 2003 | D63: =FLOOR(IMDB4[[#This Row],[Year]],10)&"s" -> 2000s | E63: Color | F63: Action | G63: English | H63: USA | I63: R | J63: Johnny Depp | K63: Robert Rodriguez | L63: 40000 | M63: 46186 | N63: 0 | O63: 0 | P63: 6.4 | Q63: 178 | R63: 102 | S63: 55845943 | T63: 29000000 | U63: =IMDB4[[#This Row],[Gross Revenue]]-IMDB4[[#This Row],[Budget]] -> 26845943 | V63: =IF(IMDB4[[#This Row],[Profit]]>0,"Hit","Flop") -> Hit | W63: {=_xlfn.IFS(IMDB4[[#This Row],[IMDb Score (1-10)]]>=8,"Excellent",IMDB4[[#This Row],[IMDb Score (1-10)]]>=7,"Good",IMDB4[[#This Row],[IMDb Score (1-10)]]>=5,"Average",TRUE,"Poor")} -> Average | X63: =IF(IMDB4[[#This Row],[Duration (min)]]<90,"Short",IF(IMDB4[[#This Row],[Duration (min)]]<=120,"Medium", "Long")) -> Medium
A64: Corpse Bride | B64: 38672 | C64: =YEAR(IMDB4[[#This Row],[Release Date]]) -> 2005 | D64: =FLOOR(IMDB4[[#This Row],[Year]],10)&"s" -> 2000s | E64: Color | F64: Animation | G64: English | H64: USA | I64: PG | J64: Johnny Depp | K64: Tim Burton | L64: 40000 | M64: 60683 | N64: 13000 | O64: 0 | P64: 7.4 | Q64: 267 | R64: 77 | S64: 53337608 | T64: 40000000 | U64: =IMDB4[[#This Row],[Gross Revenue]]-IMDB4[[#This Row],[Budget]] -> 13337608 | V64: =IF(IMDB4[[#This Row],[Profit]]>0,"Hit","Flop") -> Hit | W64: {=_xlfn.IFS(IMDB4[[#This Row],[IMDb Score (1-10)]]>=8,"Excellent",IMDB4[[#This Row],[IMDb Score (1-10)]]>=7,"Good",IMDB4[[#This Row],[IMDb Score (1-10)]]>=5,"Average",TRUE,"Poor")} -> Good | X64: =IF(IMDB4[[#This Row],[Duration (min)]]<90,"Short",IF(IMDB4[[#This Row],[Duration (min)]]<=120,"Medium", "Long")) -> Short
A65: Blow | B65: 37071 | C65: =YEAR(IMDB4[[#This Row],[Release Date]]) -> 2001 | D65: =FLOOR(IMDB4[[#This Row],[Year]],10)&"s" -> 2000s | E65: Color | F65: Biography | G65: English | H65: USA | I65: R | J65: Johnny Depp | K65: Ted Demme | L65: 40000 | M65: 43453 | N65: 47 | O65: 13000 | P65: 7.6 | Q65: 147 | R65: 124 | S65: 52937130 | T65: 30000000 | U65: =IMDB4[[#This Row],[Gross Revenue]]-IMDB4[[#This Row],[Budget]] -> 22937130 | V65: =IF(IMDB4[[#This Row],[Profit]]>0,"Hit","Flop") -> Hit | W65: {=_xlfn.IFS(IMDB4[[#This Row],[IMDb Score (1-10)]]>=8,"Excellent",IMDB4[[#This Row],[IMDb Score (1-10)]]>=7,"Good",IMDB4[[#This Row],[IMDb Score (1-10)]]>=5,"Average",TRUE,"Poor")} -> Good | X65: =IF(IMDB4[[#This Row],[Duration (min)]]<90,"Short",IF(IMDB4[[#This Row],[Duration (min)]]<=120,"Medium", "Long")) -> Long
A66: Finding Neverland | B66: 38233 | C66: =YEAR(IMDB4[[#This Row],[Release Date]]) -> 2004 | D66: =FLOOR(IMDB4[[#This Row],[Year]],10)&"s" -> 2000s | E66: Color | F66: Biography | G66: English | H66: USA | I66: PG | J66: Johnny Depp | K66: Marc Forster | L66: 40000 | M66: 58823 | N66: 395 | O66: 0 | P66: 7.8 | Q66: 226 | R66: 101 | S66: 51676606 | T66: 25000000 | U66: =IMDB4[[#This Row],[Gross Revenue]]-IMDB4[[#This Row],[Budget]] -> 26676606 | V66: =IF(IMDB4[[#This Row],[Profit]]>0,"Hit","Flop") -> Hit | W66: {=_xlfn.IFS(IMDB4[[#This Row],[IMDb Score (1-10)]]>=8,"Excellent",IMDB4[[#This Row],[IMDb Score (1-10)]]>=7,"Good",IMDB4[[#This Row],[IMDb Score (1-10)]]>=5,"Average",TRUE,"Poor")} -> Good | X66: =IF(IMDB4[[#This Row],[Duration (min)]]<90,"Short",IF(IMDB4[[#This Row],[Duration (min)]]<=120,"Medium", "Long")) -> Medium
A67: Secret Window | B67: 38330 | C67: =YEAR(IMDB4[[#This Row],[Release Date]]) -> 2004 | D67: =FLOOR(IMDB4[[#This Row],[Year]],10)&"s" -> 2000s | E67: Color | F67: Mystery | G67: English | H67: USA | I67: PG-13 | J67: Johnny Depp | K67: David Koepp | L67: 40000 | M67: 41293 | N67: 192 | O67: 0 | P67: 6.6 | Q67: 195 | R67: 96 | S67: 47781388 | T67: 40000000 | U67: =IMDB4[[#This Row],[Gross Revenue]]-IMDB4[[#This Row],[Budget]] -> 7781388 | V67: =IF(IMDB4[[#This Row],[Profit]]>0,"Hit","Flop") -> Hit | W67: {=_xlfn.IFS(IMDB4[[#This Row],[IMDb Score (1-10)]]>=8,"Excellent",IMDB4[[#This Row],[IMDb Score (1-10)]]>=7,"Good",IMDB4[[#This Row],[IMDb Score (1-10)]]>=5,"Average",TRUE,"Poor")} -> Average | X67: =IF(IMDB4[[#This Row],[Duration (min)]]<90,"Short",IF(IMDB4[[#This Row],[Duration (min)]]<=120,"Medium", "Long")) -> Medium
A68: Donnie Brasco | B68: 35445 | C68: =YEAR(IMDB4[[#This Row],[Release Date]]) -> 1997 | D68: =FLOOR(IMDB4[[#This Row],[Year]],10)&"s" -> 1990s | E68: Color | F68: Biography | G68: English | H68: USA | I68: R | J68: Johnny Depp | K68: Mike Newell | L68: 40000 | M68: 56014 | N68: 179 | O68: 0 | P68: 7.8 | Q68: 117 | R68: 147 | S68: 41954997 | T68: 35000000 | U68: =IMDB4[[#This Row],[Gross Revenue]]-IMDB4[[#This Row],[Budget]] -> 6954997 | V68: =IF(IMDB4[[#This Row],[Profit]]>0,"Hit","Flop") -> Hit | W68: {=_xlfn.IFS(IMDB4[[#This Row],[IMDb Score (1-10)]]>=8,"Excellent",IMDB4[[#This Row],[IMDb Score (1-10)]]>=7,"Good",IMDB4[[#This Row],[IMDb Score (1-10)]]>=5,"Average",TRUE,"Poor")} -> Good | X68: =IF(IMDB4[[#This Row],[Duration (min)]]<90,"Short",IF(IMDB4[[#This Row],[Duration (min)]]<=120,"Medium", "Long")) -> Long
A69: Freddy's Dead: The Final Nightmare | B69: 33506 | C69: =YEAR(IMDB4[[#This Row],[Release Date]]) -> 1991 | D69: =FLOOR(IMDB4[[#This Row],[Year]],10)&"s" -> 1990s | E69: Color | F69: Comedy | G69: English | H69: USA | I69: R | J69: Johnny Depp | K69: Rachel Talalay | L69: 40000 | M69: 42002 | N69: 54 | O69: 963 | P69: 4.9 | Q69: 91 | R69: 93 | S69: 34872293 | T69: 8500000 | U69: =IMDB4[[#This Row],[Gross Revenue]]-IMDB4[[#This Row],[Budget]] -> 26372293 | V69: =IF(IMDB4[[#This Row],[Profit]]>0,"Hit","Flop") -> Hit | W69: {=_xlfn.IFS(IMDB4[[#This Row],[IMDb Score (1-10)]]>=8,"Excellent",IMDB4[[#This Row],[IMDb Score (1-10)]]>=7,"Good",IMDB4[[#This Row],[IMDb Score (1-10)]]>=5,"Average",TRUE,"Poor")} -> Poor | X69: =IF(IMDB4[[#This Row],[Duration (min)]]<90,"Short",IF(IMDB4[[#This Row],[Duration (min)]]<=120,"Medium", "Long")) -> Medium
... A3727: Antarctic Edge: 70Â° South | B3727: 42057 | C3727: =YEAR(IMDB4[[#This Row],[Release Date]]) -> 2015 | D3727: =FLOOR(IMDB4[[#This Row],[Year]],10)&"s" -> 2010s | E3727: Color | F3727: Adventure | G3727: English | H3727: USA | I3727: Not Rated | J3727: Naderev Sano | K3727: Dena Seidel | L3727: 0 | M3727: 0 | N3727: 0 | O3727: 215 | P3727: 7 | Q3727: 5 | R3727: 72 | S3727: 4914 | T3727: 150000 | U3727: =IMDB4[[#This Row],[Gross Revenue]]-IMDB4[[#This Row],[Budget]] -> -145086 | V3727: =IF(IMDB4[[#This Row],[Profit]]>0,"Hit","Flop") -> Flop | W3727: {=_xlfn.IFS(IMDB4[[#This Row],[IMDb Score (1-10)]]>=8,"Excellent",IMDB4[[#This Row],[IMDb Score (1-10)]]>=7,"Good",IMDB4[[#This Row],[IMDb Score (1-10)]]>=5,"Average",TRUE,"Poor")} -> Good | X3727: =IF(IMDB4[[#This Row],[Duration (min)]]<90,"Short",IF(IMDB4[[#This Row],[Duration (min)]]<=120,"Medium", "Long")) -> Short

Sheet Formula_Analysis
A1: Total Number of Movies | B1: =COUNTA(IMDB4[Title]) -> 3726
A2: Average IMDb Score | B2: =AVERAGE(IMDB4[IMDb Score (1-10)]) -> 6.463956
A3: Total Gross Revenue | B3: =SUM(IMDB4[Gross Revenue]) -> 185291371640
A4: Total Profit | B4: =SUM(IMDB4[Profit]) -> 20013582391
A6: Top 10 Movies by IMDb Score
A7: {=_xlfn._xlws.SORT(IMDB4[[Title]:[IMDb Score (1-10)]],16,-1)} -> The Shawshank Redemption | B7: 34427 | C7: 1994 | D7: 1990s | E7: Color | F7: Crime | G7: English | H7: USA | I7: R | J7: Morgan Freeman | K7: Frank Darabont | L7: 11000 | M7: 13495 | N7: 0 | O7: 108000 | P7: 9.3 | R7: {=_xlfn.TAKE(_xlfn.ANCHORARRAY(A7),10)} -> The Shawshank Redemption | S7: 34427 | T7: 1994 | U7: 1990s | V7: Color | W7: Crime | X7: English | Y7: USA | Z7: R | AA7: Morgan Freeman | AB7: Frank Darabont | AC7: 11000 | AD7: 13495 | AE7: 0 | AF7: 108000 | AG7: 9.3
A8: The Godfather | B8: 26351 | C8: 1972 | D8: 1970s | E8: Color | F8: Crime | G8: English | H8: USA | I8: R | J8: Al Pacino | K8: Francis Ford Coppola | L8: 14000 | M8: 28122 | N8: 0 | O8: 43000 | P8: 9.2 | R8: The Godfather | S8: 26351 | T8: 1972 | U8: 1970s | V8: Color | W8: Crime | X8: English | Y8: USA | Z8: R | AA8: Al Pacino | AB8: Francis Ford Coppola | AC8: 14000 | AD8: 28122 | AE8: 0 | AF8: 43000 | AG8: 9.2
A9: The Dark Knight | B9: 39577 | C9: 2008 | D9: 2000s | E9: Color | F9: Action | G9: English | H9: USA | I9: PG-13 | J9: Christian Bale | K9: Christopher Nolan | L9: 23000 | M9: 57802 | N9: 22000 | O9: 37000 | P9: 9 | R9: The Dark Knight | S9: 39577 | T9: 2008 | U9: 2000s | V9: Color | W9: Action | X9: English | Y9: USA | Z9: PG-13 | AA9: Christian Bale | AB9: Christopher Nolan | AC9: 23000 | AD9: 57802 | AE9: 22000 | AF9: 37000 | AG9: 9
A10: The Godfather: Part II | B10: 27132 | C10: 1974 | D10: 1970s | E10: Color | F10: Crime | G10: English | H10: USA | I10: R | J10: Robert De Niro | K10: Francis Ford Coppola | L10: 22000 | M10: 39960 | N10: 0 | O10: 14000 | P10: 9 | R10: The Godfather: Part II | S10: 27132 | T10: 1974 | U10: 1970s | V10: Color | W10: Crime | X10: English | Y10: USA | Z10: R | AA10: Robert De Niro | AB10: Francis Ford Coppola | AC10: 22000 | AD10: 39960 | AE10: 0 | AF10: 14000 | AG10: 9
A11: The Good, the Bad and the Ugly | B11: 24283 | C11: 1966 | D11: 1960s | E11: Color | F11: Western | G11: Italian | H11: Italy | I11: Approved | J11: Clint Eastwood | K11: Sergio Leone | L11: 16000 | M11: 16089 | N11: 0 | O11: 20000 | P11: 8.9 | R11: The Good, the Bad and the Ugly | S11: 24283 | T11: 1966 | U11: 1960s | V11: Color | W11: Western | X11: Italian | Y11: Italy | Z11: Approved | AA11: Clint Eastwood | AB11: Sergio Leone | AC11: 16000 | AD11: 16089 | AE11: 0 | AF11: 20000 | AG11: 8.9
A12: Schindler's List | B12: 34305 | C12: 1993 | D12: 1990s | E12: Black and White | F12: Biography | G12: English | H12: USA | I12: R | J12: Liam Neeson | K12: Steven Spielberg | L12: 14000 | M12: 15233 | N12: 14000 | O12: 41000 | P12: 8.9 | R12: Schindler's List | S12: 34305 | T12: 1993 | U12: 1990s | V12: Black and White | W12: Biography | X12: English | Y12: USA | Z12: R | AA12: Liam Neeson | AB12: Steven Spielberg | AC12: 14000 | AD12: 15233 | AE12: 14000 | AF12: 41000 | AG12: 8.9
A13: Pulp Fiction | B13: 34516 | C13: 1994 | D13: 1990s | E13: Color | F13: Crime | G13: English | H13: USA | I13: R | J13: Bruce Willis | K13: Quentin Tarantino | L13: 13000 | M13: 16557 | N13: 16000 | O13: 45000 | P13: 8.9 | R13: Pulp Fiction | S13: 34516 | T13: 1994 | U13: 1990s | V13: Color | W13: Crime | X13: English | Y13: USA | Z13: R | AA13: Bruce Willis | AB13: Quentin Tarantino | AC13: 13000 | AD13: 16557 | AE13: 16000 | AF13: 45000 | AG13: 8.9
A14: The Lord of the Rings: The Return of the King | B14: 37885 | C14: 2003 | D14: 2000s | E14: Color | F14: Action | G14: English | H14: USA | I14: PG-13 | J14: Orlando Bloom | K14: Peter Jackson | L14: 5000 | M14: 6434 | N14: 0 | O14: 16000 | P14: 8.9 | R14: The Lord of the Rings: The Return of the King | S14: 37885 | T14: 2003 | U14: 2000s | V14: Color | W14: Action | X14: English | Y14: USA | Z14: PG-13 | AA14: Orlando Bloom | AB14: Peter Jackson | AC14: 5000 | AD14: 6434 | AE14: 0 | AF14: 16000 | AG14: 8.9
A15: Inception | B15: 40240 | C15: 2010 | D15: 2010s | E15: Color | F15: Action | G15: English | H15: USA | I15: PG-13 | J15: Leonardo DiCaprio | K15: Christopher Nolan | L15: 29000 | M15: 81115 | N15: 22000 | O15: 175000 | P15: 8.8 | R15: Inception | S15: 40240 | T15: 2010 | U15: 2010s | V15: Color | W15: Action | X15: English | Y15: USA | Z15: PG-13 | AA15: Leonardo DiCaprio | AB15: Christopher Nolan | AC15: 29000 | AD15: 81115 | AE15: 22000 | AF15: 175000 | AG15: 8.8
A16: The Lord of the Rings: The Fellowship of the Ring | B16: 37201 | C16: 2001 | D16: 2000s | E16: Color | F16: Action | G16: English | H16: New Zealand | I16: PG-13 | J16: Christopher Lee | K16: Peter Jackson | L16: 16000 | M16: 22342 | N16: 0 | O16: 21000 | P16: 8.8 | R16: The Lord of the Rings: The Fellowship of the Ring | S16: 37201 | T16: 2001 | U16: 2000s | V16: Color | W16: Action | X16: English | Y16: New Zealand | Z16: PG-13 | AA16: Christopher Lee | AB16: Peter Jackson | AC16: 16000 | AD16: 22342 | AE16: 0 | AF16: 21000 | AG16: 8.8
A17: Forrest Gump | B17: 34651 | C17: 1994 | D17: 1990s | E17: Black and White | F17: Comedy | G17: English | H17: USA | I17: PG-13 | J17: Tom Hanks | K17: Robert Zemeckis | L17: 15000 | M17: 15700 | N17: 0 | O17: 59000 | P17: 8.8
A18: Star Wars: Episode V - The Empire Strikes Back | B18: 29331 | C18: 1980 | D18: 1980s | E18: Color | F18: Action | G18: English | H18: USA | I18: PG | J18: Harrison Ford | K18: Irvin Kershner | L18: 11000 | M18: 12643 | N18: 883 | O18: 17000 | P18: 8.8
A19: Fight Club | B19: 36253 | C19: 1999 | D19: 1990s | E19: Color | F19: Drama | G19: English | H19: USA | I19: R | J19: Brad Pitt | K19: David Fincher | L19: 11000 | M19: 13209 | N19: 21000 | O19: 48000 | P19: 8.8 | R19: Top 10 Movies by Gross Revenue
A20: Goodfellas | B20: 33069 | C20: 1990 | D20: 1990s | E20: Color | F20: Biography | G20: English | H20: USA | I20: R | J20: Robert De Niro | K20: Martin Scorsese | L20: 22000 | M20: 24783 | N20: 17000 | O20: 25000 | P20: 8.7 | R20: {=_xlfn._xlws.SORT(IMDB4[[Title]:[Gross Revenue]],19,-1)} -> Avatar | S20: 39950 | T20: 2009 | U20: 2000s | V20: Color | W20: Action | X20: English | Y20: USA | Z20: PG-13 | AA20: CCH Pounder | AB20: James Cameron | AC20: 1000 | AD20: 4834 | AE20: 0 | AF20: 33000 | AG20: 7.9 | AH20: 723 | AI20: 178 | AJ20: 760505847 | AL20: {=_xlfn.TAKE(_xlfn.ANCHORARRAY(R20),10)} -> Avatar | AM20: 39950 | AN20: 2009 | AO20: 2000s | AP20: Color | AQ20: Action | AR20: English | AS20: USA | AT20: PG-13 | AU20: CCH Pounder | AV20: James Cameron | AW20: 1000 | AX20: 4834 | AY20: 0 | AZ20: 33000 | BA20: 7.9 | BB20: 723 | BC20: 178 | BD20: 760505847
A21: The Matrix | B21: 36521 | C21: 1999 | D21: 1990s | E21: Color | F21: Action | G21: English | H21: USA | I21: R | J21: Keanu Reeves | K21: Lana Wachowski | L21: 18000 | M21: 18563 | N21: 0 | O21: 25000 | P21: 8.7 | R21: Titanic | S21: 35500 | T21: 1997 | U21: 1990s | V21: Color | W21: Drama | X21: English | Y21: USA | Z21: PG-13 | AA21: Leonardo DiCaprio | AB21: James Cameron | AC21: 29000 | AD21: 45223 | AE21: 0 | AF21: 26000 | AG21: 7.7 | AH21: 315 | AI21: 194 | AJ21: 658672302 | AL21: Titanic | AM21: 35500 | AN21: 1997 | AO21: 1990s | AP21: Color | AQ21: Drama | AR21: English | AS21: USA | AT21: PG-13 | AU21: Leonardo DiCaprio | AV21: James Cameron | AW21: 29000 | AX21: 45223 | AY21: 0 | AZ21: 26000 | BA21: 7.7 | BB21: 315 | BC21: 194 | BD21: 658672302
A22: The Lord of the Rings: The Two Towers | B22: 37321 | C22: 2002 | D22: 2000s | E22: Color | F22: Action | G22: English | H22: USA | I22: PG-13 | J22: Christopher Lee | K22: Peter Jackson | L22: 16000 | M22: 23052 | N22: 0 | O22: 10000 | P22: 8.7 | R22: Jurassic World | S22: 42188 | T22: 2015 | U22: 2010s | V22: Color | W22: Action | X22: English | Y22: USA | Z22: PG-13 | AA22: Bryce Dallas Howard | AB22: Colin Trevorrow | AC22: 3000 | AD22: 8458 | AE22: 365 | AF22: 150000 | AG22: 7 | AH22: 644 | AI22: 124 | AJ22: 652177271 | AL22: Jurassic World | AM22: 42188 | AN22: 2015 | AO22: 2010s | AP22: Color | AQ22: Action | AR22: English | AS22: USA | AT22: PG-13 | AU22: Bryce Dallas Howard | AV22: Colin Trevorrow | AW22: 3000 | AX22: 8458 | AY22: 365 | AZ22: 150000 | BA22: 7 | BB22: 644 | BC22: 124 | BD22: 652177271
A23: Star Wars: Episode IV - A New Hope | B23: 28163 | C23: 1977 | D23: 1970s | E23: Color | F23: Action | G23: English | H23: USA | I23: PG | J23: Harrison Ford | K23: George Lucas | L23: 11000 | M23: 13485 | N23: 0 | O23: 33000 | P23: 8.7 | R23: The Avengers | S23: 41118 | T23: 2012 | U23: 2010s | V23: Color | W23: Action | X23: English | Y23: USA | Z23: PG-13 | AA23: Chris Hemsworth | AB23: Joss Whedon | AC23: 26000 | AD23: 87697 | AE23: 0 | AF23: 123000 | AG23: 8.1 | AH23: 703 | AI23: 173 | AJ23: 623279547 | AL23: The Avengers | AM23: 41118 | AN23: 2012 | AO23: 2010s | AP23: Color | AQ23: Action | AR23: English | AS23: USA | AT23: PG-13 | AU23: Chris Hemsworth | AV23: Joss Whedon | AW23: 26000 | AX23: 87697 | AY23: 0 | AZ23: 123000 | BA23: 8.1 | BB23: 703 | BC23: 173 | BD23: 623279547
A24: City of God | B24: 37503 | C24: 2002 | D24: 2000s | E24: Color | F24: Crime | G24: Portuguese | H24: Brazil | I24: R | J24: Alice Braga | K24: Fernando Meirelles | L24: 1000 | M24: 1211 | N24: 353 | O24: 28000 | P24: 8.7 | R24: The Dark Knight | S24: 39577 | T24: 2008 | U24: 2000s | V24: Color | W24: Action | X24: English | Y24: USA | Z24: PG-13 | AA24: Christian Bale | AB24: Christopher Nolan | AC24: 23000 | AD24: 57802 | AE24: 22000 | AF24: 37000 | AG24: 9 | AH24: 645 | AI24: 152 | AJ24: 533316061 | AL24: The Dark Knight | AM24: 39577 | AN24: 2008 | AO24: 2000s | AP24: Color | AQ24: Action | AR24: English | AS24: USA | AT24: PG-13 | AU24: Christian Bale | AV24: Christopher Nolan | AW24: 23000 | AX24: 57802 | AY24: 22000 | AZ24: 37000 | BA24: 9 | BB24: 645 | BC24: 152 | BD24: 533316061
A25: One Flew Over the Cuckoo's Nest | B25: 27544 | C25: 1975 | D25: 1970s | E25: Color | F25: Drama | G25: English | H25: USA | I25: R | J25: Scatman Crothers | K25: Milos Forman | L25: 888 | M25: 2176 | N25: 869 | O25: 32000 | P25: 8.7 | R25: Star Wars: Episode I - The Phantom Menace | S25: 36330 | T25: 1999 | U25: 1990s | V25: Color | W25: Action | X25: English | Y25: USA | Z25: PG | AA25: Natalie Portman | AB25: George Lucas | AC25: 20000 | AD25: 37723 | AE25: 0 | AF25: 13000 | AG25: 6.5 | AH25: 320 | AI25: 136 | AJ25: 474544677 | AL25: Star Wars: Episode I - The Phantom Menace | AM25: 36330 | AN25: 1999 | AO25: 1990s | AP25: Color | AQ25: Action | AR25: English | AS25: USA | AT25: PG | AU25: Natalie Portman | AV25: George Lucas | AW25: 20000 | AX25: 37723 | AY25: 0 | AZ25: 13000 | BA25: 6.5 | BB25: 320 | BC25: 136 | BD25: 474544677
A26: Seven Samurai | B26: 19907 | C26: 1954 | D26: 1950s | E26: Black and White | F26: Action | G26: Japanese | H26: Japan | I26: Unrated | J26: Takashi Shimura | K26: Akira Kurosawa | L26: 304 | M26: 338 | N26: 0 | O26: 11000 | P26: 8.7 | R26: Star Wars: Episode IV - A New Hope | S26: 28163 | T26: 1977 | U26: 1970s | V26: Color | W26: Action | X26: English | Y26: USA | Z26: PG | AA26: Harrison Ford | AB26: George Lucas | AC26: 11000 | AD26: 13485 | AE26: 0 | AF26: 33000 | AG26: 8.7 | AH26: 282 | AI26: 125 | AJ26: 460935665 | AL26: Star Wars: Episode IV - A New Hope | AM26: 28163 | AN26: 1977 | AO26: 1970s | AP26: Color | AQ26: Action | AR26: English | AS26: USA | AT26: PG | AU26: Harrison Ford | AV26: George Lucas | AW26: 11000 | AX26: 13485 | AY26: 0 | AZ26: 33000 | BA26: 8.7 | BB26: 282 | BC26: 125 | BD26: 460935665
A27: The Usual Suspects | B27: 34868 | C27: 1995 | D27: 1990s | E27: Color | F27: Crime | G27: English | H27: USA | I27: R | J27: Kevin Spacey | K27: Bryan Singer | L27: 18000 | M27: 20821 | N27: 0 | O27: 28000 | P27: 8.6 | R27: Avengers: Age of Ultron | S27: 42055 | T27: 2015 | U27: 2010s | V27: Color | W27: Action | X27: English | Y27: USA | Z27: PG-13 | AA27: Chris Hemsworth | AB27: Joss Whedon | AC27: 26000 | AD27: 92000 | AE27: 0 | AF27: 118000 | AG27: 7.5 | AH27: 635 | AI27: 141 | AJ27: 458991599 | AL27: Avengers: Age of Ultron | AM27: 42055 | AN27: 2015 | AO27: 2010s | AP27: Color | AQ27: Action | AR27: English | AS27: USA | AT27: PG-13 | AU27: Chris Hemsworth | AV27: Joss Whedon | AW27: 26000 | AX27: 92000 | AY27: 0 | AZ27: 118000 | BA27: 7.5 | BB27: 635 | BC27: 141 | BD27: 458991599
A28: Saving Private Ryan | B28: 36134 | C28: 1998 | D28: 1990s | E28: Color | F28: Action | G28: English | H28: USA | I28: R | J28: Tom Hanks | K28: Steven Spielberg | L28: 15000 | M28: 44998 | N28: 14000 | O28: 22000 | P28: 8.6 | R28: The Dark Knight Rises | S28: 41108 | T28: 2012 | U28: 2010s | V28: Color | W28: Action | X28: English | Y28: USA | Z28: PG-13 | AA28: Tom Hardy | AB28: Christopher Nolan | AC28: 27000 | AD28: 106759 | AE28: 22000 | AF28: 164000 | AG28: 8.5 | AH28: 813 | AI28: 164 | AJ28: 448130642 | AL28: The Dark Knight Rises | AM28: 41108 | AN28: 2012 | AO28: 2010s | AP28: Color | AQ28: Action | AR28: English | AS28: USA | AT28: PG-13 | AU28: Tom Hardy | AV28: Christopher Nolan | AW28: 27000 | AX28: 106759 | AY28: 22000 | AZ28: 164000 | BA28: 8.5 | BB28: 813 | BC28: 164 | BD28: 448130642
A29: The Silence of the Lambs | B29: 33391 | C29: 1991 | D29: 1990s | E29: Color | F29: Crime | G29: English | H29: USA | I29: R | J29: Anthony Hopkins | K29: Jonathan Demme | L29: 12000 | M29: 13184 | N29: 438 | O29: 40000 | P29: 8.6 | R29: Shrek 2 | S29: 38076 | T29: 2004 | U29: 2000s | V29: Color | W29: Adventure | X29: English | Y29: USA | Z29: PG | AA29: Rupert Everett | AB29: Andrew Adamson | AC29: 692 | AD29: 1148 | AE29: 80 | AF29: 0 | AG29: 7.2 | AH29: 205 | AI29: 93 | AJ29: 436471036 | AL29: Shrek 2 | AM29: 38076 | AN29: 2004 | AO29: 2000s | AP29: Color | AQ29: Adventure | AR29: English | AS29: USA | AT29: PG | AU29: Rupert Everett | AV29: Andrew Adamson | AW29: 692 | AX29: 1148 | AY29: 80 | AZ29: 0 | BA29: 7.2 | BB29: 205 | BC29: 93 | BD29: 436471036
A30: Interstellar | B30: 42001 | C30: 2014 | D30: 2010s | E30: Color | F30: Adventure | G30: English | H30: USA | I30: PG-13 | J30: Matthew McConaughey | K30: Christopher Nolan | L30: 11000 | M30: 31488 | N30: 22000 | O30: 349000 | P30: 8.6 | R30: E.T. the Extra-Terrestrial | S30: 30248 | T30: 1982 | U30: 1980s | V30: Color | W30: Family | X30: English | Y30: USA | Z30: PG | AA30: Henry Thomas | AB30: Steven Spielberg | AC30: 861 | AD30: 2811 | AE30: 14000 | AF30: 34000 | AG30: 7.9 | AH30: 215 | AI30: 120 | AJ30: 434949459
A31: Se7en | B31: 35024 | C31: 1995 | D31: 1990s | E31: Color | F31: Crime | G31: English | H31: USA | I31: R | J31: Morgan Freeman | K31: David Fincher | L31: 11000 | M31: 22678 | N31: 21000 | O31: 39000 | P31: 8.6 | R31: The Hunger Games: Catching Fire | S31: 41347 | T31: 2013 | U31: 2010s | V31: Color | W31: Adventure | X31: English | Y31: USA | Z31: PG-13 | AA31: Jennifer Lawrence | AB31: Francis Lawrence | AC31: 34000 | AD31: 49355 | AE31: 508 | AF31: 82000 | AG31: 7.6 | AH31: 502 | AI31: 146 | AJ31: 424645577
A32: American History X | B32: 35976 | C32: 1998 | D32: 1990s | E32: Black and White | F32: Crime | G32: English | H32: USA | I32: R | J32: Ethan Suplee | K32: Tony Kaye | L32: 1000 | M32: 3858 | N32: 194 | O32: 35000 | P32: 8.6 | R32: Pirates of the Caribbean: Dead Man's Chest | S32: 39081 | T32: 2006 | U32: 2000s | V32: Color | W32: Action | X32: English | Y32: USA | Z32: PG-13 | AA32: Johnny Depp | AB32: Gore Verbinski | AC32: 40000 | AD32: 48486 | AE32: 563 | AF32: 5000 | AG32: 7.3 | AH32: 313 | AI32: 151 | AJ32: 423032628 | AL32: Director with Highest Average IMDb Score | AQ32: Lead Actor with Highest Total Gross Revenue | AV32: Genre with Highest Average IMDb Score | BA32: Year with Highest Total Gross Revenue | BF32: Movie with Highest Budget | BI32: Movie with Highest Profit
A33: Modern Times | B33: 13430 | C33: 1936 | D33: 1930s | E33: Black and White | F33: Comedy | G33: English | H33: USA | I33: G | J33: Paulette Goddard | K33: Charles Chaplin | L33: 309 | M33: 352 | N33: 0 | O33: 0 | P33: 8.6 | R33: The Lion King | S33: 34484 | T33: 1994 | U33: 1990s | V33: Color | W33: Adventure | X33: English | Y33: USA | Z33: G | AA33: Matthew Broderick | AB33: Roger Allers | AC33: 2000 | AD33: 6458 | AE33: 28 | AF33: 17000 | AG33: 8.5 | AH33: 186 | AI33: 73 | AJ33: 422783777 | AL33: Director Name | AM33: Avg IMDb Score | AN33: Highest Avg Score | AO33: =MAX(AM34:AM1766) -> 8.6 | AQ33: Lead Actor | AR33: Total Gross Revenue | AS33: Highest Gross | AT33: =MAX(AR34:AR1528) -> 3391556163 | AV33: Genre | AW33: Avg IMDb Score | AX33: Highest Avg Score | AY33: =MAX(AW34:AW50) -> 7.1502439 | BA33: Release Year | BB33: Total Gross Revenue | BC33: Highest Gross | BD33: =MAX(BB34:BB107) -> 9961663010 | BF33: Highest Budget | BG33: =MAX(IMDB4[Budget]) -> 12215500000 | BI33: Highest Profit | BJ33: =MAX(IMDB4[Profit]) -> 523505847
A34: Spirited Away | B34: 37003 | C34: 2001 | D34: 2000s | E34: Color | F34: Adventure | G34: Japanese | H34: Japan | I34: PG | J34: Bunta Sugawara | K34: Hayao Miyazaki | L34: 17 | M34: 44 | N34: 6000 | O34: 28000 | P34: 8.6 | R34: Toy Story 3 | S34: 40216 | T34: 2010 | U34: 2010s | V34: Color | W34: Adventure | X34: English | Y34: USA | Z34: G | AA34: Tom Hanks | AB34: Lee Unkrich | AC34: 15000 | AD34: 19085 | AE34: 125 | AF34: 30000 | AG34: 8.3 | AH34: 453 | AI34: 103 | AJ34: 414984497 | AL34: {=_xlfn.UNIQUE(IMDB4[Director Name])} -> Adam McKay | AM34: =AVERAGEIFS(IMDB4[IMDb Score (1-10)],IMDB4[Director Name],Formula_Analysis!AL34) -> 6.9166667 | AN34: Best Director | AO34: {=_xlfn.XLOOKUP(AO33,AM34:AM1766,_xlfn.ANCHORARRAY(AL34))} -> Tony Kaye | AQ34: {=_xlfn.UNIQUE(IMDB4[Lead Actor])} -> Darcy Donavan | AR34: =SUMIFS(IMDB4[Gross Revenue],IMDB4[Lead Actor],Formula_Analysis!AQ34) -> 84136909 | AS34: Top Lead Actor | AT34: {=_xlfn.XLOOKUP(AT33,AR34:AR1528,_xlfn.ANCHORARRAY(AQ34))} -> Harrison Ford | AV34: {=_xlfn.UNIQUE(IMDB4[Genre])} -> Comedy | AW34: =AVERAGEIFS(IMDB4[IMDb Score (1-10)],IMDB4[Genre],Formula_Analysis!AV34) -> 6.1705709 | AX34: Top Genre | AY34: {=_xlfn.XLOOKUP(AY33,AW34:AW50,_xlfn.ANCHORARRAY(AV34))} -> Biography | BA34: {=_xlfn.UNIQUE(IMDB4[Year])} -> 2004 | BB34: =SUMIFS(IMDB4[Gross Revenue],IMDB4[Year],Formula_Analysis!BA34) -> 7746292471 | BC34: Top Revenue Year | BD34: {=_xlfn.XLOOKUP(BD33,BB34:BB107,_xlfn.ANCHORARRAY(BA34))} -> 2013 | BF34: Movie Title | BG34: =_xlfn.XLOOKUP(BG33,IMDB4[Budget],IMDB4[Title]) -> The Host | BI34: Movie Title | BJ34: =_xlfn.XLOOKUP(Formula_Analysis!BJ33,IMDB4[Profit],IMDB4[Title]) -> Avatar
A35: Django Unchained | B35: 41270 | C35: 2012 | D35: 2010s | E35: Color | F35: Drama | G35: English | H35: USA | I35: R | J35: Leonardo DiCaprio | K35: Quentin Tarantino | L35: 29000 | M35: 40978 | N35: 16000 | O35: 199000 | P35: 8.5 | R35: Iron Man 3 | S35: 41385 | T35: 2013 | U35: 2010s | V35: Color | W35: Action | X35: English | Y35: USA | Z35: PG-13 | AA35: Robert Downey Jr. | AB35: Shane Black | AC35: 21000 | AD35: 30426 | AE35: 1000 | AF35: 95000 | AG35: 7.2 | AH35: 608 | AI35: 195 | AJ35: 408992272 | AL35: Johnny Remo | AM35: =AVERAGEIFS(IMDB4[IMDb Score (1-10)],IMDB4[Director Name],Formula_Analysis!AL35) -> 5.6 | AQ35: Matthew Ziff | AR35: =SUMIFS(IMDB4[Gross Revenue],IMDB4[Lead Actor],Formula_Analysis!AQ35) -> 96734 | AV35: Action | AW35: =AVERAGEIFS(IMDB4[IMDb Score (1-10)],IMDB4[Genre],Formula_Analysis!AV35) -> 6.2814444 | BA35: 2012 | BB35: =SUMIFS(IMDB4[Gross Revenue],IMDB4[Year],Formula_Analysis!BA35) -> 9809584344
A36: The Departed | B36: 38983 | C36: 2006 | D36: 2000s | E36: Color | F36: Crime | G36: English | H36: USA | I36: R | J36: Leonardo DiCaprio | K36: Martin Scorsese | L36: 29000 | M36: 45648 | N36: 17000 | O36: 29000 | P36: 8.5 | R36: The Hunger Games | S36: 41228 | T36: 2012 | U36: 2010s | V36: Color | W36: Adventure | X36: English | Y36: USA | Z36: PG-13 | AA36: Jennifer Lawrence | AB36: Gary Ross | AC36: 34000 | AD36: 49942 | AE36: 378 | AF36: 140000 | AG36: 7.3 | AH36: 673 | AI36: 142 | AJ36: 407999255 | AL36: David R. Ellis | AM36: =AVERAGEIFS(IMDB4[IMDb Score (1-10)],IMDB4[Director Name],Formula_Analysis!AL36) -> 5.5 | AQ36: Krista Allen | AR36: =SUMIFS(IMDB4[Gross Revenue],IMDB4[Lead Actor],Formula_Analysis!AQ36) -> 66466372 | AV36: Horror | AW36: =AVERAGEIFS(IMDB4[IMDb Score (1-10)],IMDB4[Genre],Formula_Analysis!AV36) -> 5.7907285 | BA36: 2009 | BB36: =SUMIFS(IMDB4[Gross Revenue],IMDB4[Year],Formula_Analysis!BA36) -> 9441301389
A37: The Dark Knight Rises | B37: 41108 | C37: 2012 | D37: 2010s | E37: Color | F37: Action | G37: English | H37: USA | I37: PG-13 | J37: Tom Hardy | K37: Christopher Nolan | L37: 27000 | M37: 106759 | N37: 22000 | O37: 164000 | P37: 8.5 | R37: Spider-Man | S37: 37291 | T37: 2002 | U37: 2000s | V37: Color | W37: Action | X37: English | Y37: USA | Z37: PG-13 | AA37: J.K. Simmons | AB37: Sam Raimi | AC37: 24000 | AD37: 40484 | AE37: 0 | AF37: 5000 | AG37: 7.3 | AH37: 291 | AI37: 121 | AJ37: 403706375 | AL37: John Erick Dowdle | AM37: =AVERAGEIFS(IMDB4[IMDb Score (1-10)],IMDB4[Director Name],Formula_Analysis!AL37) -> 6.3 | AQ37: Andrew Fiscella | AR37: =SUMIFS(IMDB4[Gross Revenue],IMDB4[Lead Actor],Formula_Analysis!AQ37) -> 47680687 | AV37: Drama | AW37: =AVERAGEIFS(IMDB4[IMDb Score (1-10)],IMDB4[Genre],Formula_Analysis!AV37) -> 6.8261905 | BA37: 2008 | BB37: =SUMIFS(IMDB4[Gross Revenue],IMDB4[Year],Formula_Analysis!BA37) -> 8550222881
A38: Whiplash | B38: 41756 | C38: 2014 | D38: 2010s | E38: Color | F38: Drama | G38: English | H38: USA | I38: R | J38: J.K. Simmons | K38: Damien Chazelle | L38: 24000 | M38: 26495 | N38: 141 | O38: 129000 | P38: 8.5 | R38: Transformers: Revenge of the Fallen | S38: 39868 | T38: 2009 | U38: 2000s | V38: Color | W38: Action | X38: English | Y38: USA | Z38: PG-13 | AA38: Glenn Morshower | AB38: Michael Bay | AC38: 894 | AD38: 3218 | AE38: 0 | AF38: 0 | AG38: 6 | AH38: 366 | AI38: 150 | AJ38: 402076689 | AL38: NimrÃ³d Antal | AM38: =AVERAGEIFS(IMDB4[IMDb Score (1-10)],IMDB4[Director Name],Formula_Analysis!AL38) -> 6.05 | AQ38: Jimmy Bennett | AR38: =SUMIFS(IMDB4[Gross Revenue],IMDB4[Lead Actor],Formula_Analysis!AQ38) -> 329550504 | AV38: Crime | AW38: =AVERAGEIFS(IMDB4[IMDb Score (1-10)],IMDB4[Genre],Formula_Analysis!AV38) -> 6.9376984 | BA38: 2007 | BB38: =SUMIFS(IMDB4[Gross Revenue],IMDB4[Year],Formula_Analysis!BA38) -> 7338744132 | BF38: Correlation Between Budget & Gross Revenue
A39: The Prestige | B39: 38900 | C39: 2006 | D39: 2000s | E39: Color | F39: Drama | G39: English | H39: USA | I39: PG-13 | J39: Christian Bale | K39: Christopher Nolan | L39: 23000 | M39: 63986 | N39: 22000 | O39: 49000 | P39: 8.5 | R39: Frozen | S39: 41356 | T39: 2013 | U39: 2010s | V39: Color | W39: Adventure | X39: English | Y39: USA | Z39: PG | AA39: Josh Gad | AB39: Chris Buck | AC39: 1000 | AD39: 2582 | AE39: 69 | AF39: 58000 | AG39: 7.6 | AH39: 406 | AI39: 102 | AJ39: 400736600 | AL39: Tom Shadyac | AM39: =AVERAGEIFS(IMDB4[IMDb Score (1-10)],IMDB4[Director Name],Formula_Analysis!AL39) -> 6.3142857 | AQ39: Michael Joiner | AR39: =SUMIFS(IMDB4[Gross Revenue],IMDB4[Lead Actor],Formula_Analysis!AQ39) -> 2428241 | AV39: Adventure | AW39: =AVERAGEIFS(IMDB4[IMDb Score (1-10)],IMDB4[Genre],Formula_Analysis!AV39) -> 6.5558011 | BA39: 2005 | BB39: =SUMIFS(IMDB4[Gross Revenue],IMDB4[Year],Formula_Analysis!BA39) -> 7553429810 | BF39: Correlation (Budget vs Gross) | BG39: =CORREL(IMDB4[Budget],IMDB4[Gross Revenue]) -> 0.093302956
A40: The Green Mile | B40: 36376 | C40: 1999 | D40: 1990s | E40: Color | F40: Crime | G40: English | H40: USA | I40: R | J40: Tom Hanks | K40: Frank Darabont | L40: 15000 | M40: 17716 | N40: 0 | O40: 30000 | P40: 8.5 | R40: Finding Nemo | S40: 37836 | T40: 2003 | U40: 2000s | V40: Color | W40: Adventure | X40: English | Y40: USA | Z40: G | AA40: Alexander Gould | AB40: Andrew Stanton | AC40: 1000 | AD40: 5641 | AE40: 475 | AF40: 11000 | AG40: 8.2 | AH40: 301 | AI40: 100 | AJ40: 380838870 | AL40: Andrew Douglas | AM40: =AVERAGEIFS(IMDB4[IMDb Score (1-10)],IMDB4[Director Name],Formula_Analysis!AL40) -> 6 | AQ40: Robin Williams | AR40: =SUMIFS(IMDB4[Gross Revenue],IMDB4[Lead Actor],Formula_Analysis!AQ40) -> 2296971817 | AV40: Animation | AW40: =AVERAGEIFS(IMDB4[IMDb Score (1-10)],IMDB4[Genre],Formula_Analysis!AV40) -> 6.7622222 | BA40: 2006 | BB40: =SUMIFS(IMDB4[Gross Revenue],IMDB4[Year],Formula_Analysis!BA40) -> 7807179111
A41: Raiders of the Lost Ark | B41: 29722 | C41: 1981 | D41: 1980s | E41: Color | F41: Action | G41: English | H41: USA | I41: PG | J41: Harrison Ford | K41: Steven Spielberg | L41: 11000 | M41: 12906 | N41: 14000 | O41: 16000 | P41: 8.5 | R41: Star Wars: Episode III - Revenge of the Sith | S41: 38404 | T41: 2005 | U41: 2000s | V41: Color | W41: Action | X41: English | Y41: USA | Z41: PG-13 | AA41: Natalie Portman | AB41: George Lucas | AC41: 20000 | AD41: 44042 | AE41: 0 | AF41: 10000 | AG41: 7.6 | AH41: 359 | AI41: 140 | AJ41: 380262555 | AL41: Wolfgang Petersen | AM41: =AVERAGEIFS(IMDB4[IMDb Score (1-10)],IMDB4[Director Name],Formula_Analysis!AL41) -> 6.7666667 | AQ41: Craig Stark | AR41: =SUMIFS(IMDB4[Gross Revenue],IMDB4[Lead Actor],Formula_Analysis!AQ41) -> 54116191 | AV41: Biography | AW41: =AVERAGEIFS(IMDB4[IMDb Score (1-10)],IMDB4[Genre],Formula_Analysis!AV41) -> 7.1502439 | BA41: 2010 | BB41: =SUMIFS(IMDB4[Gross Revenue],IMDB4[Year],Formula_Analysis!BA41) -> 8933076563
A42: Apocalypse Now | B42: 29106 | C42: 1979 | D42: 1970s | E42: Color | F42: Drama | G42: English | H42: USA | I42: R | J42: Harrison Ford | K42: Francis Ford Coppola | L42: 11000 | M42: 25313 | N42: 0 | O42: 19000 | P42: 8.5 | R42: The Lord of the Rings: The Return of the King | S42: 37885 | T42: 2003 | U42: 2000s | V42: Color | W42: Action | X42: English | Y42: USA | Z42: PG-13 | AA42: Orlando Bloom | AB42: Peter Jackson | AC42: 5000 | AD42: 6434 | AE42: 0 | AF42: 16000 | AG42: 8.9 | AH42: 328 | AI42: 192 | AJ42: 377019252 | AL42: Richard Loncraine | AM42: =AVERAGEIFS(IMDB4[IMDb Score (1-10)],IMDB4[Director Name],Formula_Analysis!AL42) -> 6.5333333 | AQ42: Muse Watson | AR42: =SUMIFS(IMDB4[Gross Revenue],IMDB4[Lead Actor],Formula_Analysis!AQ42) -> 363066972 | AV42: Fantasy | AW42: =AVERAGEIFS(IMDB4[IMDb Score (1-10)],IMDB4[Genre],Formula_Analysis!AV42) -> 6.2342857 | BA42: 1993 | BB42: =SUMIFS(IMDB4[Gross Revenue],IMDB4[Year],Formula_Analysis!BA42) -> 2044795249
A43: Gladiator | B43: 36877 | C43: 2000 | D43: 2000s | E43: Color | F43: Action | G43: English | H43: USA | I43: R | J43: Djimon Hounsou | K43: Ridley Scott | L43: 3000 | M43: 6521 | N43: 0 | O43: 21000 | P43: 8.5 | R43: Spider-Man 2 | S43: 38161 | T43: 2004 | U43: 2000s | V43: Color | W43: Action | X43: English | Y43: USA | Z43: PG-13 | AA43: J.K. Simmons | AB43: Sam Raimi | AC43: 24000 | AD43: 43388 | AE43: 0 | AF43: 0 | AG43: 7.3 | AH43: 300 | AI43: 135 | AJ43: 373377893 | AL43: Florent-Emilio Siri | AM43: =AVERAGEIFS(IMDB4[IMDb Score (1-10)],IMDB4[Director Name],Formula_Analysis!AL43) -> 6.6 | AQ43: Tim Holmes | AR43: =SUMIFS(IMDB4[Gross Revenue],IMDB4[Lead Actor],Formula_Analysis!AQ43) -> 234903076 | AV43: Mystery | AW43: =AVERAGEIFS(IMDB4[IMDb Score (1-10)],IMDB4[Genre],Formula_Analysis!AV43) -> 6.5869565 | BA43: 1992 | BB43: =SUMIFS(IMDB4[Gross Revenue],IMDB4[Year],Formula_Analysis!BA43) -> 2138649635
A44: The Lion King | B44: 34484 | C44: 1994 | D44: 1990s | E44: Color | F44: Adventure | G44: English | H44: USA | I44: G | J44: Matthew Broderick | K44: Roger Allers | L44: 2000 | M44: 6458 | N44: 28 | O44: 17000 | P44: 8.5 | R44: Despicable Me 2 | S44: 41439 | T44: 2013 | U44: 2010s | V44: Color | W44: Animation | X44: English | Y44: USA | Z44: PG | AA44: Steve Carell | AB44: Pierre Coffin | AC44: 7000 | AD44: 11905 | AE44: 275 | AF44: 56000 | AG44: 7.5 | AH44: 306 | AI44: 98 | AJ44: 368049635 | AL44: Robert Rodriguez | AM44: =AVERAGEIFS(IMDB4[IMDb Score (1-10)],IMDB4[Director Name],Formula_Analysis!AL44) -> 5.6923077 | AQ44: Johnny Depp | AR44: =SUMIFS(IMDB4[Gross Revenue],IMDB4[Lead Actor],Formula_Analysis!AQ44) -> 3167368026 | AV44: Western | AW44: =AVERAGEIFS(IMDB4[IMDb Score (1-10)],IMDB4[Genre],Formula_Analysis!AV44) -> 6.7666667 | BA44: 1997 | BB44: =SUMIFS(IMDB4[Gross Revenue],IMDB4[Year],Formula_Analysis!BA44) -> 5091713703
A45: Back to the Future | B45: 31386 | C45: 1985 | D45: 1980s | E45: Color | F45: Adventure | G45: English | H45: USA | I45: PG | J45: Lea Thompson | K45: Robert Zemeckis | L45: 1000 | M45: 3230 | N45: 0 | O45: 39000 | P45: 8.5 | R45: Jurassic Park | S45: 34184 | T45: 1993 | U45: 1990s | V45: Color | W45: Adventure | X45: English | Y45: USA | Z45: PG-13 | AA45: Wayne Knight | AB45: Steven Spielberg | AC45: 967 | AD45: 2129 | AE45: 14000 | AF45: 19000 | AG45: 8.1 | AH45: 308 | AI45: 127 | AJ45: 356784000 | AL45: James Mottern | AM45: =AVERAGEIFS(IMDB4[IMDb Score (1-10)],IMDB4[Director Name],Formula_Analysis!AL45) -> 6.7 | AQ45: Bella Thorne | AR45: =SUMIFS(IMDB4[Gross Revenue],IMDB4[Lead Actor],Formula_Analysis!AQ45) -> 233133659 | AV45: Romance | AW45: =AVERAGEIFS(IMDB4[IMDb Score (1-10)],IMDB4[Genre],Formula_Analysis!AV45) -> 6.1333333 | BA45: 1998 | BB45: =SUMIFS(IMDB4[Gross Revenue],IMDB4[Year],Formula_Analysis!BA45) -> 4907264474
A46: Alien | B46: 29131 | C46: 1979 | D46: 1970s | E46: Color | F46: Horror | G46: English | H46: UK | I46: R | J46: Tom Skerritt | K46: Ridley Scott | L46: 1000 | M46: 2524 | N46: 0 | O46: 23000 | P46: 8.5 | R46: Inside Out | S46: 42104 | T46: 2015 | U46: 2010s | V46: Color | W46: Adventure | X46: English | Y46: USA | Z46: PG | AA46: Amy Poehler | AB46: Pete Docter | AC46: 1000 | AD46: 2944 | AE46: 0 | AF46: 118000 | AG46: 8.3 | AH46: 536 | AI46: 95 | AJ46: 356454367 | AL46: David G. Evans | AM46: =AVERAGEIFS(IMDB4[IMDb Score (1-10)],IMDB4[Director Name],Formula_Analysis!AL46) -> 6.4 | AQ46: Jennifer Lawrence | AR46: =SUMIFS(IMDB4[Gross Revenue],IMDB4[Lead Actor],Formula_Analysis!AQ46) -> 2212870937 | AV46: Documentary | AW46: =AVERAGEIFS(IMDB4[IMDb Score (1-10)],IMDB4[Genre],Formula_Analysis!AV46) -> 6.9511628 | BA46: 1987 | BB46: =SUMIFS(IMDB4[Gross Revenue],IMDB4[Year],Formula_Analysis!BA46) -> 1215008641
A47: Terminator 2: Judgment Day | B47: 33335 | C47: 1991 | D47: 1990s | E47: Color | F47: Action | G47: English | H47: USA | I47: R | J47: Joe Morton | K47: James Cameron | L47: 780 | M47: 2829 | N47: 0 | O47: 13000 | P47: 8.5 | R47: Transformers: Dark of the Moon | S47: 40588 | T47: 2011 | U47: 2010s | V47: Color | W47: Action | X47: English | Y47: USA | Z47: PG-13 | AA47: Glenn Morshower | AB47: Michael Bay | AC47: 894 | AD47: 2593 | AE47: 0 | AF47: 46000 | AG47: 6.3 | AH47: 428 | AI47: 154 | AJ47: 352358779 | AL47: Shawn Levy | AM47: =AVERAGEIFS(IMDB4[IMDb Score (1-10)],IMDB4[Director Name],Formula_Analysis!AL47) -> 6.0909091 | AQ47: Ryan Gosling | AR47: =SUMIFS(IMDB4[Gross Revenue],IMDB4[Lead Actor],Formula_Analysis!AQ47) -> 465009357 | AV47: Sci-Fi | AW47: =AVERAGEIFS(IMDB4[IMDb Score (1-10)],IMDB4[Genre],Formula_Analysis!AV47) -> 6.5875 | BA47: 1991 | BB47: =SUMIFS(IMDB4[Gross Revenue],IMDB4[Year],Formula_Analysis!BA47) -> 1615335050
A48: Memento | B48: 36787 | C48: 2000 | D48: 2000s | E48: Black and White | F48: Mystery | G48: English | H48: USA | I48: R | J48: Callum Rennie | K48: Christopher Nolan | L48: 716 | M48: 1997 | N48: 22000 | O48: 40000 | P48: 8.5 | R48: American Sniper | S48: 41689 | T48: 2014 | U48: 2010s | V48: Color | W48: Action | X48: English | Y48: USA | Z48: R | AA48: Bradley Cooper | AB48: Clint Eastwood | AC48: 14000 | AD48: 16277 | AE48: 16000 | AF48: 112000 | AG48: 7.3 | AH48: 490 | AI48: 133 | AJ48: 350123553 | AL48: Chris Columbus | AM48: =AVERAGEIFS(IMDB4[IMDb Score (1-10)],IMDB4[Director Name],Formula_Analysis!AL48) -> 6.6545455 | AQ48: Chris Moss | AR48: =SUMIFS(IMDB4[Gross Revenue],IMDB4[Lead Actor],Formula_Analysis!AQ48) -> 19179969 | AV48: Musical | AW48: =AVERAGEIFS(IMDB4[IMDb Score (1-10)],IMDB4[Genre],Formula_Analysis!AV48) -> 6.75 | BA48: 2014 | BB48: =SUMIFS(IMDB4[Gross Revenue],IMDB4[Year],Formula_Analysis!BA48) -> 9852133822
A49: Psycho | B49: 22224 | C49: 1960 | D49: 1960s | E49: Black and White | F49: Horror | G49: English | H49: USA | I49: R | J49: Janet Leigh | K49: Alfred Hitchcock | L49: 606 | M49: 1885 | N49: 13000 | O49: 18000 | P49: 8.5 | R49: Furious 7 | S49: 42012 | T49: 2015 | U49: 2010s | V49: Color | W49: Action | X49: English | Y49: USA | Z49: PG-13 | AA49: Jason Statham | AB49: James Wan | AC49: 26000 | AD49: 79150 | AE49: 0 | AF49: 94000 | AG49: 7.2 | AH49: 424 | AI49: 140 | AJ49: 350034110 | AL49: Ron Clements | AM49: =AVERAGEIFS(IMDB4[IMDb Score (1-10)],IMDB4[Director Name],Formula_Analysis!AL49) -> 7.4 | AQ49: Marisa Saks | AR49: =SUMIFS(IMDB4[Gross Revenue],IMDB4[Lead Actor],Formula_Analysis!AQ49) -> 32014289 | AV49: Family | AW49: =AVERAGEIFS(IMDB4[IMDb Score (1-10)],IMDB4[Genre],Formula_Analysis!AV49) -> 6.5 | BA49: 1989 | BB49: =SUMIFS(IMDB4[Gross Revenue],IMDB4[Year],Formula_Analysis!BA49) -> 1612558954
A50: The Pianist | B50: 37447 | C50: 2002 | D50: 2000s | E50: Black and White | F50: Biography | G50: English | H50: France | I50: R | J50: Emilia Fox | K50: Roman Polanski | L50: 396 | M50: 1075 | N50: 2000 | O50: 21000 | P50: 8.5 | R50: The Lord of the Rings: The Two Towers | S50: 37321 | T50: 2002 | U50: 2000s | V50: Color | W50: Action | X50: English | Y50: USA | Z50: PG-13 | AA50: Christopher Lee | AB50: Peter Jackson | AC50: 16000 | AD50: 23052 | AE50: 0 | AF50: 10000 | AG50: 8.7 | AH50: 294 | AI50: 172 | AJ50: 340478898 | AL50: George Miller | AM50: =AVERAGEIFS(IMDB4[IMDb Score (1-10)],IMDB4[Director Name],Formula_Analysis!AL50) -> 6.6833333 | AQ50: Mem Ferda | AR50: =SUMIFS(IMDB4[Gross Revenue],IMDB4[Lead Actor],Formula_Analysis!AQ50) -> 1357042 | AV50: Thriller | AW50: =AVERAGEIFS(IMDB4[IMDb Score (1-10)],IMDB4[Genre],Formula_Analysis!AV50) -> 5.3 | BA50: 2011 | BB50: =SUMIFS(IMDB4[Gross Revenue],IMDB4[Year],Formula_Analysis!BA50) -> 8547731884
A51: The Lives of Others | B51: 38883 | C51: 2006 | D51: 2000s | E51: Color | F51: Drama | G51: German | H51: Germany | I51: R | J51: Sebastian Koch | K51: Florian Henckel von Donnersmarck | L51: 380 | M51: 927 | N51: 207 | O51: 39000 | P51: 8.5 | R51: The Hunger Games: Mockingjay - Part 1 | S51: 41721 | T51: 2014 | U51: 2010s | V51: Color | W51: Adventure | X51: English | Y51: USA | Z51: PG-13 | AA51: Jennifer Lawrence | AB51: Francis Lawrence | AC51: 34000 | AD51: 81385 | AE51: 508 | AF51: 52000 | AG51: 6.7 | AH51: 403 | AI51: 123 | AJ51: 337103873 | AL51: Gus Van Sant | AM51: =AVERAGEIFS(IMDB4[IMDb Score (1-10)],IMDB4[Director Name],Formula_Analysis!AL51) -> 7.1285714 | AQ51: Leonardo DiCaprio | AR51: =SUMIFS(IMDB4[Gross Revenue],IMDB4[Lead Actor],Formula_Analysis!AQ51) -> 2495768978 | BA51: 1999 | BB51: =SUMIFS(IMDB4[Gross Revenue],IMDB4[Year],Formula_Analysis!BA51) -> 6296171788
A52: Samsara | B52: 40894 | C52: 2011 | D52: 2010s | E52: Color | F52: Documentary | G52: None | H52: USA | I52: PG-13 | J52: Collin Alfredo St. Dic | K52: Ron Fricke | L52: 48 | M52: 48 | N52: 330 | O52: 26000 | P52: 8.5 | R52: Spider-Man 3 | S52: 39123 | T52: 2007 | U52: 2000s | V52: Color | W52: Action | X52: English | Y52: USA | Z52: PG-13 | AA52: J.K. Simmons | AB52: Sam Raimi | AC52: 24000 | AD52: 46055 | AE52: 0 | AF52: 0 | AG52: 6.2 | AH52: 392 | AI52: 156 | AJ52: 336530303 | AL52: Barry Levinson | AM52: =AVERAGEIFS(IMDB4[IMDb Score (1-10)],IMDB4[Director Name],Formula_Analysis!AL52) -> 6.5769231 | AQ52: Tom Hardy | AR52: =SUMIFS(IMDB4[Gross Revenue],IMDB4[Lead Actor],Formula_Analysis!AQ52) -> 724395134 | BA52: 2002 | BB52: =SUMIFS(IMDB4[Gross Revenue],IMDB4[Year],Formula_Analysis!BA52) -> 8568266419
A53: Children of Heaven | B53: 35688 | C53: 1997 | D53: 1990s | E53: Color | F53: Drama | G53: Persian | H53: Iran | I53: PG | J53: Bahare Seddiqi | K53: Majid Majidi | L53: 36 | M53: 100 | N53: 373 | O53: 0 | P53: 8.5 | R53: Minions | S53: 42220 | T53: 2015 | U53: 2010s | V53: Color | W53: Action | X53: English | Y53: USA | Z53: PG | AA53: Steve Carell | AB53: Kyle Balda | AC53: 7000 | AD53: 13616 | AE53: 22 | AF53: 70000 | AG53: 6.4 | AH53: 308 | AI53: 91 | AJ53: 336029560 | AL53: Steven Spielberg | AM53: =AVERAGEIFS(IMDB4[IMDb Score (1-10)],IMDB4[Director Name],Formula_Analysis!AL53) -> 7.575 | AQ53: Chris Hemsworth | AR53: =SUMIFS(IMDB4[Gross Revenue],IMDB4[Lead Actor],Formula_Analysis!AQ53) -> 2057901421 | BA53: 2013 | BB53: =SUMIFS(IMDB4[Gross Revenue],IMDB4[Year],Formula_Analysis!BA53) -> 9961663010
A54: Once Upon a Time in America | B54: 30948 | C54: 1984 | D54: 1980s | E54: Color | F54: Crime | G54: English | H54: Italy | I54: R | J54: Robert De Niro | K54: Sergio Leone | L54: 22000 | M54: 24719 | N54: 0 | O54: 12000 | P54: 8.4 | R54: Alice in Wonderland | S54: 40266 | T54: 2010 | U54: 2010s | V54: Color | W54: Adventure | X54: English | Y54: USA | Z54: PG | AA54: Johnny Depp | AB54: Tim Burton | AC54: 40000 | AD54: 79957 | AE54: 13000 | AF54: 24000 | AG54: 6.5 | AH54: 451 | AI54: 108 | AJ54: 334185206 | AL54: Peter Weir | AM54: =AVERAGEIFS(IMDB4[IMDb Score (1-10)],IMDB4[Director Name],Formula_Analysis!AL54) -> 7.725 | AQ54: Jason Statham | AR54: =SUMIFS(IMDB4[Gross Revenue],IMDB4[Lead Actor],Formula_Analysis!AQ54) -> 1081308838 | BA54: 2015 | BB54: =SUMIFS(IMDB4[Gross Revenue],IMDB4[Year],Formula_Analysis!BA54) -> 8578243488
A55: American Beauty | B55: 36415 | C55: 1999 | D55: 1990s | E55: Color | F55: Drama | G55: English | H55: USA | I55: R | J55: Kevin Spacey | K55: Sam Mendes | L55: 18000 | M55: 19078 | N55: 0 | O55: 22000 | P55: 8.4 | R55: Guardians of the Galaxy | S55: 41834 | T55: 2014 | U55: 2010s | V55: Color | W55: Action | X55: English | Y55: USA | Z55: PG-13 | AA55: Bradley Cooper | AB55: James Gunn | AC55: 14000 | AD55: 32438 | AE55: 571 | AF55: 96000 | AG55: 8.1 | AH55: 653 | AI55: 121 | AJ55: 333130696 | AL55: Les Mayfield | AM55: =AVERAGEIFS(IMDB4[IMDb Score (1-10)],IMDB4[Director Name],Formula_Analysis!AL55) -> 5.5 | AQ55: Alan Rickman | AR55: =SUMIFS(IMDB4[Gross Revenue],IMDB4[Lead Actor],Formula_Analysis!AQ55) -> 699415604 | BA55: 1995 | BB55: =SUMIFS(IMDB4[Gross Revenue],IMDB4[Year],Formula_Analysis!BA55) -> 3089321823
A56: Reservoir Dogs | B56: 33687 | C56: 1992 | D56: 1990s | E56: Color | F56: Crime | G56: English | H56: USA | I56: R | J56: Quentin Tarantino | K56: Quentin Tarantino | L56: 16000 | M56: 28994 | N56: 16000 | O56: 19000 | P56: 8.4 | R56: Forrest Gump | S56: 34651 | T56: 1994 | U56: 1990s | V56: Black and White | W56: Comedy | X56: English | Y56: USA | Z56: PG-13 | AA56: Tom Hanks | AB56: Robert Zemeckis | AC56: 15000 | AD56: 15700 | AE56: 0 | AF56: 59000 | AG56: 8.8 | AH56: 149 | AI56: 142 | AJ56: 329691196 | AL56: Vincent Ward | AM56: =AVERAGEIFS(IMDB4[IMDb Score (1-10)],IMDB4[Director Name],Formula_Analysis!AL56) -> 7 | AQ56: Jeremy Irvine | AR56: =SUMIFS(IMDB4[Gross Revenue],IMDB4[Lead Actor],Formula_Analysis!AQ56) -> 84504796 | BA56: 2003 | BB56: =SUMIFS(IMDB4[Gross Revenue],IMDB4[Year],Formula_Analysis!BA56) -> 7682827147
A57: Star Wars: Episode VI - Return of the Jedi | B57: 30674 | C57: 1983 | D57: 1980s | E57: Color | F57: Action | G57: English | H57: USA | I57: PG | J57: Harrison Ford | K57: Richard Marquand | L57: 11000 | M57: 13649 | N57: 37 | O57: 14000 | P57: 8.4 | R57: Shrek the Third | S57: 39188 | T57: 2007 | U57: 2000s | V57: Color | W57: Adventure | X57: English | Y57: USA | Z57: PG | AA57: Justin Timberlake | AB57: Chris Miller | AC57: 3000 | AD57: 4705 | AE57: 50 | AF57: 0 | AG57: 6.1 | AH57: 227 | AI57: 93 | AJ57: 320706665 | AL57: Walt Becker | AM57: =AVERAGEIFS(IMDB4[IMDb Score (1-10)],IMDB4[Director Name],Formula_Analysis!AL57) -> 5.6 | AQ57: J.K. Simmons | AR57: =SUMIFS(IMDB4[Gross Revenue],IMDB4[Lead Actor],Formula_Analysis!AQ57) -> 2232860537 | BA57: 1986 | BB57: =SUMIFS(IMDB4[Gross Revenue],IMDB4[Year],Formula_Analysis!BA57) -> 1110911601
A58: Aliens | B58: 31619 | C58: 1986 | D58: 1980s | E58: Color | F58: Action | G58: English | H58: USA | I58: R | J58: Michael Biehn | K58: James Cameron | L58: 2000 | M58: 4228 | N58: 0 | O58: 18000 | P58: 8.4 | R58: Transformers | S58: 39338 | T58: 2007 | U58: 2000s | V58: Color | W58: Action | X58: English | Y58: USA | Z58: PG-13 | AA58: Zack Ward | AB58: Michael Bay | AC58: 662 | AD58: 2333 | AE58: 0 | AF58: 8000 | AG58: 7.1 | AH58: 396 | AI58: 144 | AJ58: 318759914 | AL58: Ken Kwapis | AM58: =AVERAGEIFS(IMDB4[IMDb Score (1-10)],IMDB4[Director Name],Formula_Analysis!AL58) -> 6.2 | AQ58: Christian Bale | AR58: =SUMIFS(IMDB4[Gross Revenue],IMDB4[Lead Actor],Formula_Analysis!AQ58) -> 1515299320 | BA58: 1990 | BB58: =SUMIFS(IMDB4[Gross Revenue],IMDB4[Year],Formula_Analysis!BA58) -> 2070298274
A59: WALLÂ·E | B59: 39649 | C59: 2008 | D59: 2000s | E59: Color | F59: Adventure | G59: English | H59: USA | I59: G | J59: John Ratzenberger | K59: Andrew Stanton | L59: 1000 | M59: 2975 | N59: 475 | O59: 16000 | P59: 8.4 | R59: Iron Man | S59: 39622 | T59: 2008 | U59: 2000s | V59: Color | W59: Action | X59: English | Y59: USA | Z59: PG-13 | AA59: Robert Downey Jr. | AB59: Jon Favreau | AC59: 21000 | AD59: 39252 | AE59: 4000 | AF59: 10000 | AG59: 7.9 | AH59: 486 | AI59: 126 | AJ59: 318298180 | AL59: Kirsten Sheridan | AM59: =AVERAGEIFS(IMDB4[IMDb Score (1-10)],IMDB4[Director Name],Formula_Analysis!AL59) -> 7.5 | AQ59: Paul Walker | AR59: =SUMIFS(IMDB4[Gross Revenue],IMDB4[Lead Actor],Formula_Analysis!AQ59) -> 896901855 | BA59: 2001 | BB59: =SUMIFS(IMDB4[Gross Revenue],IMDB4[Year],Formula_Analysis!BA59) -> 7599762619
A60: Requiem for a Dream | B60: 36701 | C60: 2000 | D60: 2000s | E60: Color | F60: Drama | G60: English | H60: USA | I60: R | J60: Ellen Burstyn | K60: Darren Aronofsky | L60: 1000 | M60: 2235 | N60: 0 | O60: 38000 | P60: 8.4 | R60: Harry Potter and the Sorcerer's Stone | S60: 36935 | T60: 2001 | U60: 2000s | V60: Color | W60: Adventure | X60: English | Y60: UK | Z60: PG | AA60: Daniel Radcliffe | AB60: Chris Columbus | AC60: 11000 | AD60: 13191 | AE60: 0 | AF60: 16000 | AG60: 7.5 | AH60: 258 | AI60: 159 | AJ60: 317557891 | AL60: Mark Romanek | AM60: =AVERAGEIFS(IMDB4[IMDb Score (1-10)],IMDB4[Director Name],Formula_Analysis!AL60) -> 7 | AQ60: Joseph Gordon-Levitt | AR60: =SUMIFS(IMDB4[Gross Revenue],IMDB4[Lead Actor],Formula_Analysis!AQ60) -> 675997319 | BA60: 1984 | BB60: =SUMIFS(IMDB4[Gross Revenue],IMDB4[Year],Formula_Analysis!BA60) -> 1250305771
A61: Braveheart | B61: 34755 | C61: 1995 | D61: 1990s | E61: Color | F61: Biography | G61: English | H61: USA | I61: R | J61: Mhairi Calvey | K61: Mel Gibson | L61: 906 | M61: 1976 | N61: 0 | O61: 17000 | P61: 8.4 | R61: Indiana Jones and the Kingdom of the Crystal Skull | S61: 39808 | T61: 2008 | U61: 2000s | V61: Color | W61: Action | X61: English | Y61: USA | Z61: PG-13 | AA61: Harrison Ford | AB61: Steven Spielberg | AC61: 11000 | AD61: 14959 | AE61: 14000 | AF61: 5000 | AG61: 6.2 | AH61: 470 | AI61: 122 | AJ61: 317011114 | AL61: Justin Zackham | AM61: =AVERAGEIFS(IMDB4[IMDb Score (1-10)],IMDB4[Director Name],Formula_Analysis!AL61) -> 5.6 | AQ61: Robert De Niro | AR61: =SUMIFS(IMDB4[Gross Revenue],IMDB4[Lead Actor],Formula_Analysis!AQ61) -> 2065207594 | BA61: 1994 | BB61: =SUMIFS(IMDB4[Gross Revenue],IMDB4[Year],Formula_Analysis!BA61) -> 3139089602
A62: Princess Mononoke | B62: 35629 | C62: 1997 | D62: 1990s | E62: Color | F62: Adventure | G62: Japanese | H62: Japan | I62: PG-13 | J62: Minnie Driver | K62: Hayao Miyazaki | L62: 893 | M62: 2710 | N62: 6000 | O62: 11000 | P62: 8.4 | R62: The Lord of the Rings: The Fellowship of the Ring | S62: 37201 | T62: 2001 | U62: 2000s | V62: Color | W62: Action | X62: English | Y62: New Zealand | Z62: PG-13 | AA62: Christopher Lee | AB62: Peter Jackson | AC62: 16000 | AD62: 22342 | AE62: 0 | AF62: 21000 | AG62: 8.8 | AH62: 297 | AI62: 171 | AJ62: 313837577 | AL62: Danny DeVito | AM62: =AVERAGEIFS(IMDB4[IMDb Score (1-10)],IMDB4[Director Name],Formula_Analysis!AL62) -> 6.2666667 | AQ62: Philip Seymour Hoffman | AR62: =SUMIFS(IMDB4[Gross Revenue],IMDB4[Lead Actor],Formula_Analysis!AQ62) -> 1027933295 | BA62: 2000 | BB62: =SUMIFS(IMDB4[Gross Revenue],IMDB4[Year],Formula_Analysis!BA62) -> 6986468484
... A107: On the Waterfront | B107: 20026 | C107: 1954 | D107: 1950s | E107: Black and White | F107: Crime | G107: English | H107: USA | I107: Not Rated | J107: Marlon Brando | K107: Elia Kazan | L107: 10000 | M107: 11094 | N107: 603 | O107: 0 | P107: 8.2 | R107: Night at the Museum | S107: 38835 | T107: 2006 | U107: 2000s | V107: Color | W107: Action | X107: English | Y107: USA | Z107: PG | AA107: Robin Williams | AB107: Shawn Levy | AC107: 49000 | AD107: 55486 | AE107: 189 | AF107: 3000 | AG107: 6.4 | AH107: 179 | AI107: 108 | AJ107: 250863268 | AL107: Boaz Yakin | AM107: =AVERAGEIFS(IMDB4[IMDb Score (1-10)],IMDB4[Director Name],Formula_Analysis!AL107) -> 7.0333333 | AQ107: Sylvester Stallone | AR107: =SUMIFS(IMDB4[Gross Revenue],IMDB4[Lead Actor],Formula_Analysis!AQ107) -> 1023650665 | BA107: 1920 | BB107: =SUMIFS(IMDB4[Gross Revenue],IMDB4[Year],Formula_Analysis!BA107) -> 3000000
A108: Trainspotting | B108: 35318 | C108: 1996 | D108: 1990s | E108: Color | F108: Drama | G108: English | H108: UK | I108: R | J108: Kelly Macdonald | K108: Danny Boyle | L108: 2000 | M108: 3559 | N108: 0 | O108: 21000 | P108: 8.2 | R108: Men in Black | S108: 35431 | T108: 1997 | U108: 1990s | V108: Color | W108: Adventure | X108: English | Y108: USA | Z108: PG-13 | AA108: Will Smith | AB108: Barry Sonnenfeld | AC108: 10000 | AD108: 12998 | AE108: 188 | AF108: 0 | AG108: 7.3 | AH108: 175 | AI108: 98 | AJ108: 250147615 | AL108: Glenn Ficarra | AM108: =AVERAGEIFS(IMDB4[IMDb Score (1-10)],IMDB4[Director Name],Formula_Analysis!AL108) -> 6.8666667 | AQ108: Michael Fassbender | AR108: =SUMIFS(IMDB4[Gross Revenue],IMDB4[Lead Actor],Formula_Analysis!AQ108) -> 284199168
A109: Finding Nemo | B109: 37836 | C109: 2003 | D109: 2000s | E109: Color | F109: Adventure | G109: English | H109: USA | I109: G | J109: Alexander Gould | K109: Andrew Stanton | L109: 1000 | M109: 5641 | N109: 475 | O109: 11000 | P109: 8.2 | R109: Harry Potter and the Prisoner of Azkaban | S109: 38045 | T109: 2004 | U109: 2000s | V109: Color | W109: Adventure | X109: English | Y109: UK | Z109: PG | AA109: Daniel Radcliffe | AB109: Alfonso CuarÃ³n | AC109: 11000 | AD109: 33284 | AE109: 0 | AF109: 11000 | AG109: 7.8 | AH109: 274 | AI109: 142 | AJ109: 249358727 | AL109: Ruben Fleischer | AM109: =AVERAGEIFS(IMDB4[IMDb Score (1-10)],IMDB4[Director Name],Formula_Analysis!AL109) -> 6.8333333 | AQ109: Heath Ledger | AR109: =SUMIFS(IMDB4[Gross Revenue],IMDB4[Lead Actor],Formula_Analysis!AQ109) -> 219335451
A110: A Beautiful Mind | B110: 37123 | C110: 2001 | D110: 2000s | E110: Color | F110: Biography | G110: English | H110: USA | I110: PG-13 | J110: Adam Goldberg | K110: Ron Howard | L110: 1000 | M110: 2827 | N110: 2000 | O110: 29000 | P110: 8.2 | R110: Toy Story 2 | S110: 36318 | T110: 1999 | U110: 1990s | V110: Color | W110: Adventure | X110: English | Y110: USA | Z110: G | AA110: Tom Hanks | AB110: John Lasseter | AC110: 15000 | AD110: 21275 | AE110: 487 | AF110: 0 | AG110: 7.9 | AH110: 191 | AI110: 82 | AJ110: 245823397 | AL110: George Clooney | AM110: =AVERAGEIFS(IMDB4[IMDb Score (1-10)],IMDB4[Director Name],Formula_Analysis!AL110) -> 6.675 | AQ110: Eddie Redmayne | AR110: =SUMIFS(IMDB4[Gross Revenue],IMDB4[Lead Actor],Formula_Analysis!AQ110) -> 67183560
A111: The Thing | B111: 30006 | C111: 1982 | D111: 1980s | E111: Color | F111: Horror | G111: English | H111: USA | I111: R | J111: Wilford Brimley | K111: John Carpenter | L111: 957 | M111: 1757 | N111: 0 | O111: 23000 | P111: 8.2 | R111: Transformers: Age of Extinction | S111: 41752 | T111: 2014 | U111: 2010s | V111: Color | W111: Action | X111: English | Y111: USA | Z111: PG-13 | AA111: Bingbing Li | AB111: Michael Bay | AC111: 974 | AD111: 3988 | AE111: 0 | AF111: 56000 | AG111: 5.7 | AH111: 378 | AI111: 165 | AJ111: 245428137 | AL111: Nicolas Winding Refn | AM111: =AVERAGEIFS(IMDB4[IMDb Score (1-10)],IMDB4[Director Name],Formula_Analysis!AL111) -> 6.75 | AQ111: Gabriel Millman | AR111: =SUMIFS(IMDB4[Gross Revenue],IMDB4[Lead Actor],Formula_Analysis!AQ111) -> 14060950
A112: The Secret in Their Eyes | B112: 39979 | C112: 2009 | D112: 2000s | E112: Color | F112: Drama | G112: Spanish | H112: Argentina | I112: R | J112: Ricardo DarÃ­n | K112: Juan JosÃ© Campanella | L112: 827 | M112: 1044 | N112: 195 | O112: 33000 | P112: 8.2 | R112: Cars | S112: 38731 | T112: 2006 | U112: 2000s | V112: Color | W112: Adventure | X112: English | Y112: USA | Z112: G | AA112: John Ratzenberger | AB112: John Lasseter | AC112: 1000 | AD112: 4905 | AE112: 487 | AF112: 0 | AG112: 7.2 | AH112: 256 | AI112: 117 | AJ112: 244052771 | AL112: Barbet Schroeder | AM112: =AVERAGEIFS(IMDB4[IMDb Score (1-10)],IMDB4[Director Name],Formula_Analysis!AL112) -> 6 | AQ112: Steve Buscemi | AR112: =SUMIFS(IMDB4[Gross Revenue],IMDB4[Lead Actor],Formula_Analysis!AQ112) -> 2023386536
A113: The Bridge on the River Kwai | B113: 21087 | C113: 1957 | D113: 1950s | E113: Color | F113: Adventure | G113: English | H113: UK | I113: PG | J113: William Holden | K113: David Lean | L113: 682 | M113: 1035 | N113: 767 | O113: 0 | P113: 8.2 | R113: Bruce Almighty | S113: 37884 | T113: 2003 | U113: 2000s | V113: Color | W113: Comedy | X113: English | Y113: USA | Z113: PG-13 | AA113: Morgan Freeman | AB113: Tom Shadyac | AC113: 11000 | AD113: 21276 | AE113: 293 | AF113: 0 | AG113: 6.7 | AH113: 191 | AI113: 101 | AJ113: 242589580 | AL113: Derek Cianfrance | AM113: =AVERAGEIFS(IMDB4[IMDb Score (1-10)],IMDB4[Director Name],Formula_Analysis!AL113) -> 7.35 | AQ113: Dwayne Johnson | AR113: =SUMIFS(IMDB4[Gross Revenue],IMDB4[Lead Actor],Formula_Analysis!AQ113) -> 1171115915
A114: Pan's Labyrinth | B114: 38834 | C114: 2006 | D114: 2000s | E114: Color | F114: Drama | G114: Spanish | H114: Spain | I114: R | J114: Ivana Baquero | K114: Guillermo del Toro | L114: 634 | M114: 1322 | N114: 0 | O114: 27000 | P114: 8.2 | R114: Raiders of the Lost Ark | S114: 29722 | T114: 1981 | U114: 1980s | V114: Color | W114: Action | X114: English | Y114: USA | Z114: PG | AA114: Harrison Ford | AB114: Steven Spielberg | AC114: 11000 | AD114: 12906 | AE114: 14000 | AF114: 16000 | AG114: 8.5 | AH114: 234 | AI114: 115 | AJ114: 242374454 | AL114: Jay Chandrasekhar | AM114: =AVERAGEIFS(IMDB4[IMDb Score (1-10)],IMDB4[Director Name],Formula_Analysis!AL114) -> 6.025 | AQ114: Nicolas Cage | AR114: =SUMIFS(IMDB4[Gross Revenue],IMDB4[Lead Actor],Formula_Analysis!AQ114) -> 1468672594
A115: Gone with the Wind | B115: 14561 | C115: 1939 | D115: 1930s | E115: Color | F115: Drama | G115: English | H115: USA | I115: G | J115: Hattie McDaniel | K115: Victor Fleming | L115: 503 | M115: 1862 | N115: 149 | O115: 16000 | P115: 8.2 | R115: Twister | S115: 35261 | T115: 1996 | U115: 1990s | V115: Color | W115: Action | X115: English | Y115: USA | Z115: PG-13 | AA115: Philip Seymour Hoffman | AB115: Jan de Bont | AC115: 22000 | AD115: 26239 | AE115: 101 | AF115: 0 | AG115: 6.3 | AH115: 114 | AI115: 113 | AJ115: 241688385 | AL115: Craig Gillespie | AM115: =AVERAGEIFS(IMDB4[IMDb Score (1-10)],IMDB4[Director Name],Formula_Analysis!AL115) -> 6.9333333 | AQ115: Jeff Bridges | AR115: =SUMIFS(IMDB4[Gross Revenue],IMDB4[Lead Actor],Formula_Analysis!AQ115) -> 602882741
A116: Incendies | B116: 40408 | C116: 2010 | D116: 2010s | E116: Color | F116: Drama | G116: French | H116: Canada | I116: R | J116: Lubna Azabal | K116: Denis Villeneuve | L116: 131 | M116: 343 | N116: 777 | O116: 37000 | P116: 8.2 | R116: My Big Fat Greek Wedding | S116: 37466 | T116: 2002 | U116: 2000s | V116: Color | W116: Comedy | X116: English | Y116: USA | Z116: PG | AA116: Nia Vardalos | AB116: Joel Zwick | AC116: 567 | AD116: 1495 | AE116: 38 | AF116: 5000 | AG116: 6.6 | AH116: 168 | AI116: 95 | AJ116: 241437427 | AL116: Ryan Fleck | AM116: =AVERAGEIFS(IMDB4[IMDb Score (1-10)],IMDB4[Director Name],Formula_Analysis!AL116) -> 7.2 | AQ116: Anthony Hopkins | AR116: =SUMIFS(IMDB4[Gross Revenue],IMDB4[Lead Actor],Formula_Analysis!AQ116) -> 780617919
A117: The Act of Killing | B117: 41163 | C117: 2012 | D117: 2010s | E117: Color | F117: Biography | G117: Indonesian | H117: UK | I117: Not Rated | J117: Anwar Congo | K117: Joshua Oppenheimer | L117: 3 | M117: 6 | N117: 50 | O117: 20000 | P117: 8.2 | R117: Maleficent | S117: 41704 | T117: 2014 | U117: 2010s | V117: Color | W117: Action | X117: English | Y117: USA | Z117: PG | AA117: Angelina Jolie Pitt | AB117: Robert Stromberg | AC117: 11000 | AD117: 15516 | AE117: 171 | AF117: 89000 | AG117: 7 | AH117: 401 | AI117: 97 | AJ117: 241407328 | AL117: Henry Bean | AM117: =AVERAGEIFS(IMDB4[IMDb Score (1-10)],IMDB4[Director Name],Formula_Analysis!AL117) -> 7.2 | AQ117: Leonard Nimoy | AR117: =SUMIFS(IMDB4[Gross Revenue],IMDB4[Lead Actor],Formula_Analysis!AQ117) -> 561449216
A118: Pirates of the Caribbean: The Curse of the Black Pearl | B118: 37951 | C118: 2003 | D118: 2000s | E118: Color | F118: Action | G118: English | H118: USA | I118: PG-13 | J118: Johnny Depp | K118: Gore Verbinski | L118: 40000 | M118: 48184 | N118: 563 | O118: 10000 | P118: 8.1 | R118: Pirates of the Caribbean: On Stranger Tides | S118: 40865 | T118: 2011 | U118: 2010s | V118: Color | W118: Action | X118: English | Y118: USA | Z118: PG-13 | AA118: Johnny Depp | AB118: Rob Marshall | AC118: 40000 | AD118: 54083 | AE118: 252 | AF118: 58000 | AG118: 6.7 | AH118: 448 | AI118: 136 | AJ118: 241063875 | AL118: Nick Cassavetes | AM118: =AVERAGEIFS(IMDB4[IMDb Score (1-10)],IMDB4[Director Name],Formula_Analysis!AL118) -> 7.075 | AQ118: Taylor Lautner | AR118: =SUMIFS(IMDB4[Gross Revenue],IMDB4[Lead Actor],Formula_Analysis!AQ118) -> 121747073
A119: Platoon | B119: 31537 | C119: 1986 | D119: 1980s | E119: Color | F119: Drama | G119: English | H119: UK | I119: R | J119: Johnny Depp | K119: Oliver Stone | L119: 40000 | M119: 42028 | N119: 0 | O119: 9000 | P119: 8.1 | R119: Shrek Forever After | S119: 40255 | T119: 2010 | U119: 2010s | V119: Color | W119: Adventure | X119: English | Y119: USA | Z119: PG | AA119: Jon Hamm | AB119: Mike Mitchell | AC119: 4000 | AD119: 4628 | AE119: 31 | AF119: 0 | AG119: 6.4 | AH119: 226 | AI119: 93 | AJ119: 238371987 | AL119: Alex Smith | AM119: =AVERAGEIFS(IMDB4[IMDb Score (1-10)],IMDB4[Director Name],Formula_Analysis!AL119) -> 6.1 | AQ119: Norman Reedus | AR119: =SUMIFS(IMDB4[Gross Revenue],IMDB4[Lead Actor],Formula_Analysis!AQ119) -> 113393959
... A1528: Bloodsport | B1528: 32467 | C1528: 1988 | D1528: 1980s | E1528: Color | F1528: Action | G1528: English | H1528: USA | I1528: R | J1528: Bolo Yeung | K1528: Newt Arnold | L1528: 633 | M1528: 1168 | N1528: 15 | O1528: 0 | P1528: 6.8 | R1528: How Stella Got Her Groove Back | S1528: 35992 | T1528: 1998 | U1528: 1990s | V1528: Color | W1528: Comedy | X1528: English | Y1528: USA | Z1528: R | AA1528: Richard Lawson | AB1528: Kevin Rodney Sullivan | AC1528: 508 | AD1528: 1660 | AE1528: 8 | AF1528: 0 | AG1528: 5.5 | AH1528: 29 | AI1528: 124 | AJ1528: 37672350 | AL1528: Franck Khalfoun | AM1528: =AVERAGEIFS(IMDB4[IMDb Score (1-10)],IMDB4[Director Name],Formula_Analysis!AL1528) -> 6.1 | AQ1528: Naderev Sano | AR1528: =SUMIFS(IMDB4[Gross Revenue],IMDB4[Lead Actor],Formula_Analysis!AQ1528) -> 4914
A1529: Bulworth | B1529: 35878 | C1529: 1998 | D1529: 1990s | E1529: Color | F1529: Comedy | G1529: English | H1529: USA | I1529: R | J1529: Warren Beatty | K1529: Warren Beatty | L1529: 631 | M1529: 1023 | N1529: 631 | O1529: 0 | P1529: 6.8 | R1529: Red Riding Hood | S1529: 40650 | T1529: 2011 | U1529: 2010s | V1529: Color | W1529: Fantasy | X1529: English | Y1529: USA | Z1529: PG-13 | AA1529: Gary Oldman | AB1529: Catherine Hardwicke | AC1529: 10000 | AD1529: 15369 | AE1529: 308 | AF1529: 20000 | AG1529: 5.4 | AH1529: 291 | AI1529: 100 | AJ1529: 37652565 | AL1529: King Vidor | AM1529: =AVERAGEIFS(IMDB4[IMDb Score (1-10)],IMDB4[Director Name],Formula_Analysis!AL1529) -> 6.9
A1530: Superman II | B1530: 29507 | C1530: 1980 | D1530: 1980s | E1530: Color | F1530: Action | G1530: English | H1530: USA | I1530: PG | J1530: Margot Kidder | K1530: Richard Lester | L1530: 593 | M1530: 2908 | N1530: 44 | O1530: 0 | P1530: 6.8 | R1530: Pan's Labyrinth | S1530: 38834 | T1530: 2006 | U1530: 2000s | V1530: Color | W1530: Drama | X1530: Spanish | Y1530: Spain | Z1530: R | AA1530: Ivana Baquero | AB1530: Guillermo del Toro | AC1530: 634 | AD1530: 1322 | AE1530: 0 | AF1530: 27000 | AG1530: 8.2 | AH1530: 406 | AI1530: 112 | AJ1530: 37623143 | AL1530: Robert Townsend | AM1530: =AVERAGEIFS(IMDB4[IMDb Score (1-10)],IMDB4[Director Name],Formula_Analysis!AL1530) -> 7
A1531: Live and Let Die | B1531: 26885 | C1531: 1973 | D1531: 1970s | E1531: Color | F1531: Action | G1531: English | H1531: UK | I1531: PG | J1531: Yaphet Kotto | K1531: Guy Hamilton | L1531: 581 | M1531: 1865 | N1531: 82 | O1531: 0 | P1531: 6.8 | R1531: The Nativity Story | S1531: 39029 | T1531: 2006 | U1531: 2000s | V1531: Color | W1531: Drama | X1531: English | Y1531: USA | Z1531: PG | AA1531: Keisha Castle-Hughes | AB1531: Catherine Hardwicke | AC1531: 446 | AD1531: 966 | AE1531: 308 | AF1531: 0 | AG1531: 6.8 | AH1531: 122 | AI1531: 101 | AJ1531: 37617947 | AL1531: Todd Lincoln | AM1531: =AVERAGEIFS(IMDB4[IMDb Score (1-10)],IMDB4[Director Name],Formula_Analysis!AL1531) -> 4.1
A1532: Fido | B1532: 39014 | C1532: 2006 | D1532: 2000s | E1532: Black and White | F1532: Comedy | G1532: English | H1532: Canada | I1532: R | J1532: Alexia Fast | K1532: Andrew Currie | L1532: 553 | M1532: 786 | N1532: 8 | O1532: 0 | P1532: 6.8 | R1532: First Knight | S1532: 34708 | T1532: 1995 | U1532: 1990s | V1532: Color | W1532: Action | X1532: English | Y1532: USA | Z1532: PG-13 | AA1532: Julia Ormond | AB1532: Jerry Zucker | AC1532: 919 | AD1532: 1695 | AE1532: 109 | AF1532: 0 | AG1532: 5.9 | AH1532: 53 | AI1532: 134 | AJ1532: 37600435 | AL1532: Christopher Scott Cherot | AM1532: =AVERAGEIFS(IMDB4[IMDb Score (1-10)],IMDB4[Director Name],Formula_Analysis!AL1532) -> 6.5
A1533: Young Guns | B1533: 32319 | C1533: 1988 | D1533: 1980s | E1533: Color | F1533: Action | G1533: English | H1533: USA | I1533: R | J1533: Jack Palance | K1533: Christopher Cain | L1533: 549 | M1533: 1747 | N1533: 58 | O1533: 0 | P1533: 6.8 | R1533: Conan the Barbarian | S1533: 30175 | T1533: 1982 | U1533: 1980s | V1533: Color | W1533: Adventure | X1533: English | Y1533: USA | Z1533: R | AA1533: William Smith | AB1533: John Milius | AC1533: 919 | AD1533: 2024 | AE1533: 468 | AF1533: 0 | AG1533: 6.9 | AH1533: 166 | AI1533: 129 | AJ1533: 37567440 | AL1533: R. Balki | AM1533: =AVERAGEIFS(IMDB4[IMDb Score (1-10)],IMDB4[Director Name],Formula_Analysis!AL1533) -> 7.2
A1534: Spider | B1534: 37335 | C1534: 2002 | D1534: 2000s | E1534: Color | F1534: Drama | G1534: English | H1534: Canada | I1534: R | J1534: Miranda Richardson | K1534: David Cronenberg | L1534: 530 | M1534: 1381 | N1534: 0 | O1534: 0 | P1534: 6.8 | R1534: Good Boy! | S1534: 37936 | T1534: 2003 | U1534: 2000s | V1534: Color | W1534: Comedy | X1534: English | Y1534: USA | Z1534: PG | AA1534: Liam Aiken | AB1534: John Hoffman | AC1534: 818 | AD1534: 2164 | AE1534: 9 | AF1534: 309 | AG1534: 5.1 | AH1534: 52 | AI1534: 87 | AJ1534: 37566230 | AL1534: Daniel Stamm | AM1534: =AVERAGEIFS(IMDB4[IMDb Score (1-10)],IMDB4[Director Name],Formula_Analysis!AL1534) -> 5.6
A1535: The American President | B1535: 35063 | C1535: 1995 | D1535: 1990s | E1535: Color | F1535: Comedy | G1535: English | H1535: USA | I1535: PG-13 | J1535: Shawna Waldron | K1535: Rob Reiner | L1535: 524 | M1535: 2668 | N1535: 0 | O1535: 0 | P1535: 6.8 | R1535: In Time | S1535: 40765 | T1535: 2011 | U1535: 2010s | V1535: Color | W1535: Action | X1535: English | Y1535: USA | Z1535: PG-13 | AA1535: Matt Bomer | AB1535: Andrew Niccol | AC1535: 20000 | AD1535: 34011 | AE1535: 487 | AF1535: 52000 | AG1535: 6.7 | AH1535: 360 | AI1535: 109 | AJ1535: 37553932 | AL1535: Wilson Yip | AM1535: =AVERAGEIFS(IMDB4[IMDb Score (1-10)],IMDB4[Director Name],Formula_Analysis!AL1535) -> 7.2
A1536: Liar Liar | B1536: 35693 | C1536: 1997 | D1536: 1990s | E1536: Color | F1536: Comedy | G1536: English | H1536: USA | I1536: PG-13 | J1536: Maura Tierney | K1536: Tom Shadyac | L1536: 509 | M1536: 2070 | N1536: 293 | O1536: 0 | P1536: 6.8 | R1536: Abraham Lincoln: Vampire Hunter | S1536: 41168 | T1536: 2012 | U1536: 2010s | V1536: Color | W1536: Action | X1536: English | Y1536: USA | Z1536: R | AA1536: Rufus Sewell | AB1536: Timur Bekmambetov | AC1536: 3000 | AD1536: 8281 | AE1536: 335 | AF1536: 98000 | AG1536: 5.9 | AH1536: 393 | AI1536: 105 | AJ1536: 37516013 | AL1536: Hal Needham | AM1536: =AVERAGEIFS(IMDB4[IMDb Score (1-10)],IMDB4[Director Name],Formula_Analysis!AL1536) -> 3.5
A1537: High Tension | B1537: 37707 | C1537: 2003 | D1537: 2000s | E1537: Color | F1537: Horror | G1537: French | H1537: France | I1537: Unrated | J1537: CÃ©cile De France | K1537: Alexandre Aja | L1537: 447 | M1537: 923 | N1537: 192 | O1537: 0 | P1537: 6.8 | R1537: Raising Helen | S1537: 38020 | T1537: 2004 | U1537: 2000s | V1537: Color | W1537: Comedy | X1537: English | Y1537: USA | Z1537: PG-13 | AA1537: Amber Valletta | AB1537: Garry Marshall | AC1537: 627 | AD1537: 2052 | AE1537: 0 | AF1537: 718 | AG1537: 6 | AH1537: 93 | AI1537: 119 | AJ1537: 37486138 | AL1537: George Cukor | AM1537: =AVERAGEIFS(IMDB4[IMDb Score (1-10)],IMDB4[Director Name],Formula_Analysis!AL1537) -> 7.9
A1538: The Nativity Story | B1538: 39029 | C1538: 2006 | D1538: 2000s | E1538: Color | F1538: Drama | G1538: English | H1538: USA | I1538: PG | J1538: Keisha Castle-Hughes | K1538: Catherine Hardwicke | L1538: 446 | M1538: 966 | N1538: 308 | O1538: 0 | P1538: 6.8 | R1538: The Back-up Plan | S1538: 40385 | T1538: 2010 | U1538: 2010s | V1538: Color | W1538: Comedy | X1538: English | Y1538: USA | Z1538: PG-13 | AA1538: Danneel Ackles | AB1538: Alan Poul | AC1538: 1000 | AD1538: 3356 | AE1538: 16 | AF1538: 0 | AG1538: 5.3 | AH1538: 148 | AI1538: 104 | AJ1538: 37481242 | AL1538: Dean Israelite | AM1538: =AVERAGEIFS(IMDB4[IMDb Score (1-10)],IMDB4[Director Name],Formula_Analysis!AL1538) -> 6.4
A1539: The Perfect Host | B1539: 40274 | C1539: 2010 | D1539: 2010s | E1539: Color | F1539: Comedy | G1539: English | H1539: USA | I1539: R | J1539: David Hyde Pierce | K1539: Nick Tomnay | L1539: 443 | M1539: 1452 | N1539: 11 | O1539: 0 | P1539: 6.8 | R1539: Invictus | S1539: 39892 | T1539: 2009 | U1539: 2000s | V1539: Color | W1539: Biography | X1539: English | Y1539: USA | Z1539: PG-13 | AA1539: Matt Damon | AB1539: Clint Eastwood | AC1539: 13000 | AD1539: 24458 | AE1539: 16000 | AF1539: 23000 | AG1539: 7.4 | AH1539: 306 | AI1539: 134 | AJ1539: 37479778 | AL1539: Masayuki Ochiai | AM1539: =AVERAGEIFS(IMDB4[IMDb Score (1-10)],IMDB4[Director Name],Formula_Analysis!AL1539) -> 5.2
A1540: Babe | B1540: 34858 | C1540: 1995 | D1540: 1990s | E1540: Color | F1540: Comedy | G1540: English | H1540: Australia | I1540: G | J1540: Miriam Margolyes | K1540: Chris Noonan | L1540: 405 | M1540: 1185 | N1540: 108 | O1540: 5000 | P1540: 6.8 | R1540: Jeepers Creepers | S1540: 37063 | T1540: 2001 | U1540: 2000s | V1540: Color | W1540: Horror | X1540: English | Y1540: Germany | Z1540: R | AA1540: Eileen Brennan | AB1540: Victor Salva | AC1540: 1000 | AD1540: 1982 | AE1540: 108 | AF1540: 0 | AG1540: 6.1 | AH1540: 190 | AI1540: 90 | AJ1540: 37470017 | AL1540: Andy Cadiff | AM1540: =AVERAGEIFS(IMDB4[IMDb Score (1-10)],IMDB4[Director Name],Formula_Analysis!AL1540) -> 6.1
... A1766: Contagion | B1766: 40856 | C1766: 2011 | D1766: 2010s | E1766: Color | F1766: Drama | G1766: English | H1766: USA | I1766: PG-13 | J1766: Matt Damon | K1766: Steven Soderbergh | L1766: 13000 | M1766: 13634 | N1766: 0 | O1766: 42000 | P1766: 6.6 | R1766: Mirrors | S1766: 39659 | T1766: 2008 | U1766: 2000s | V1766: Color | W1766: Horror | X1766: English | Y1766: USA | Z1766: R | AA1766: Jason Flemyng | AB1766: Alexandre Aja | AC1766: 1000 | AD1766: 3185 | AE1766: 192 | AF1766: 5000 | AG1766: 6.2 | AH1766: 208 | AI1766: 112 | AJ1766: 30691439 | AL1766: Dena Seidel | AM1766: =AVERAGEIFS(IMDB4[IMDb Score (1-10)],IMDB4[Director Name],Formula_Analysis!AL1766) -> 7
A1767: Tears of the Sun | B1767: 37811 | C1767: 2003 | D1767: 2000s | E1767: Color | F1767: Action | G1767: English | H1767: USA | I1767: R | J1767: Bruce Willis | K1767: Antoine Fuqua | L1767: 13000 | M1767: 16580 | N1767: 845 | O1767: 0 | P1767: 6.6 | R1767: 3 Days to Kill | S1767: 41815 | T1767: 2014 | U1767: 2010s | V1767: Color | W1767: Action | X1767: English | Y1767: USA | Z1767: PG-13 | AA1767: Connie Nielsen | AB1767: McG | AC1767: 933 | AD1767: 1286 | AE1767: 368 | AF1767: 10000 | AG1767: 6.2 | AH1767: 211 | AI1767: 123 | AJ1767: 30688364
A1768: Bandits | B1768: 37067 | C1768: 2001 | D1768: 2000s | E1768: Color | F1768: Comedy | G1768: English | H1768: USA | I1768: PG-13 | J1768: Bruce Willis | K1768: Barry Levinson | L1768: 13000 | M1768: 13934 | N1768: 272 | O1768: 0 | P1768: 6.6 | R1768: Predator 2 | S1768: 33062 | T1768: 1990 | U1768: 1990s | V1768: Color | W1768: Action | X1768: English | Y1768: USA | Z1768: R | AA1768: Adam Baldwin | AB1768: Stephen Hopkins | AC1768: 2000 | AD1768: 4722 | AE1768: 81 | AF1768: 0 | AG1768: 6.2 | AH1768: 119 | AI1768: 103 | AJ1768: 30669413
A1769: 16 Blocks | B1769: 39029 | C1769: 2006 | D1769: 2000s | E1769: Color | F1769: Action | G1769: English | H1769: Germany | I1769: PG-13 | J1769: Bruce Willis | K1769: Richard Donner | L1769: 13000 | M1769: 15053 | N1769: 503 | O1769: 0 | P1769: 6.6 | R1769: Delivery Man | S1769: 41371 | T1769: 2013 | U1769: 2010s | V1769: Color | W1769: Comedy | X1769: English | Y1769: USA | Z1769: PG-13 | AA1769: Jack Reynor | AB1769: Ken Scott | AC1769: 390 | AD1769: 1006 | AE1769: 31 | AF1769: 0 | AG1769: 6.4 | AH1769: 168 | AI1769: 105 | AJ1769: 30659817
A1770: Titan A.E. | B1770: 36636 | C1770: 2000 | D1770: 2000s | E1770: Color | F1770: Action | G1770: English | H1770: USA | I1770: PG | J1770: Matt Damon | K1770: Don Bluth | L1770: 13000 | M1770: 15857 | N1770: 383 | O1770: 0 | P1770: 6.6 | R1770: Dogma | S1770: 36304 | T1770: 1999 | U1770: 1990s | V1770: Color | W1770: Adventure | X1770: English | Y1770: USA | Z1770: R | AA1770: Matt Damon | AB1770: Kevin Smith | AC1770: 13000 | AD1770: 16693 | AE1770: 0 | AF1770: 10000 | AG1770: 7.4 | AH1770: 206 | AI1770: 130 | AJ1770: 30651422
A1771: EuroTrip | B1771: 38252 | C1771: 2004 | D1771: 2000s | E1771: Color | F1771: Comedy | G1771: English | H1771: USA | I1771: R | J1771: Matt Damon | K1771: Jeff Schaffer | L1771: 13000 | M1771: 14180 | N1771: 17 | O1771: 0 | P1771: 6.6 | R1771: Superstar | S1771: 36433 | T1771: 1999 | U1771: 1990s | V1771: Color | W1771: Comedy | X1771: English | Y1771: USA | Z1771: PG-13 | AA1771: Will Ferrell | AB1771: Bruce McCulloch | AC1771: 8000 | AD1771: 10792 | AE1771: 54 | AF1771: 2000 | AG1771: 5 | AH1771: 43 | AI1771: 81 | AJ1771: 30628981
A1772: The Man Who Knew Too Little | B1772: 35567 | C1772: 1997 | D1772: 1990s | E1772: Color | F1772: Action | G1772: English | H1772: USA | I1772: PG | J1772: Bill Murray | K1772: Jon Amiel | L1772: 13000 | M1772: 15183 | N1772: 36 | O1772: 0 | P1772: 6.6 | R1772: Deliver Us from Evil | S1772: 41668 | T1772: 2014 | U1772: 2010s | V1772: Color | W1772: Horror | X1772: English | Y1772: USA | Z1772: R | AA1772: Olivia Munn | AB1772: Scott Derrickson | AC1772: 2000 | AD1772: 5697 | AE1772: 301 | AF1772: 18000 | AG1772: 6.2 | AH1772: 242 | AI1772: 118 | AJ1772: 30523568
A1773: Promised Land | B1773: 41253 | C1773: 2012 | D1773: 2010s | E1773: Color | F1773: Drama | G1773: English | H1773: USA | I1773: R | J1773: Matt Damon | K1773: Gus Van Sant | L1773: 13000 | M1773: 14544 | N1773: 835 | O1773: 10000 | P1773: 6.6 | R1773: Get on Up | S1773: 41746 | T1773: 2014 | U1773: 2010s | V1773: Color | W1773: Biography | X1773: English | Y1773: USA | Z1773: PG-13 | AA1773: Tika Sumpter | AB1773: Tate Taylor | AC1773: 521 | AD1773: 2060 | AE1773: 150 | AF1773: 11000 | AG1773: 6.9 | AH1773: 165 | AI1773: 139 | AJ1773: 30513940
A1774: Star Trek III: The Search for Spock | B1774: 30967 | C1774: 1984 | D1774: 1980s | E1774: Color | F1774: Action | G1774: English | H1774: USA | I1774: PG | J1774: Leonard Nimoy | K1774: Leonard Nimoy | L1774: 12000 | M1774: 14762 | N1774: 12000 | O1774: 0 | P1774: 6.6 | R1774: Open Water | S1774: 37892 | T1774: 2003 | U1774: 2000s | V1774: Color | W1774: Adventure | X1774: English | Y1774: USA | Z1774: R | AA1774: Blanchard Ryan | AB1774: Chris Kentis | AC1774: 48 | AD1774: 67 | AE1774: 9 | AF1774: 0 | AG1774: 5.7 | AH1774: 235 | AI1774: 79 | AJ1774: 30500882
A1775: Monster House | B1775: 38771 | C1775: 2006 | D1775: 2000s | E1775: Color | F1775: Animation | G1775: English | H1775: USA | I1775: PG | J1775: Steve Buscemi | K1775: Gil Kenan | L1775: 12000 | M1775: 17299 | N1775: 27 | O1775: 0 | P1775: 6.6 | R1775: Sgt. Bilko | S1775: 35346 | T1775: 1996 | U1775: 1990s | V1775: Color | W1775: Comedy | X1775: English | Y1775: USA | Z1775: PG | AA1775: Austin Pendleton | AB1775: Jonathan Lynn | AC1775: 592 | AD1775: 2176 | AE1775: 36 | AF1775: 478 | AG1775: 5.7 | AH1775: 23 | AI1775: 93 | AJ1775: 30400000
A1776: The Weather Man | B1776: 38402 | C1776: 2005 | D1776: 2000s | E1776: Color | F1776: Comedy | G1776: English | H1776: USA | I1776: R | J1776: Nicolas Cage | K1776: Gore Verbinski | L1776: 12000 | M1776: 13156 | N1776: 563 | O1776: 0 | P1776: 6.6 | R1776: Yentl | S1776: 30619 | T1776: 1983 | U1776: 1980s | V1776: Color | W1776: Drama | X1776: English | Y1776: UK | Z1776: PG | AA1776: Miriam Margolyes | AB1776: Barbra Streisand | AC1776: 405 | AD1776: 914 | AE1776: 0 | AF1776: 0 | AG1776: 6.6 | AH1776: 16 | AI1776: 132 | AJ1776: 30400000
A1777: White Squall | B1777: 35343 | C1777: 1996 | D1777: 1990s | E1777: Color | F1777: Adventure | G1777: English | H1777: USA | I1777: PG-13 | J1777: Jeff Bridges | K1777: Ridley Scott | L1777: 12000 | M1777: 16237 | N1777: 0 | O1777: 911 | P1777: 6.6 | R1777: A Night at the Roxbury | S1777: 35997 | T1777: 1998 | U1777: 1990s | V1777: Color | W1777: Comedy | X1777: English | Y1777: USA | Z1777: PG-13 | AA1777: Will Ferrell | AB1777: John Fortenberry | AC1777: 8000 | AD1777: 9271 | AE1777: 12 | AF1777: 0 | AG1777: 6.2 | AH1777: 63 | AI1777: 82 | AJ1777: 30324946
A1778: What Lies Beneath | B1778: 36621 | C1778: 2000 | D1778: 2000s | E1778: Color | F1778: Drama | G1778: English | H1778: USA | I1778: PG-13 | J1778: Harrison Ford | K1778: Robert Zemeckis | L1778: 11000 | M1778: 12890 | N1778: 0 | O1778: 0 | P1778: 6.6 | R1778: Queen of the Damned | S1778: 37405 | T1778: 2002 | U1778: 2000s | V1778: Color | W1778: Drama | X1778: English | Y1778: USA | Z1778: R | AA1778: Aaliyah | AB1778: Michael Rymer | AC1778: 775 | AD1778: 3001 | AE1778: 48 | AF1778: 0 | AG1778: 5.2 | AH1778: 137 | AI1778: 101 | AJ1778: 30307804
...

Sheet Pivot_Analysis
B3: Count of Movies by Genre | E3: Count of Movies by Country | H3: Average IMDb Score by Genre | L3: Total Gross Revenue by Release Year | P3: TOTAL PROFIT BY DIRECTOR NAME | T3: TOP 5 LEAD ACTORS BY TOTAL PROFIT | AV3: PROFIT BY GENRE
B5: Row Labels | C5: Count of Title | E5: Row Labels | F5: Count of Title | H5: Row Labels | I5: Average of IMDb Score (1-10) | L5: Row Labels | M5: Sum of Gross Revenue | P5: Row Labels | Q5: Sum of Profit | T5: Row Labels | U5: Sum of Profit | AV5: Row Labels | AW5: Sum of Profit
B6: Family | C6: 3 | E6: Indonesia | F6: 1 | H6: Comedy | I6: 6.1705709 | L6: 1920 | M6: 3000000 | P6: Steven Spielberg | Q6: 2573539924 | T6: Bradley Cooper | U6: 1005369595 | AV6: Adventure | AW6: 6044906402
B7: Fantasy | C7: 35 | E7: West Germany | F7: 1 | H7: Fantasy | I7: 6.2342857 | L7: 1927 | M7: 26435 | P7: George Lucas | Q7: 1386641480 | T7: Tom Cruise | U7: 1135788356 | AV7: Action | AW7: 4593270249
B8: Documentary | C8: 43 | E8: Sweden | F8: 1 | H8: Action | I8: 6.2814444 | L8: 1933 | M8: 2300000 | P8: James Cameron | Q8: 1199625910 | T8: Jennifer Lawrence | U8: 1208720937 | AV8: Horror | AW8: 3089110908
B9: Animation | C9: 45 | E9: Poland | F9: 1 | H9: Family | I9: 6.5 | L9: 1935 | M9: 3000000 | P9: Chris Columbus | Q9: 941707624 | T9: Tom Hanks | U9: 1492647092 | AV9: Biography | AW9: 2336513401
B10: Biography | C10: 205 | E10: Aruba | F10: 1 | H10: Adventure | I10: 6.5558011 | L10: 1936 | M10: 163245 | P10: Peter Jackson | Q10: 899883917 | T10: Harrison Ford | U10: 2092779163 | AV10: Comedy | AW10: 2318536490
B11: Crime | C11: 252 | E11: Colombia | F11: 1 | H11: Animation | I11: 6.7622222 | L11: 1937 | M11: 184925485 | P11: Christopher Nolan | Q11: 791696692 | T11: Grand Total | U11: 6935305143 | AV11: Animation | AW11: 1339944545
B12: Adventure | C12: 362 | E12: Afghanistan | F12: 1 | H12: Drama | I12: 6.8261905 | L12: 1939 | M12: 220857890 | P12: Francis Lawrence | Q12: 755501971 | AV12: Fantasy | AW12: 813595199
B13: Drama | C13: 672 | E13: Georgia | F13: 1 | H13: Crime | I13: 6.9376984 | L13: 1940 | M13: 160700000 | P13: Michael Bay | Q13: 731621093 | AV13: Drama | AW13: 795469697
B14: Action | C14: 900 | E14: New Line | F14: 1 | H14: Documentary | I14: 6.9511628 | L14: 1946 | M14: 44050000 | P14: Jay Roach | Q14: 642524555 | AV14: Family | AW14: 402981433
B15: Comedy | C15: 1016 | E15: Finland | F15: 1 | H15: Biography | I15: 7.1502439 | L15: 1947 | M15: 7927 | P15: Tim Burton | Q15: 610078534 | T15: TOP 5 DIRECTORS BY TOTAL GROSS | AV15: Mystery | AW15: 348498819
B16: Grand Total | C16: 3533 | E16: Official site | F16: 1 | H16: Grand Total | I16: 6.4924993 | L16: 1948 | M16: 2956000 | P16: Joss Whedon | Q16: 597607081 | AV16: Musical | AW16: 177789000
E17: Chile | F17: 1 | L17: 1950 | M17: 8000000 | P17: Todd Phillips | Q17: 581756030 | T17: Row Labels | U17: Sum of Gross Revenue | AV17: Documentary | AW17: 173283731
E18: Peru | F18: 1 | L18: 1952 | M18: 36000000 | P18: Clint Eastwood | Q18: 575721100 | T18: Steven Spielberg | U18: 4061440794 | AV18: Western | AW18: 39613768
E19: Iceland | F19: 2 | L19: 1953 | M19: 41000000 | P19: Robert Zemeckis | Q19: 549309108 | T19: Michael Bay | U19: 2142621093 | AV19: Sci-Fi | AW19: 14224725
E20: Belgium | F20: 2 | L20: 1954 | M20: 9869061 | P20: Andrew Adamson | Q20: 522446920 | T20: Peter Jackson | U20: 2112883917 | AV20: Thriller | AW20: -1685461
E21: Taiwan | F21: 2 | L21: 1957 | M21: 27200000 | P21: Sam Raimi | Q21: 508458479 | T21: James Cameron | U21: 1948125910 | AV21: Romance | AW21: -57555984
E22: Hungary | F22: 2 | L22: 1959 | M22: 25000000 | P22: Colin Trevorrow | Q22: 505435063 | T22: Christopher Nolan | U22: 1787696692 | AV22: Crime | AW22: -2414914531
E23: Romania | F23: 2 | L23: 1961 | M23: 43650000 | P23: John Lasseter | Q23: 475915953 | T23: Grand Total | U23: 12052768406 | AV23: Grand Total | AW23: 20013582391
E24: Argentina | F24: 3 | L24: 1962 | M24: 22067035 | P24: Pierre Coffin | Q24: 474551280
E25: Russia | F25: 3 | L25: 1963 | M25: 128850000 | P25: Pete Docter | Q25: 474341341
E26: Czech Republic | F26: 3 | L26: 1964 | M26: 229427443 | P26: Phil Lord | Q26: 460690377
E27: South Africa | F27: 3 | L27: 1965 | M27: 346551159 | P27: Garry Marshall | Q27: 416336386 | T27: PROFIT BY GENRE
E28: Israel | F28: 3 | L28: 1967 | M28: 43100000 | P28: Tom Shadyac | Q28: 413339768
E29: Netherlands | F29: 3 | L29: 1968 | M29: 73515371 | P29: Steven Soderbergh | Q29: 405375226 | T29: Row Labels | U29: Sum of Profit
E30: Iran | F30: 4 | L30: 1969 | M30: 125135793 | P30: Jon Favreau | Q30: 394091265 | T30: Adventure | U30: 6044906402 | AN30: Row Labels | AO30: Average of Profit
E31: Norway | F31: 4 | L31: 1970 | M31: 41800000 | P31: Roger Allers | Q31: 377087335 | T31: Action | U31: 4593270249 | AN31: 1920 | AO31: 2900000
E32: Thailand | F32: 4 | L32: 1971 | M32: 108988231 | P32: M. Night Shyamalan | Q32: 368021716 | T32: Biography | U32: 2336513401 | AN32: 1927 | AO32: -5973565
E33: Brazil | F33: 5 | L33: 1972 | M33: 135002435 | P33: Gary Ross | Q33: 363146700 | T33: Comedy | U33: 2318536490 | AN33: 1933 | AO33: 1861000
E34: Ireland | F34: 7 | L34: 1973 | M34: 310032645 | P34: Shawn Levy | Q34: 361950988 | T34: Animation | U34: 1339944545 | AN34: 1935 | AO34: 2391000
E35: Italy | F35: 8 | L35: 1974 | M35: 323652600 | P35: Dennis Dugan | Q35: 341781972 | T35: Fantasy | U35: 813595199 | AN35: 1936 | AO35: -1336755
E36: South Korea | F36: 8 | L36: 1975 | M36: 373229197 | P36: Quentin Tarantino | Q36: 323939594 | T36: Drama | U36: 795469697 | AN36: 1937 | AO36: 182925485
E37: Denmark | F37: 9 | L37: 1976 | M37: 142235247 | P37: Carlos Saldanha | Q37: 304057871 | T37: Family | U37: 402981433 | AN37: 1939 | AO37: 107040445
E38: New Zealand | F38: 9 | L38: 1977 | M38: 727035665 | P38: Leonard Nimoy | Q38: 300894092 | T38: Documentary | U38: 173283731 | AN38: 1940 | AO38: 77910000
E39: Mexico | F39: 10 | L39: 1978 | M39: 392740394 | P39: David O. Russell | Q39: 297549751 | T39: Crime | U39: -2414914531 | AN39: 1946 | AO39: 16975000
E40: India | F40: 12 | L40: 1979 | M40: 289500000 | P40: Ron Howard | Q40: 294979817 | T40: Grand Total | U40: 16403586616 | AN40: 1947 | AO40: -2292073
E41: Hong Kong | F41: 13 | L41: 1980 | M41: 732282001 | P41: Tim Story | Q41: 294866200 | T41: Row Labels | U41: Count of Title | AN41: 1948 | AO41: -744000
E42: China | F42: 14 | L42: 1981 | M42: 667620899 | P42: Ivan Reitman | Q42: 293858920 | T42: Flop | U42: 1717 | AN42: 1950 | AO42: 4231215
E43: Japan | F43: 15 | L43: 1982 | M43: 995050557 | P43: Irvin Kershner | Q43: 291658751 | T43: Hit | U43: 1816 | AN43: 1952 | AO43: 32000000
E44: Spain | F44: 19 | L44: 1983 | M44: 812725409 | P44: Francis Ford Coppola | Q44: 288360377 | T44: Grand Total | U44: 3533 | AN44: 1953 | AO44: 17895000
E45: Australia | F45: 36 | L45: 1984 | M45: 1191200771 | P45: Sydney Pollack | Q45: 287218684 | AN45: 1954 | AO45: 3479530.5
E46: Canada | F46: 56 | L46: 1985 | M46: 825647012 | P46: Judd Apatow | Q46: 286323538 | AN46: 1957 | AO46: 24200000
E47: Germany | F47: 73 | L47: 1986 | M47: 1066237745 | P47: James Wan | Q47: 280625354 | AN47: 1959 | AO47: 22116152
E48: France | F48: 101 | L48: 1987 | M48: 1215008641 | P48: Richard Marquand | Q48: 276625409 | T48: Average Rating by Movie Length | AN48: 1961 | AO48: 37650000
E49: UK | F49: 298 | L49: 1988 | M49: 1136949138 | P49: Adam Shankman | Q49: 272071855 | AN49: 1962 | AO49: 2983517.5 | AR49: Count of Genre | AS49: Column Labels
E50: USA | F50: 2787 | L50: 1989 | M50: 1600916700 | P50: Alfonso CuarÃ³n | Q50: 264352439 | T50: Row Labels | U50: Average of IMDb Score (1-10) | AN50: 1963 | AO50: 28778333 | AR50: Row Labels | AS50: USA | AT50: UK | AU50: France | AV50: Germany | AW50: Canada | AX50: Grand Total
E51: Grand Total | F51: 3533 | L51: 1990 | M51: 2069948656 | P51: Kyle Balda | Q51: 262029560 | T51: Short | U51: 6.0207317 | AN51: 1964 | AO51: 33751240 | AR51: Action | AS51: 702 | AT51: 69 | AU51: 27 | AV51: 24 | AW51: 10 | AX51: 832
L52: 1991 | M52: 1615335050 | P52: Gore Verbinski | Q52: 258600995 | T52: Medium | U52: 6.3558758 | AN52: 1965 | AO52: 58910232 | AR52: Adventure | AS52: 285 | AT52: 37 | AU52: 8 | AV52: 7 | AW52: 5 | AX52: 342
L53: 1992 | M53: 2106548635 | P53: Joel Zwick | Q53: 258551983 | T53: Long | U53: 7.0702765 | AN53: 1967 | AO53: 33600000 | AR53: Animation | AS53: 37 | AT53: 2 | AU53: 3 | AV53: 1 | AX53: 43
L54: 1993 | M54: 2044795249 | P54: Chris Buck | Q54: 250736600 | T54: Grand Total | U54: 6.4924993 | AN54: 1968 | AO54: 25757686 | AR54: Biography | AS54: 137 | AT54: 42 | AU54: 7 | AV54: 6 | AW54: 3 | AX54: 195
L55: 1994 | M55: 3139089602 | P55: George Roy Hill | Q55: 250408900 | AN55: 1969 | AO55: 36845264 | AR55: Comedy | AS55: 865 | AT55: 58 | AU55: 22 | AV55: 18 | AW55: 20 | AX55: 983
L56: 1995 | M56: 3074194875 | P56: Tyler Perry | Q56: 249337748 | AN56: 1970 | AO56: -2425000 | AR56: Crime | AS56: 199 | AT56: 21 | AU56: 6 | AV56: 8 | AW56: 2 | AX56: 236
L57: 1996 | M57: 3859094317 | P57: John Lee Hancock | Q57: 246253540 | AN57: 1971 | AO57: 23065308 | AR57: Documentary | AS57: 33 | AT57: 3 | AU57: 3 | AW57: 1 | AX57: 40
L58: 1997 | M58: 4857108453 | P58: Paul Feig | Q58: 243802481 | T58: Ratings By Country | AN58: 1972 | AO58: 64496218 | AR58: Drama | AS58: 497 | AT58: 65 | AU58: 25 | AV58: 9 | AW58: 12 | AX58: 608
L59: 1998 | M59: 4771750543 | P59: Jeff Tremaine | Q59: 243471008 | T59: Row Labels | U59: Count of Rating Category | AN59: 1973 | AO59: 74063911 | AR59: Family | AS59: 3 | AX59: 3
L60: 1999 | M60: 5942436240 | P60: Peter Segal | Q60: 242219624 | T60: USA | U60: 2787 | AN60: 1974 | AO60: 58350520 | AR60: Fantasy | AS60: 29 | AT60: 1 | AW60: 3 | AX60: 33
L61: 2000 | M61: 6682287759 | P61: F. Gary Gray | Q61: 241423809 | T61: UK | U61: 298 | AN61: 1975 | AO61: 120199874 | AR61: Grand Total | AS61: 2787 | AT61: 298 | AU61: 101 | AV61: 73 | AW61: 56 | AX61: 3315
L62: 2001 | M62: 7439339778 | P62: Raja Gosnell | Q62: 234162220 | T62: France | U62: 101 | AN62: 1976 | AO62: 66137624
L63: 2002 | M63: 8503333397 | P63: David Slade | Q63: 232581075 | T63: Germany | U63: 73 | AN63: 1977 | AO63: 1.0727247e+08
L64: 2003 | M64: 7421668326 | P64: Andy Tennant | Q64: 228029178 | T64: Canada | U64: 56 | AN64: 1978 | AO64: 55348079
L65: 2004 | M65: 7491326933 | P65: Adrian Lyne | Q65: 226033012 | T65: Grand Total | U65: 3315 | AN65: 1979 | AO65: 34500000
L66: 2005 | M66: 7239300151 | P66: Seth Gordon | Q66: 222119868 | AN66: 1980 | AO66: 40731833
L67: 2006 | M67: 7247788337 | P67: Anne Fletcher | Q67: 220630465 | AN67: 1981 | AO67: 34865778
L68: 2007 | M68: 6987537950 | P68: Paul Greengrass | Q68: 220551025 | AN68: 1982 | AO68: 82385056
L69: 2008 | M69: 8221016847 | P69: Bobby Farrelly | Q69: 216581384 | AN69: 1983 | AO69: 47477117
L70: 2009 | M70: 9035701219 | P70: Mel Brooks | Q70: 215819483 | AN70: 1984 | AO70: 47694487
L71: 2010 | M71: 8571691678 | P71: Lee Unkrich | Q71: 214984497 | AN71: 1985 | AO71: 45241653
L72: 2011 | M72: 8082224486 | P72: Ethan Coen | Q72: 214740662 | AN72: 1986 | AO72: 34698226
L73: 2012 | M73: 9582218639 | P73: Victor Fleming | Q73: 214080890 | AN73: 1987 | AO73: 26591955
L74: 2013 | M74: 9643564664 | P74: David Fincher | Q74: 213904524 | AN74: 1988 | AO74: -13786034 | AR74: Row Labels | AS74: Average of Profit
L75: 2014 | M75: 9654117046 | P75: Jason Reitman | Q75: 212760971 | AN75: 1989 | AO75: 32776023 | AR75: 1937 | AS75: 182925485
L76: 2015 | M76: 8308542425 | P76: Rob Reiner | Q76: 211997333 | AN76: 1990 | AO76: 48641910 | AR76: 1975 | AS76: 120199874
L77: Grand Total | M77: 178461169386 | P77: Mike Mitchell | Q77: 208950437 | AN77: 1991 | AO77: 27845402 | AR77: 1977 | AS77: 1.0727247e+08
P78: Rawson Marshall Thurber | Q78: 207693043 | AN78: 1992 | AO78: 39348176 | AR78: 1939 | AS78: 107040445
P79: Nancy Meyers | Q79: 203599150 | AN79: 1993 | AO79: 23873228 | AR79: 1982 | AS79: 82385056
P80: Peyton Reed | Q80: 202908514 | AN80: 1994 | AO80: 30960762 | AR80: 1940 | AS80: 77910000
P81: Robert Wise | Q81: 202314286 | AN81: 1995 | AO81: 13382877 | AR81: 1973 | AS81: 74063911
P82: Tom Hooper | Q82: 202020360 | AN82: 1996 | AO82: 9405761.7 | AR82: 1976 | AS82: 66137624
P83: Tim Hill | Q83: 199921863 | AN83: 1997 | AO83: -13896215 | AR83: 1972 | AS83: 64496218
P84: John G. Avildsen | Q84: 199075247 | AN84: 1998 | AO84: -619219.46 | AR84: 1965 | AS84: 58910232
P85: Shane Black | Q85: 198228109 | AN85: 1999 | AO85: -1298117.6 | AR85: Grand Total | AS85: 87377996
P86: Barry Levinson | Q86: 194709246 | AN86: 2000 | AO86: 7836255
P87: Robert Rodriguez | Q87: 194211796 | AN87: 2001 | AO87: 5298528.1
P88: David Yates | Q88: 193957846 | AN88: 2002 | AO88: 12103808
P89: Barry Sonnenfeld | Q89: 192924214 | AN89: 2003 | AO89: 12808872 | AR89: Row Labels | AS89: Count of Title
P90: Jerry Zucker | Q90: 186838964 | AN90: 2004 | AO90: -7144658.7 | AR90: Average | AS90: 2022
P91: Seth MacFarlane | Q91: 184501865 | AN91: 2005 | AO91: -35715576 | AR91: Good | AS91: 1042
P92: Andy Fickman | Q92: 183433732 | AN92: 2006 | AO92: -66897520 | AR92: Poor | AS92: 265
P93: Bill Condon | Q93: 182996112 | AN93: 2007 | AO93: 9209985.6 | AR93: Excellent | AS93: 204
P94: William Cottrell | Q94: 182925485 | AN94: 2008 | AO94: 1886539.8 | AR94: Grand Total | AS94: 3533
P95: Adam McKay | Q95: 182449691 | AN95: 2009 | AO95: 10574768
P96: Chris Miller | Q96: 179941412 | AN96: 2010 | AO96: 3570662.6 | AR96: Row Labels | AS96: Count of Title
P97: Chris Wedge | Q97: 178102714 | AN97: 2011 | AO97: 5065881.7 | AR97: Average | AS97: 2150
P98: John Singleton | Q98: 175714434 | AN98: 2012 | AO98: 15925396 | AR98: Good | AS98: 1066
P99: Betty Thomas | Q99: 174410970 | AN99: 2013 | AO99: 10864864 | AR99: Poor | AS99: 298
P100: Chris Weitz | Q100: 173200378 | AN100: 2014 | AO100: 18288174 | AR100: Excellent | AS100: 212
P101: David Frankel | Q101: 172624584 | AN101: 2015 | AO101: 17235431 | AR101: Grand Total | AS101: 3726
P102: Sam Mendes | Q102: 171503349 | AN102: Grand Total | AO102: 4642962.5
P103: Alexander Payne | Q103: 169630386
...

Sheet Home

Sheet Insights
C5: INSIGHTS
C8: High-profit genres drive most revenue.
C9: Many movies fail; the industry is high risk.
C10: Bigger budgets often profit more, but not always.
C11: Profit trends fluctuate over years.
C12: Star actors boost box-office revenue.
C13: Medium/long movies get slightly higher ratings.
C14: Most movies earn average ratings; excellence is rare.
